Workbook
Name AWP_ACTIVITES: REF_AWP!$A$2:$A$73
Name AWP_CAT_Commandes_et_Approvisionnement: REF_AWP!$C$151:$C$155
Name AWP_CAT_Coordination_et_Gouvernance: REF_AWP!$H$151:$H$153
Name AWP_CAT_Distribution_et_Livraison: REF_AWP!$E$151:$E$154
Name AWP_CAT_Donnees_et_Reporting: REF_AWP!$F$151:$F$154
Name AWP_CAT_Formation_et_Renforcement_de_Capacites: REF_AWP!$I$151:$I$152
Name AWP_CAT_Gestion_de_Projet: REF_AWP!$J$151:$J$153
Name AWP_CAT_Gestion_de_Stocks: REF_AWP!$D$151:$D$155
Name AWP_CAT_Produits_Specifiques: REF_AWP!$K$151:$K$152
Name AWP_CAT_Quantification_et_Prevision: REF_AWP!$B$151:$B$153
Name AWP_CAT_Systemes_d_Information: REF_AWP!$G$151:$G$155
Name AWP_CATEGORIES: REF_AWP!$A$101:$A$136
Name AWP_T_1_1_1: REF_AWP!$E$2:$E$5
Name AWP_T_1_1_10: REF_AWP!$M$2
Name AWP_T_1_1_11: REF_AWP!$N$2:$N$5
Name AWP_T_1_1_2: REF_AWP!$F$2:$F$3
Name AWP_T_1_1_3: REF_AWP!$G$2
Name AWP_T_1_1_4: REF_AWP!$H$2
Name AWP_T_1_1_5: REF_AWP!$I$2:$I$3
Name AWP_T_1_1_6: REF_AWP!$J$2:$J$3
Name AWP_T_1_1_7: REF_AWP!$K$2
Name AWP_T_1_1_9: REF_AWP!$L$2
Name AWP_T_1_10_1: REF_AWP!$AL$2
Name AWP_T_1_10_2: REF_AWP!$AM$2
Name AWP_T_1_10_3: REF_AWP!$AN$2
Name AWP_T_1_11_1: REF_AWP!$AO$2:$AO$14
Name AWP_T_1_11_2: REF_AWP!$AP$2:$AP$4
Name AWP_T_1_11_3: REF_AWP!$AQ$2:$AQ$5
Name AWP_T_1_11_4: REF_AWP!$AR$2:$AR$9
Name AWP_T_1_11_5: REF_AWP!$AS$2:$AS$8
Name AWP_T_1_11_6: REF_AWP!$AT$2:$AT$14
Name AWP_T_1_2_1: REF_AWP!$O$2:$O$4
Name AWP_T_1_2_2: REF_AWP!$P$2
Name AWP_T_1_2_3: REF_AWP!$Q$2
Name AWP_T_1_3_1: REF_AWP!$R$2:$R$5
Name AWP_T_1_3_2: REF_AWP!$S$2:$S$9
Name AWP_T_1_4_1: REF_AWP!$T$2:$T$5
Name AWP_T_1_5_1: REF_AWP!$U$2
Name AWP_T_1_7_1: REF_AWP!$V$2:$V$3
Name AWP_T_1_7_11: REF_AWP!$AE$2:$AE$3
Name AWP_T_1_7_12: REF_AWP!$AF$2:$AF$9
Name AWP_T_1_7_13: REF_AWP!$AG$2:$AG$5
Name AWP_T_1_7_14: REF_AWP!$AH$2
Name AWP_T_1_7_2: REF_AWP!$W$2:$W$4
Name AWP_T_1_7_3: REF_AWP!$X$2:$X$12
Name AWP_T_1_7_4: REF_AWP!$Y$2:$Y$3
Name AWP_T_1_7_5: REF_AWP!$Z$2
Name AWP_T_1_7_6: REF_AWP!$AA$2:$AA$6
Name AWP_T_1_7_7: REF_AWP!$AB$2
Name AWP_T_1_7_8: REF_AWP!$AC$2
Name AWP_T_1_7_9: REF_AWP!$AD$2:$AD$4
Name AWP_T_1_8_2: REF_AWP!$AI$2
Name AWP_T_1_8_3: REF_AWP!$AJ$2
Name AWP_T_1_9_1: REF_AWP!$AK$2
Name AWP_T_2_1_1: REF_AWP!$AU$2:$AU$5
Name AWP_T_2_1_2: REF_AWP!$AV$2:$AV$9
Name AWP_T_2_2_1: REF_AWP!$AW$2:$AW$5
Name AWP_T_2_2_2: REF_AWP!$AX$2:$AX$6
Name AWP_T_2_2_3: REF_AWP!$AY$2:$AY$3
Name AWP_T_2_2_4: REF_AWP!$AZ$2

Sheet AIDE
A1: AIDE MEMOIRE — BULLETIN HEBDOMADAIRE LHSPLA-TA
A3: OBJECTIF | B3: Alimenter chaque semaine le Bulletin d'Information transmis au Directeur des Opérations (DoS). Il récapitule les activités réalisées la semaine précédente et les activités planifiées sur un mois glissant.
A4: FRÉQUENCE | B4: Hebdomadaire. Chaque entité soumet son onglet chaque LUNDI matin avant 9h00
A5: STRUCTURE | B5: Ce classeur contient 10 onglets : MODE D'EMPLOI + 8 onglets entité (CAD, PMO, QAD, SE, SI, FINANCES, ABIDJAN, BOUAKE) + 1 onglet COMPILATION.
A6: COMMENT REMPLIR | B6: 1. Ouvrir VOTRE onglet (ex : SE pour le service SE). 2. Section A : saisir le Responsable, la Semaine de référence (ex : Du 07/04 au 11/04/2025) et la date de soumission. 3. Section B : décrire chaque activité RÉALISÉE (max 8 lignes — ajouter des lignes si besoin). 4. Section C : planifier les activités PRÉVUES sur les 4 prochaines semaines (max 10 lignes). 5. Section D : signaler tout RISQUE ou point nécessitant une décision / arbitrage (max 5 lignes).
A7: PARTICIPATION DoS | B7: Dans la colonne « Participation DoS ? » (Section C), sélectionner ✅ OUI ou ❌ NON dans le menu déroulant. Toute activité impliquant le DoS doit être signalée AU MOINS 2 SEMAINES avant son démarrage.
A8: CRITICITÉ (Section D) | B8: Utiliser le menu déroulant pour choisir le niveau : 🔴 Critique — Décision urgente requise 🟠 Élevé — Attention forte nécessaire 🟡 Modéré — À surveiller 🟢 Faible — Pour information
A9: COMPILATION AUTO | B9: L'onglet COMPILATION agrège automatiquement les données de tous les onglets entité via des formules. NE PAS modifier directement les cellules de la compilation — elles se mettent à jour automatiquement.
A10: ENVOI | B10: Envoyer le fichier EXCEL complété chaque lundi matin à Charles Oscar LEBRI (c.lebri@npsp.ci). L'objet du mail : [BULLETIN LHSPLA] Semaine du JJ/MM au JJ/MM/YYYY — [Votre entité]
A11: RÈGLES IMPORTANTES | B11: • Ne modifier NI supprimer les formules dans l'onglet COMPILATION. • Les cellules en jaune 🟡 sont les SEULES à renseigner. • Respecter le délai : soumission avant LUNDI 9h00. • En cas de doute, contacter Charles Oscar LEBRI.

Sheet CAD
A1: BULLETIN HEBDOMADAIRE LHSPLA-TA — CANEVAS DE REPORTING ENTITÉ
A2: Entité : CAD – Chaîne d'Approvisionnement Décentralisée
A4: A. INFORMATIONS DE SOUMISSION
A5: Entité | C5: Responsable (Nom & Prénom) | E5: Semaine de référence | G5: Date de soumission
A6: CAD | E6: =SE!E6 -> Du 25/05 au 29/05/2026 | G6: =SE!G6 -> 46174
A8: B. ACTIVITÉS RÉALISÉES — Semaine précédente
A9: ℹ️ Pour chaque activité réalisée au cours de la semaine écoulée, compléter une ligne.
A10: N° | B10: N° Activités | C10: Libellé de la tâche | D10: Objectifs | E10: Lieu | F10: Date(s) | G10: Principales recommandations / Résultats clés
A11: 1 | B11: 1.3-2 | C11: 1.3-2.4 : Organiser des rencontres d'orientation logistique au niveau départemental | D11: · Présenter et analyser les résultats des activités logistiques au niveau des ESPC : rapportage et qualité des données rapportées ; disponibilités des stocks de produits traceurs et Système d’Alerte Précoce ; Gestion des stocks et utilisation de mSupply ; données de la File Active. · Identifier les problèmes à la mise en œuvre des activités au niveau des ESPC · Renforcer les capacités des gestionnaires de pharmacie des ESPC · Formuler des recommandations | E11: DS APA (26/05/2026) | F11: 46168 | G11: Nombre d'acteurs des ESPC présents : 14 acteurs; Les acteurs présents ont été sensibilités sur l'importance du respect du délai de dépôt des RM, coachés sur la qualité des données rapportées en passant en revue les erreurs courantes de rapportage (report mensuel des données; mauvaise unité de rapportage; items insuffisamment renseignés; erreurs de calculs; les incohérences régimes et indicateurs), au SAP et sa mise en oeuvre. Aussi, les acteurs ont été orientés sur la gestion des produits iCCM. Quelques recommandations : Organiser les services en responsabilisant les acteurs; Elaborer et transmettre dans les délais les RM; Valider en interne les données avant transmission des rapports au DS; Utiliser correctement toutes les fonctionnalités de mSupply; Estimer correctement les quantités à allouer en tenant compte des consommations réelles et des nombres de jours de rupture notifiés; Mettre en oeuvre le SAP pour anticiper tous risques de rupture et de péremptione
A12: 2 | B12: 1.3-2 | C12: 1.3-2.2 : Organiser des visites d'assistance technique aux acteurs de la chaîne d'approvisionnement décentralisée | D12: Améliorer la qualité du rapportage, la qualité des prestations et de la gestion des produits et intrants des PNS | F12: Du 25 au 29/05/2026 | G12: Pas de visite réalisée cette semaine
A13: 3 | B13: 1.3-2 | C13: 1.3-2.3 : Apporter un appui technique et financier aux réunions régionales d'analyse et de mise à niveau des stocks | D13: Accompagner les gestionnaires des sites clients directs dans l'exécution effective des plans de redéploiements des stocks issus des réunions d'analyse | E13: Suivi de l'execution des plans de redeploiement élaborés et en cours de réalisation | F13: Du 25 au 29/05/2026 | G13: 1 plan de redéploiement a été élaboré et en cours de réalisation avec l'appui logistique de LHSPLA. Pour les réunions réalisées la semaine du 11 au 15/05/202, le point de suivi de la réalisation des 4 plans de redéploiement est le suivant : Région Moronou (100%); Région Lôh Djiboua (80%); Région Gôh (80%) et Agnéby-Tiassa (80%)
A14: 4 | B14: 1.3-1 | C14: 1.3-1.1 : Faire la mise à jour mensuelle des contacts téléphoniques des prestataires à insérer dans la flotte | D14: Faciliter les échanges d'informations logistiques des produits de santé du niveau central au niveau communautaire
A15: 5 | B15: 1.2-1 | C15: 1.2-1.1 : Faire le suivi la complétude et la promptitude des rapports des sites non clients directs (mSupply, …) | D15: améliorer la disponibilité des produits traceurs au niveau des sites derservis par les districts | E15: Régions sanitaires livrées par l'Agence Régionale de Bouaké | F15: Du 25/05/2026 au 31/05/2026 | G15: Relance sous forme de rappels dans les groupes watsapp de districts pour les differentes tâches à effectuer avec mSupply;
A16: 6 | B16: 1.3-2 | C16: 1.3-2.3 : Apporter un appui technique et financier aux réunions régionales d'analyse et de mise à niveau des stocks | D16: améliorer la disponibilité des produits traceurs des programmes de sante au niveau de chaque région | E16: Bélier, Marahoué,Hambol, Haut-Sassandra, Guémon, et Worodougou | F16: Du 25/05/2026 au 29/05/2026 | G16: suivi de l'excécution des plans de rédeploiement issus des réunions d'analyse des stocks; le taux est de 100% pour le Worodougou, Bélier et Haut-Sassandra
A17: 7 | B17: 1.8-2 | C17: 1.8-2.1 : Organiser des sessions de formation des acteurs de la chaîne d'approvisionnement | D17: Renforcer less capacité techniques des gestionnaires (APGP, IDE et SFDE) des produits de santé des sites péripheriques | E17: Yamoussoukro | F17: 27/05/2026 au 31/05/2026 | G17: Formation de 15 acteurs des ESPC et districts surl'optimisation de la gestion des stocks des produits de santé; entreposage et stockage; prise en main de mSupply; Système d'Alerte Précoce et Assistance Technique. La progression des apprenants etait significative à l'issu des pré et Post-Test
A18: 8
A19: ↳ Ajouter autant de lignes que nécessaire avant soumission.
A21: C. ACTIVITÉS PLANIFIÉES — Mois glissant (4 semaines à venir)
A22: ℹ️ Lister toutes les activités prévues sur les 4 prochaines semaines. Signaler en ROUGE les activités nécessitant la participation du DoS.
A23: N° | B23: N° Activités | C23: Libellé de la tâche | D23: Objectifs | E23: Lieu | F23: Date(s) prévues | G23: Participation DoS ? | H23: Observations / Points d'attention
A24: 1 | B24: 1.3-2 | C24: 1.3-2.3 : Apporter un appui technique et financier aux réunions régionales d'analyse et de mise à niveau des stocks | D24: - Faire le point des recommandations ( suivi du taux de redéploiement, etc.) de la dernière réunion - Faciliter la prise en main du “Weekly Report” pour l’analyse des niveaux de stocks au niveau régional et la prise de décision. - Effectuer les analyses avec les données disponibles pour une prise de décision - Discuter des autres activités et identifier les problèmes à la gestion de la chaîne d’approvisionnement - Proposer un plan d’amélioration ( plans de redéploiements) - Formuler des recommandations | E24: Régions sanitaires Gbôklê; N'zi et Grands Ponts | F24: Du 08 au 12/06/2026 | G24: ❌ NON | H24: Activité reprogrammée : DS Gbôklê (12/06/2026); DS N'zi (date pas encore communiquée); GRANDS PONTS (date pas encore communiquée)
B25: 1.3-2 | C25: 1.3-2.2 : Organiser des visites d'assistance technique aux acteurs de la chaîne d'approvisionnement décentralisée | D25: Améliorer la qualité du rapportage, la qualité des prestations et de la gestion des produits et intrants des PNS et la disponibilité des produits traceurs des PNS | E25: Région Abidjan 2 | F25: Du 01 au 05/06/2026 | G25: ❌ NON | H25: Ces visites de sites de la région Abidjan 2, seront mis à profit pour redéployer les stocks issus du plan de la réunion d'analyse et de mise à niveau des stocks. Afin d'assurer la disponibilité des produits de santé des PNS
A26: 2 | B26: 1.3-2 | C26: 1.3-2.4 : Organiser des rencontres d'orientation logistique au niveau départemental | D26: · Présenter et analyser les résultats des activités logistiques au niveau des ESPC : rapportage et qualité des données rapportées ; disponibilités des stocks de produits traceurs et Système d’Alerte Précoce ; Gestion des stocks et utilisation de mSupply ; données de la File Active. · Identifier les problèmes à la mise en œuvre des activités au niveau des ESPC · Renforcer les capacités des gestionnaires de pharmacie des ESPC · Formuler des recommandations | E26: DS DIVO; DS DABOU; DS DOROPO et DS Alépé | F26: 01 au 12/06/2026 | G26: ❌ NON | H26: DS DIVO (date pas encore communiquée); DS DABOU (date pas encore communiquée) DS DOROPO (date pas encore communiquée) et DS Alépé (prévue le 29/05/2026; reprogrammée à une date ultérieure pour conflit de calendrier)
A27: 3 | B27: 1.3-2 | C27: 1.3-2.4 : Organiser des rencontres d'orientation logistique au niveau départemental | D27: · Présenter et analyser les résultats des activités logistiques au niveau des ESPC des trois derniers mois (Mars,Avril et MAI): rapportage et qualité des données rapportées ; disponibilités des stocks de produits traceurs et Système d’Alerte Précoce ; Gestion des stocks et utilisation de mSupply ; données de la File Active. · Identifier les problèmes à la mise en œuvre des activités au niveau des ESPC · Renforcer les capacités des gestionnaires de pharmacie des ESPC · Formuler des recommandations | E27: Korhogo 2, Dikodougou, Niakara, Katiola, Botro, Béoumi, Bouaké nord ouest, Mankono, Yamousoukro, Toumodi, Odiénné, Madinani, Zouan-Hounien, Bloléquin, Zoukougbeu, Vavoua, Issia ,Bouaflé, Kani et Kounahiri | F27: 08/06/2026 au 19/06/2026 | G27: ❌ NON | H27: réception des TDR de 08 sites ; préparation avec les Pharmaciens de Districts pour le bon deroulement de ses rencontres
A28: 4 | B28: 1.3-2 | C28: 1.3-2.2 : Organiser des visites d'assistance technique aux acteurs de la chaîne d'approvisionnement décentralisée | D28: effectuer des visites de sites à faibles resultats, travailler avec le site sur:rapportage et qualité des données rapportées ; disponibilités des stocks de produits traceurs et Système d’Alerte Précoce ; Gestion des stocks et utilisation de mSupply ; données de la File Active. | E28: sites à identifier par PRES dans la zone couverte par CAD BOUAKE | F28: du 15/06/26 au 25/06/26 | G28: ❌ NON | H28: identification de sites selon des points précis de mauvaises performance
A29: 5 | B29: 1.3-2 | C29: 1.2-1.1 : Faire le suivi la complétude et la promptitude des rapports des sites non clients directs (mSupply, …) | D29: Assister les sites au rapportage ,dans les délais, des sites clients directs NPSP | E29: sites CAD Bouaké | F29: du 11/05/26 au 31/05/26 | G29: ❌ NON | H29: Disponibilité à 100% des données logistiques pour la prise de décision
A30: 6 | B30: 1.3-1 | C30: 1.3-1.2 : Fournir des forfaits de communication et de connexion internet aux structures du niveau central jusqu'au niveau communautaire. | D30: maintenir les sites clients directs NPSP dans la flotte pour faciliter la communication | E30: CAD Bouaké | F30: en continue | G30: ❌ NON | H30: Maintien de tous les numéros des sites dans la flotte compte tenu du turn over des gestionnaires
A31: 7 | B31: 1.2-1 | C31: 1.4-1.3 : Apporter un appui technique et financier au district sanitaire pour le suivi de la distribution communautaire | D31: Renforcer la disponibilité des CTA et autres ILP en vue d’une meilleure performance de l’ICCM au niveau communautaire | E31: CAD Abidjan | F31: Du 11/05/2026 au 31/05/2026 | G31: ❌ NON | H31: Appui technique à l'élaboration des TDR et à la programmation des visites des DS
A32: 8 | B32: 1.8-2 | C32: 1.8-2.1 : Organiser des sessions de formation des acteurs de la chaîne d'approvisionnement | D32: Renforcer less capacité techniques des gestionnaires (APGP, IDE et SFDE) des produits de santé des sites péripheriques | E32: Yamoussoukro | F32: 01/06/26 au 06/06/26 | G32: ❌ NON | H32: Formation de 30 acteurs (APGP,IDE, SFDE) attendus; des Tests prévus; briefing des formateurs afin de prendre en compte les leçons apprises de la formation du groupe precédant
A33: 9 | B33: 1.2-1 | C33: 1.2-1.1 : Faire le suivi la complétude et la promptitude des rapports des sites non clients directs (mSupply, …) | D33: améliorer le rapportage des sites périphériques | E33: CAD Bouaké | F33: Du 18 au 31/05/2026 | G33: ❌ NON | H33: sensibiliser les gestionnaires sur la gestion des produits périmés afin d'eviter de les rapportés comme produits disponibles et utilisables
A34: 10 | B34: 1.3-2 | C34: 1.3-2.7 : Organiser une orientation des pharmaciens de régions sur le management de la CA | D34: Renforcer les compétence en management et en leadership des PR pour assurer la gouvernance efficace et une redevabilité accrue de la chaine d'approvisionnement pharmaceutique décentralisée | E34: YAMOUSOUKRO | F34: 08 au 12/06/2026 | G34: ❌ NON | H34: Elaboration des plan de contingence des 10 régions participants afin d'améliorer la disponibilité des produits de santé dans leurs points de prestations de service. Partage d'expériences et de bonnes pratiques de gestion de chaine d'approvisionnement
A35: ↳ Toute activité impliquant le DoS doit être transmise au moins 2 semaines avant son démarrage.
A37: D. POINTS DE VIGILANCE / RISQUES / BESOINS DE DÉCISION
A38: ℹ️ Signaler tout élément nécessitant une attention particulière, une décision ou un arbitrage.
A39: N° | B39: Thème | C39: Catégorie | D39: Description du point | E39: Niveau de criticité | F39: Action attendue / Décision souhaitée
A40: 1
A41: 2
A42: 3
A43: 4
A44: 5

Sheet CAC
A1: BULLETIN HEBDOMADAIRE LHSPLA-TA — CANEVAS DE REPORTING ENTITÉ
A2: Entité : CAC - Chaine d'Approvisionnement Communautaire
A4: A. INFORMATIONS DE SOUMISSION
A5: Entité | C5: Responsable (Nom & Prénom) | E5: Semaine de référence | G5: Date de soumission
A6: CAC | E6: =SE!E6 -> Du 25/05 au 29/05/2026 | G6: =SE!G6 -> 46174
A8: B. ACTIVITÉS RÉALISÉES — Semaine précédente
A9: ℹ️ Pour chaque activité réalisée au cours de la semaine écoulée, compléter une ligne.
A10: N° | B10: N° Activités | C10: Libellé de la tâche | D10: Objectifs | E10: Lieu | F10: Date(s) | G10: Principales recommandations / Résultats clés
A11: 1 | B11: 1.4-1 | C11: 1.4-1.4 : Faire le suivi de la disponibilité des produits de santé communautaires | D11: Mission de suivi des recommandations EUV et de coaching des CAC et ASS dans les districts Tiassalé, 2 ESPC 5DR Ahoara et CSU Morokro) caoching au remplissage du registre ASC et au Weekly Report Communautaire. Diffusion du Weekly aux ASS et CAC. | E11: DS TIASSALE | F11: Du 28 au 29 Mai 2026 | G11: Continuer le coaching au rapportage et au remplissage correcte du rapport ASC dans e-SIGL
A12: 2 | B12: 2.2-3 | C12: 2.2-3.1 : Organiser 3 inventaires des produits traceurs des programmes suivis | D12: Réalisation de l'inventaire tournant à l'agence programme du 30 au 31 Mai 2026 | E12: Agence programme | F12: du 16 au 20 Mai 2026 | G12: Inventaire physique réalisé, finalisation de la justification des écarts et de la redaction du rapport en cours
A13: 3
A14: 4
A15: 5
A16: 6
A17: 7
A18: 8
A19: ↳ Ajouter autant de lignes que nécessaire avant soumission.
A21: C. ACTIVITÉS PLANIFIÉES — Mois glissant (4 semaines à venir)
A22: ℹ️ Lister toutes les activités prévues sur les 4 prochaines semaines. Signaler en ROUGE les activités nécessitant la participation du DoS.
A23: N° | B23: N° Activités | C23: Libellé de la tâche | D23: Objectifs | E23: Lieu | F23: Date(s) prévues | G23: Participation DoS ? | H23: Observations / Points d'attention
A24: 1
A25: 2
A26: 3
A27: 4
A28: 5
A29: 6
A30: 7
A31: 8
A32: 9
A33: 10
A34: ↳ Toute activité impliquant le DoS doit être transmise au moins 2 semaines avant son démarrage.
A36: D. POINTS DE VIGILANCE / RISQUES / BESOINS DE DÉCISION
A37: ℹ️ Signaler tout élément nécessitant une attention particulière, une décision ou un arbitrage.
A38: N° | B38: Thème | C38: Catégorie | D38: Description du point | E38: Niveau de criticité | F38: Action attendue / Décision souhaitée
A39: 1
A40: 2
A41: 3
A42: 4
A43: 5

Sheet PMO
A1: BULLETIN HEBDOMADAIRE LHSPLA-TA — CANEVAS DE REPORTING ENTITÉ
A2: Entité : PMO – Gestion de Projet (Project Management Office)
A4: A. INFORMATIONS DE SOUMISSION
A5: Entité | C5: Responsable (Nom & Prénom) | E5: Semaine de référence | G5: Date de soumission
A6: PMO | C6: PILLAH AUDREY | E6: =SE!E6 -> Du 25/05 au 29/05/2026 | G6: =SE!G6 -> 46174
A8: B. ACTIVITÉS RÉALISÉES — Semaine précédente
A9: ℹ️ Pour chaque activité réalisée au cours de la semaine écoulée, compléter une ligne.
A10: N° | B10: N° Activités | C10: Libellé de la tâche | D10: Objectifs | E10: Lieu | F10: Date(s) | G10: Principales recommandations / Résultats clés
A11: 1
A12: 2
A13: 3
A14: 4
A15: 5
A16: 6
A17: 7
A18: 8
A19: ↳ Ajouter autant de lignes que nécessaire avant soumission.
A21: C. ACTIVITÉS PLANIFIÉES — Mois glissant (4 semaines à venir)
A22: ℹ️ Lister toutes les activités prévues sur les 4 prochaines semaines. Signaler en ROUGE les activités nécessitant la participation du DoS.
A23: N° | B23: N° Activités | C23: Libellé de la tâche | D23: Objectifs | E23: Lieu | F23: Date(s) prévues | G23: Participation DoS ? | H23: Observations / Points d'attention
A24: 1 | B24: 1.11-3 | C24: 1.11-3.2 : Organiser des réunions mensuelles du bilan de la performance du projet | D24: Faire le reporting détaillé des activités du projet sur le mois précédent par acteur | E24: Abidjan Nouvelle PSP-CI | F24: 46189 | G24: ❌ NON | H24: *Réunion mois de juin 2026 *Causes de la non-réalisation des activités *Résolution des insatisfactions
A25: 2 | B25: 1.11-4 | C25: 1.11-4.1 : Faire la maintenance annuelle ORCHESTRA | D25: Maintenance annuelle et assistance pour le logiciel de suivi du projet LHSPLA | E25: Abidjan Nouvelle PSP-CI | G25: ❌ NON | H25: *Aucune suite pour le paiement de la maintenance *Risque de bugs lors d'utilisation de Orchestra
A26: 3 | B26: 1.8-3 | C26: 1.8-3.1 : Appuyer les gestionnaires des structures sanitaires publiques dans le cadre de leurs activités | D26: Amélioration des compétences du pool de formateurs pour des formations et des coachings de qualité fait à l'endroit des gestionnaires des structures sanitaires publiques | E26: Yamoussoukro | F26: Date à définir | G26: ❌ NON | H26: Apprentissage de l'andragogie. en deux phases : phase pratique et phase théorique
A27: 4 | B27: 1.11-3 | C27: 1.11-3.1 : Compiler mensuellement les rapports de progression dans le logiciel ORCHESTRA | D27: Orchestra est à jour | E27: Abidjan Nouvelle PSP-CI | F27: du 04 au 05/06/2026 | G27: ❌ NON | H27: Extraction des niveaux d'avancement par entité et transmission des extractions à chaque entité
A28: 5
A29: 6
A30: 7
A31: 8
A32: 9
A33: 10
A34: ↳ Toute activité impliquant le DoS doit être transmise au moins 2 semaines avant son démarrage.
A36: D. POINTS DE VIGILANCE / RISQUES / BESOINS DE DÉCISION
A37: ℹ️ Signaler tout élément nécessitant une attention particulière, une décision ou un arbitrage.
A38: N° | B38: Thème | C38: Catégorie | D38: Description du point | E38: Niveau de criticité | F38: Action attendue / Décision souhaitée
A39: 1 | B39: Gestion de Projet | D39: Restructuration du prestataire du logiciel ORCHESTRA demandant une revision du contrat. Aucune avancée sur le contrat, ce qui retarde la mise en oeuvre du paiement dans le cadre de la maintenance. | E39: 🟠 Élevé | F39: Approche du Département Juridique pour une accélération du traitement de ce dossier.
A40: 2
A41: 3
A42: 4
A43: 5

Sheet QAD
A1: BULLETIN HEBDOMADAIRE LHSPLA-TA — CANEVAS DE REPORTING ENTITÉ
A2: Entité : QAD – Quantifiction Achat et Distribution
A4: A. INFORMATIONS DE SOUMISSION
A5: Entité | C5: Responsable (Nom & Prénom) | E5: Semaine de référence | G5: Date de soumission
A6: QAD | C6: ZILLE CYRILLE | E6: =SE!E6 -> Du 25/05 au 29/05/2026 | G6: =SE!G6 -> 46174
A8: B. ACTIVITÉS RÉALISÉES — Semaine précédente
A9: ℹ️ Pour chaque activité réalisée au cours de la semaine écoulée, compléter une ligne.
A10: N° | B10: N° Activités | C10: Libellé de la tâche | D10: Objectifs | E10: Lieu | F10: Date(s) | G10: Principales recommandations / Résultats clés
A11: 1 | B11: 1.10-1 | C11: 1.10-1.1 : Participer aux réunions de suivi mensuel de stock des PNS | D11: * Suivi mensuel des stocks et des PA pour une disponibilité adéquate des produits à tous les niveaux de la chaine d'approvisionnement pour réduire les risques de rupture et de péremption | E11: En ligne | F11: 46168 | G11: *Principales recommandations pour la NPSP* Fournir la date probable de livraison du reliquat des produits de prémière ligne sous BGE Actualiser le eSigl et le fichier suivi de stock en y rétirant l'amikacine inj Retarder la prochaine commande de Bedaquiline 20mg du fait du surstock observé au niveau central comme péripherique sur ce produit ( fin septembre au lieu de fin juin 2026)
A12: 2 | B12: 3.2-1 | C12: 3.2-1.2 : Mettre à disposition des transitaires la documentation requise pour organiser l'acheminement | D12: * Disponibilité rapide des produits dans les entrepôts NPSP | E12: ABIDJAN | F12: 46171 | G12: * Résultats clés* Transmission des observations (date d'effet) sur le document projet d'exonération sur les acquisitions planifiées sur budget du Gouvernement Américain
A13: 3 | B13: 2.6-5 | C13: 2.6-5.9 : Organiser quatre sessions d'orientation des Acteurs de la gestion logistique | D13: Renforcer les capacités des gestionnaires et techniciens de laboratoire en gestion logistique des produits de la charge virale | E13: ABIDJAN | F13: 46170 | G13: Renforcement des capacités de 18 personnes (pharmacie et laboratoire) sur la gestion des produits de mPima et des consommables généraux relatifs aux produits de laboratoire.
A14: 4 | B14: 2.2-1 | C14: 2.2-1.4 : Mettre en place un fichier de suivi intégré de la reception des produits à la levée de quarantaine de ces produits | D14: Respect des délais objectivés | E14: Abidjan | F14: 25 au 29 mai | G14: Finaliser la correspondance entre les désignation/code QAT et Sage X3 pour transmission interne
A15: 5 | B15: 2.2-3 | C15: 2.2-3.1 : Organiser 3 inventaires des produits traceurs des programmes suivis | D15: Améliorer la précision et la justesse des stocks | E15: Abidjan | F15: 30 mai au 03 juin | G15: Améliorer la communication interne concernant l'inventaire tournant.
A16: 6 | B16: 2.2-2 | C16: 2.2-2.2 : Faire le suivi hebdomadaire de l'exécution du plan de réapprovisionnement | D16: Améliorer la disponibilité des produits dans les agences de distribution | E16: Abidjan | F16: 25 au 31 mai | G16: Aborder ce point lors des prochaines réunions avec les parties prenantes car les délais objectivés sont difficilement attteints
A17: 7 | B17: 2.2-3 | C17: 2.2-3.2 : Faire le suivi de la prise en compte des écarts relevés lors de chaque inventaire | D17: Améliorer la précision et la justesse des stocks | E17: Abidjan | F17: 25 au 31 mai
A18: 8
A19: ↳ Ajouter autant de lignes que nécessaire avant soumission.
A21: C. ACTIVITÉS PLANIFIÉES — Mois glissant (4 semaines à venir)
A22: ℹ️ Lister toutes les activités prévues sur les 4 prochaines semaines. Signaler en ROUGE les activités nécessitant la participation du DoS.
A23: N° | B23: N° Activités | C23: Libellé de la tâche | D23: Objectifs | E23: Lieu | F23: Date(s) prévues | G23: Participation DoS ? | H23: Observations / Points d'attention
A24: 1 | B24: 1.1-6 | C24: 1.1-6.1 : Apporter une assistance technique pour l'organisation d'un atelier de préquantification des médicaments pour la prise en charge de la santé de la Mère et de l'enfant. | D24: Disponibilité des données et hypothèses nécessaires à la prévision des besoins en médicaments de la santé de la mère et de l'enfant | E24: Bassam | F24: 01 au 04 juin 2026 | G24: ✅ OUI
A25: 2 | B25: 1.1-6 | C25: 1.1-6.2 : Apporter une assistance technique pour l'organisation d'un atelier de quantification des médicaments pour la prise en charge de la santé de la Mère et de l'enfant. | D25: Disponibilité des plans d'approvisionnements pour les besoins de la période 2027-2028 | E25: Yamoussoukro | F25: 15 au 20 juin 2026 | G25: ✅ OUI
A26: 3 | B26: 2.6-5 | C26: 2.6-5.2 : Réaliser trois missions de supervision pour les laboratoires de charge virale | D26: Renforcement des capacités des gestionnaires de pharmacie et des techniciens de laboratoire dans la gestion des produits de la charge virale /EID | E26: KORHOGO-BOUAKE-DALOA | F26: 07 au 13 juin 2026 | G26: ❌ NON
B27: 2.6-5 | C27: 2.6-5.9 : Organiser quatre sessions d'orientation des Acteurs de la gestion logistique | D27: Renforcement des capacités des gestionnaires de pharmacie et des techniciens de laboratoire dans la gestion des produits de la charge virale /EID | E27: ABIDJAN | F27: 01-04 juin 2026 | G27: ❌ NON
A28: 5 | B28: 2.6-5 | C28: 2.6-5.2 : Réaliser trois missions de supervision pour les laboratoires de charge virale | D28: Renforcement des capacités des gestionnaires de pharmacie et des techniciens de laboratoire dans la gestion des produits de la charge virale /EID | E28: ABENGOUROU | F28: 17 au 19 juin 2026 | G28: ❌ NON
A29: 6 | B29: 2.2-1 | C29: 2.2-1.2 : Faire un suivi hebdomadaire des entrées en machine des produits de programme | D29: Améliorer la disponibilité des produits au niveau des Agences de distribution | E29: Abidjan | F29: 25 au 31 mai | G29: ❌ NON
A30: 7 | B30: 2.2-3 | C30: 2.2-3.2 : Faire le suivi de la prise en compte des écarts relevés lors de chaque inventaire | D30: Améliorer la précision et la justesse des stocks | E30: Abidjan | F30: 25 au 31 mai | G30: ❌ NON
A31: 8 | B31: 2.2-2 | C31: 2.2-2.2 : Faire le suivi hebdomadaire de l'exécution du plan de réapprovisionnement | D31: Améliorer la disponibilité des produits dans les agences de distribution | E31: Abidjan | F31: 25 au 31 mai | G31: ❌ NON
A32: 9 | B32: 2.6-2 | C32: 2.6-2.1 : Organiser des reunions quinzomadaires de suivi des performances de l'Agence Programme | D32: Améliorer la disponibité et la distribution des produits des programmes aux sites clients directs | E32: Abidjan | F32: 25 mai au 7 juin | G32: ❌ NON
A33: 10 | B33: 2.2-1 | C33: 2.2-1.4 : Mettre en place un fichier de suivi intégré de la reception des produits à la levée de quarantaine de ces produits | D33: Respect des délais objectivés | E33: Abidjan | F33: 25 mai au 7 juin | G33: ❌ NON
A34: ↳ Toute activité impliquant le DoS doit être transmise au moins 2 semaines avant son démarrage.
A36: D. POINTS DE VIGILANCE / RISQUES / BESOINS DE DÉCISION
A37: ℹ️ Signaler tout élément nécessitant une attention particulière, une décision ou un arbitrage.
A38: N° | B38: Thème | C38: Catégorie | D38: Description du point | E38: Niveau de criticité | F38: Action attendue / Décision souhaitée
A39: 1 | B39: Commandes et Approvisionnement | C39: Traitement de commandes fournisseurs | D39: Faible disponibilité de plusieurs consommables à acquerir sur budget ETAT au niveau central (DBS, Tubes EDTA, Tubes rouge, Tubes gris, Pastilles de chloramine, etc) | E39: 🟠 Élevé | F39: - Procéder à des acquisitions de dépannages pour garantir la continuité des services - Procéder au paiement des fournisseurs pour une livraison des kits DBS
A40: 2 | B40: Commandes et Approvisionnement | C40: Dédouanement et enlèvement | D40: Refus de libération des colis arrivés en raison de l'expiration de l'exonération des produits financés par le Gouvernement Américain. Le service Transit a indiqué que la douane réclamait un courrier, une note ou un document officiel indiquant la poursuite des activités du projet LHSPLA sous le couvert du Département d'Etat Américain. | E40: 🟠 Élevé | F40: - Obtenir un délai additionnel avec la DGD pour la libération des colis arrivés en attendant le renouvellement de l'exonération des produits acquis sur le budget du Gouvernement Américain
A41: 3
A42: 4
A43: 5
A45: LHSPLA-TA | NPSP-CI | Canevas préparé par Charles Oscar LEBRI, MEL Manager | FY2026

Sheet SE
A1: BULLETIN HEBDOMADAIRE LHSPLA-TA — CANEVAS DE REPORTING ENTITÉ
A2: Entité : SE – Suivi & Évaluation (MEL)
A4: A. INFORMATIONS DE SOUMISSION
A5: Entité | C5: Responsable (Nom & Prénom) | E5: Semaine de référence | G5: Date de soumission
A6: SE | C6: LEBRI Charles Oscar | E6: Du 25/05 au 29/05/2026 | G6: 46174
A8: B. ACTIVITÉS RÉALISÉES — Semaine précédente
A9: ℹ️ Pour chaque activité réalisée au cours de la semaine écoulée, compléter une ligne.
A10: N° | B10: N° Activités | C10: Libellé de la tâche | D10: Objectifs | E10: Lieu | F10: Date(s) | G10: Principales recommandations / Résultats clés
A11: 3
A12: 4
A13: 5
A14: 6
A15: 7
A16: 8
A17: ↳ Ajouter autant de lignes que nécessaire avant soumission.
A19: C. ACTIVITÉS PLANIFIÉES — Mois glissant (4 semaines à venir)
A20: ℹ️ Lister toutes les activités prévues sur les 4 prochaines semaines. Signaler en ROUGE les activités nécessitant la participation du DoS.
A21: N° | B21: N° Activités | C21: Libellé de la tâche | D21: Objectifs | E21: Lieu | F21: Date(s) prévues | G21: Participation DoS ? | H21: Observations / Points d'attention
A22: 2 | B22: 1.7-6 | C22: 1.7-6.5 : Apporter un appui à la mise en oeuvre des recommandations de l'EUV. | D22: Évaluer le niveau de mise en œuvre des recommandations issues de l'EUV 2025 et renforcer les capacités des agents de la chaîne d'approvisionnement dans la gestion des produits antipaludiques au niveau de 10 districts sanitaires identifiés. | E22: MARAHOUE, HAMBOL, GBEKE, LOH-GUIBOUA, IFFOU, AGNEBY-TIASSA | F22: 27/05/2026 au 10/06/2026 | G22: ❌ NON
A23: 3 | B23: 1.7-3 | C23: 1.7-3.4 : Déploiement dans 31 régions | D23: Déployer et Former les gestionnaires des établissements sanitaires, en charge de la File Active dans les districts sanitaires des régions de BOUNKANI, GBOKLE, NAWA, GUEMON, HAUT-SASSANDRA, HAMBOL et GÔH, à l’utilisation du SNGFA pour le rapportage et la gestion des données de file active | E23: AGNEBY-TIASSA, N'ZI, MARAHOUE, GOH, GUEMON et HAMBOL | F23: 07/06/2026 au 18/06/2026 | G23: ❌ NON | H23: Quelques ajustements mineurs de l'outil, relatifs aux formulaires de suivi des patients, ont été identifiés et communiqués à Bluesquare par l'équipe LHSPLA.
A24: 4 | B24: 1.7-3 | C24: 1.7-3.4 : Déploiement dans 31 régions | D24: Déployer et Former les gestionnaires des établissements sanitaires, en charge de la File Active dans les districts sanitaires des régions de LOH DJIBOUA, MORONOU,IFFOU, BAGOUE, GRANDS-PONTS et BAFING, à l’utilisation du SNGFA pour le rapportage et la gestion des données de file active | E24: LOH DJIBOUA ; MORONOU ; IFFOU ; BAGOUE ; GRANDS-PONTS et BAFING | F24: 21/06/2026 au 03/07/2026 | G24: ❌ NON
A25: 5
A26: 6
A27: 7
A28: 8
A29: 9
A30: 10
A31: ↳ Toute activité impliquant le DoS doit être transmise au moins 2 semaines avant son démarrage.
A33: D. POINTS DE VIGILANCE / RISQUES / BESOINS DE DÉCISION
A34: ℹ️ Signaler tout élément nécessitant une attention particulière, une décision ou un arbitrage.
A35: N° | B35: Thème | C35: Catégorie | D35: Description du point | E35: Niveau de criticité | F35: Action attendue / Décision souhaitée
A36: 1
A37: 2
A38: 3
A39: 4
A40: 5

Sheet SI
A1: BULLETIN HEBDOMADAIRE LHSPLA-TA — CANEVAS DE REPORTING ENTITÉ
A2: Entité : SI – Système d'Information
A4: A. INFORMATIONS DE SOUMISSION
A5: Entité | C5: Responsable (Nom & Prénom) | E5: Semaine de référence | G5: Date de soumission
A6: SI | C6: KOUAKOU ABIMAN THERESE D'AVILA EPSE DJEREKE | E6: =SE!E6 -> Du 25/05 au 29/05/2026 | G6: =SE!G6 -> 46174
A8: B. ACTIVITÉS RÉALISÉES — Semaine précédente
A9: ℹ️ Pour chaque activité réalisée au cours de la semaine écoulée, compléter une ligne.
A10: N° | B10: N° Activités | C10: Libellé de la tâche | D10: Objectifs | E10: Lieu | F10: Date(s) | G10: Principales recommandations / Résultats clés
A11: 1
A12: 2
A13: 3
A14: 4
A15: 5
A16: 6
A17: 7
A18: 8
A19: ↳ Ajouter autant de lignes que nécessaire avant soumission.
A21: C. ACTIVITÉS PLANIFIÉES — Mois glissant (4 semaines à venir)
A22: ℹ️ Lister toutes les activités prévues sur les 4 prochaines semaines. Signaler en ROUGE les activités nécessitant la participation du DoS.
A23: N° | B23: N° Activités | C23: Libellé de la tâche | D23: Objectifs | E23: Lieu | F23: Date(s) prévues | G23: Participation DoS ? | H23: Observations / Points d'attention
A24: 4 | B24: 4.2-3 | C24: 4.2.3.3 : Développer des guides utilisateurs simplifiés | D24: - Ciblage précis des besoins en formations ; - éviter les sessions génériques peu efficaces - optimiser le budget | F24: du 01/06/2026 au 31/06/2026 | G24: ❌ NON
A25: 5 | B25: 1.2-3 | C25: 1.2-3.1 : Equiper la NPSP en équipement informatique | D25: Doter la NPSP d’ordinateurs portables | F25: du 01/06/2026 au 31/06/2026 | G25: ❌ NON | H25: Acquisition prévu: 37 ordinateurs Une premiere acquisition de 14 ordinateurs est en cours; Reste 23 ordinateurs à aquérir
A26: 6 | B26: 4.2-5 | C26: 4.2.5.1 : Réaliser une évaluation diagnostique initial (Data Quality Assessment) | D26: - Mesurer l’exactitude des données (concordance entre les données saisies et les sources primaires). - Évaluer l’exhaustivité (complétude des enregistrements et des rapports). - Vérifier la ponctualité (respect des délais de saisie et de transmission). - Analyser la cohérence des données (absence de contradictions entre les différentes sources et rapports). - Apprécier l’accessibilité des données (facilité d’accès, disponibilité et utilisation pour la prise de décision). | E26: Les districts sanitaires de Bondoukou, Kani, Niakaramadougou, Sandegué, Yakassé Attobrou, Gagnoa 1, Daloa, Bouafé, Fresco, Dianra | F26: du 08/06/2026 au 12/06/2026 | G26: ❌ NON
A27: 7 | B27: 4.2-5 | C27: 4.2.5.4 : Monitorer à distance les sites identifiés par le DQA – tableau de bord mSupply | D27: - Suivre en temps réel les indicateurs clés de performance des sites sélectionnés. - Identifier rapidement les anomalies, incohérences et écarts de données. - Évaluer la qualité et la complétude des données saisies dans mSupply. - Détecter les sites nécessitant un accompagnement ou des actions correctives. - Produire des rapports périodiques de suivi à destination des parties prenantes. - Faciliter la prise de décision basée sur les données issues du tableau de bord mSupply. | F27: du 15/06/2026 au 27/06/2026 | G27: ❌ NON
A28: 8 | B28: 4.2-4 | C28: 4.2.4.1 : Cartographier et prioriser les bugs mSupply | D28: - Recenser et documenter tous les bugs signalés dans mSupply. - Classifier les anomalies par module, fonctionnalité et type d'incident. - Évaluer l'impact de chaque bug sur les opérations et les utilisateurs. - Définir les niveaux de priorité (critique, majeur, mineur, faible). - Élaborer une feuille de route de correction en collaboration avec les équipes techniques et métiers. - Assurer le suivi de la résolution des anomalies jusqu'à leur clôture. | F28: du 01/06/2026 au 31/06/2026 | G28: ❌ NON
A29: 9
A30: 10
A31: ↳ Toute activité impliquant le DoS doit être transmise au moins 2 semaines avant son démarrage.
A33: D. POINTS DE VIGILANCE / RISQUES / BESOINS DE DÉCISION
A34: ℹ️ Signaler tout élément nécessitant une attention particulière, une décision ou un arbitrage.
A35: N° | B35: Thème | C35: Catégorie | D35: Description du point | E35: Niveau de criticité | F35: Action attendue / Décision souhaitée
A36: 1
A37: 2
A38: 3
A39: 4
A40: 5
A42: LHSPLA-TA | NPSP-CI | Canevas préparé par Charles Oscar LEBRI, MEL Manager | FY2026

Sheet FINANCES
A1: BULLETIN HEBDOMADAIRE LHSPLA-TA — CANEVAS DE REPORTING ENTITÉ
A2: Entité : Service Finances
A4: A. INFORMATIONS DE SOUMISSION
A5: Entité / Unité | C5: Responsable (Nom & Prénom) | E5: Semaine de référence | G5: Date de soumission
A6: FINANCES | C6: YAPO ARNAUD | E6: Du 24/04 au 01/05/2026 | G6: 46168
A8: B. ACTIVITÉS RÉALISÉES — Semaine précédente
A9: ℹ️ Pour chaque activité réalisée au cours de la semaine écoulée, compléter une ligne.
A10: N° | B10: N° Activités | C10: Libellé de la tâche | D10: Objectifs | E10: Lieu | F10: Date(s) | G10: Principales recommandations / Résultats clés
A11: 1 | B11: 1.11-1 | C11: 1.11-1.12 : Acquisition de stickers pour le matériel acquis par le projet | D11: Référencer et identifier le matériel acquis dans le cadre du projet LHSPLA | E11: Abidjan | F11: 46164 | G11: Finaliser les code QR
A12: 2 | B12: 1.11-1 | C12: 1.11-1.11 : Equiper le personnel du projet en matériel informatique | D12: Renforcer les capacités opérationnelles et le système d'information de l’équipe projet LHSPLA | E12: Abidjan | F12: 46164 | G12: Finaliser le paiement d'un acompte au fournisseur.
A13: 3 | B13: 1.11-1 | C13: 1.11-1.9 : Rémunération des agents LHSPLA. | D13: Déterminer la quote part de chaque financement dans les refacturation de salaires d'avril à septembre 2026 | E13: Abidjan | F13: 46155 | G13: Proposition de quote part COP=49% MOP=19% MCH=32%
A14: 4 | B14: 1.11-1 | C14: 1.11-1.5 : Atelier de formation sur les méthodes de réconciliations des pièces comptables | D14: Création d'un outil permettant de générer des budgets de TDR | E14: Abidjan | F14: 46164 | G14: Cahier de charge transmis au SI Vidéo demonstrative effectuée Test de l'outil
A15: 5 | B15: 1.11-1 | C15: 1.11-1.2 : Réaliser des clôtures comptables mensuels | D15: Editer les liquidations d'octobre 2025 à Avril 2026 pour approbation | E15: Abidjan | F15: 46162 | G15: Raport financier présentant les charges et les dépenses effectuées de la période
A16: 6 | B16: 1.11-1 | C16: 1.11-1.2 : Réaliser des clôtures comptables mensuels | D16: Editer les appels de fonds de juin à septembre 2026 pour approbation | E16: Abidjan | F16: 46162 | G16: Appels de fonds de juin à septembre 2026
A17: 7
A18: 8
A19: ↳ Ajouter autant de lignes que nécessaire avant soumission.
A21: C. ACTIVITÉS PLANIFIÉES — Mois glissant (4 semaines à venir)
A22: ℹ️ Lister toutes les activités prévues sur les 4 prochaines semaines. Signaler en ROUGE les activités nécessitant la participation du DoS.
A23: N° | B23: N° Activités | C23: Libellé de la tâche | D23: Objectifs | E23: Lieu | F23: Date(s) prévues | G23: Participation DoS ? | H23: Observations / Points d'attention
A24: 1 | B24: 1.11-1 | C24: 1.11-1.2 : Réaliser des clôtures comptables mensuels | D24: Produire des états financiers fiables présentant la situation financière du projet à fin avril 2026 | E24: NPSP | F24: 46164 | G24: ❌ NON | H24: CONTRÔLE DES COMPTES CLES: Charges, produits, tiers
A25: 2 | B25: 1.11-1 | C25: 1.11-1.3 : Réaliser un audit interne | D25: Préparer l'audit financier du projet LHSPLA de l'exercice 2025 | E25: NPSP | F25: 46174 | G25: ❌ NON | H25: L'activité sera effectué avec un cabinet
A26: 3 | B26: 1.11-1 | C26: 1.11-1.1 : Organiser une mission de collecte et de réconciliation des pièces sur le terrain | D26: Collecter les pièces et finaliser les reconciliations des appuis aux sites décentralisés | E26: NPSP | F26: 46174 | G26: ❌ NON
A27: 4
A28: 5
A29: 6
A30: 7
A31: 8
A32: 9
A33: 10
A34: ↳ Toute activité impliquant le DoS doit être transmise au moins 2 semaines avant son démarrage.
A36: D. POINTS DE VIGILANCE / RISQUES / BESOINS DE DÉCISION
A37: ℹ️ Signaler tout élément nécessitant une attention particulière, une décision ou un arbitrage.
A38: N° | B38: Thème | C38: Catégorie | D38: Description du point | E38: Niveau de criticité | F38: Action attendue / Décision souhaitée
A39: 1
A40: 2
A41: 3
A42: 4
A43: 5

Sheet COM
A1: BULLETIN HEBDOMADAIRE LHSPLA-TA — CANEVAS DE REPORTING ENTITÉ
A2: Entité : Service Communication
A4: A. INFORMATIONS DE SOUMISSION
A5: Entité | C5: Responsable (Nom & Prénom) | E5: Semaine de référence | G5: Date de soumission
A6: COM | E6: =SE!E6 -> Du 25/05 au 29/05/2026 | G6: =SE!G6 -> 46174
A8: B. ACTIVITÉS RÉALISÉES — Semaine précédente
A9: ℹ️ Pour chaque activité réalisée au cours de la semaine écoulée, compléter une ligne.
A10: N° | B10: N° Activités | C10: Libellé de la tâche | D10: Objectifs | E10: Lieu | F10: Date(s) | G10: Principales recommandations / Résultats clés
A11: 1
A12: 2
A13: 3
A14: 4
A15: 5
A16: 6
A17: 7
A18: 8
A19: ↳ Ajouter autant de lignes que nécessaire avant soumission.
A21: C. ACTIVITÉS PLANIFIÉES — Mois glissant (4 semaines à venir)
A22: ℹ️ Lister toutes les activités prévues sur les 4 prochaines semaines. Signaler en ROUGE les activités nécessitant la participation du DoS.
A23: N° | B23: N° Activités | C23: Libellé de la tâche | D23: Objectifs | E23: Lieu | F23: Date(s) prévues | G23: Participation DoS ? | H23: Observations / Points d'attention
A24: 1
A25: 2
A26: 3
A27: 4
A28: 5
A29: 6
A30: 7
A31: 8
A32: 9
A33: 10
A34: ↳ Toute activité impliquant le DoS doit être transmise au moins 2 semaines avant son démarrage.
A36: D. POINTS DE VIGILANCE / RISQUES / BESOINS DE DÉCISION
A37: ℹ️ Signaler tout élément nécessitant une attention particulière, une décision ou un arbitrage.
A38: N° | B38: Thème | C38: Catégorie | D38: Description du point | E38: Niveau de criticité | F38: Action attendue / Décision souhaitée
A39: 1
A40: 2
A41: 3
A42: 4
A43: 5

Sheet COMPILATION
A1: COMPILATION HEBDOMADAIRE — BULLETIN LHSPLA-TA
A2: Semaine de référence : (se renseigne automatiquement à partir des onglets entité) | E2: Semaine du 27 avril au 01 mai 2026
A4: B. ACTIVITÉS RÉALISÉES — Semaine précédente (toutes entités)
A5: CAD – Chaîne d'Approvisionnement Décentralisée
A6: N° | B6: Titre de l'activité | C6: Objectifs | D6: Lieu | E6: Date(s) | F6: Principales recommandations / Résultats clés
A7: 1 | B7: =IF(CAD!C11="","",CAD!C11) -> 1.3-2.4 : Organiser des rencontres d'orientation logistique au niveau départemental | C7: =IF(CAD!D11="","",CAD!D11) -> · Présenter et analyser les résultats des activités logistiques au niveau des ESPC : rapportage et qualité des données rapportées ; disponibilités des stocks de produits traceurs et Système d’Alerte Précoce ; Gestion des stocks et utilisation de mSupply ; données de la File Active. · Identifier les problèmes à la mise en œuvre des activités au niveau des ESPC · Renforcer les capacités des gestionnaires de pharmacie des ESPC · Formuler des recommandations | D7: =IF(CAD!E11="","",CAD!E11) -> DS APA (26/05/2026) | E7: =IF(CAD!F11="","",CAD!F11) -> 46168 | F7: =IF(CAD!G11="","",CAD!G11) -> Nombre d'acteurs des ESPC présents : 14 acteurs; Les acteurs présents ont été sensibilités sur l'importance du respect du délai de dépôt des RM, coachés sur la qualité des données rapportées en passant en revue les erreurs courantes de rapportage (report mensuel des données; mauvaise unité de rapportage; items insuffisamment renseignés; erreurs de calculs; les incohérences régimes et indicateurs), au SAP et sa mise en oeuvre. Aussi, les acteurs ont été orientés sur la gestion des produits iCCM. Quelques recommandations : Organiser les services en responsabilisant les acteurs; Elaborer et transmettre dans les délais les RM; Valider en interne les données avant transmission des rapports au DS; Utiliser correctement toutes les fonctionnalités de mSupply; Estimer correctement les quantités à allouer en tenant compte des consommations réelles et des nombres de jours de rupture notifiés; Mettre en oeuvre le SAP pour anticiper tous risques de rupture et de péremptione
A8: 2 | B8: =IF(CAD!C12="","",CAD!C12) -> 1.3-2.2 : Organiser des visites d'assistance technique aux acteurs de la chaîne d'approvisionnement décentralisée | C8: =IF(CAD!D12="","",CAD!D12) -> Améliorer la qualité du rapportage, la qualité des prestations et de la gestion des produits et intrants des PNS | D8: =IF(CAD!E12="","",CAD!E12) | E8: =IF(CAD!F12="","",CAD!F12) -> Du 25 au 29/05/2026 | F8: =IF(CAD!G12="","",CAD!G12) -> Pas de visite réalisée cette semaine
A9: 3 | B9: =IF(CAD!C13="","",CAD!C13) -> 1.3-2.3 : Apporter un appui technique et financier aux réunions régionales d'analyse et de mise à niveau des stocks | C9: =IF(CAD!D13="","",CAD!D13) -> Accompagner les gestionnaires des sites clients directs dans l'exécution effective des plans de redéploiements des stocks issus des réunions d'analyse | D9: =IF(CAD!E13="","",CAD!E13) -> Suivi de l'execution des plans de redeploiement élaborés et en cours de réalisation | E9: =IF(CAD!F13="","",CAD!F13) -> Du 25 au 29/05/2026 | F9: =IF(CAD!G13="","",CAD!G13) -> 1 plan de redéploiement a été élaboré et en cours de réalisation avec l'appui logistique de LHSPLA. Pour les réunions réalisées la semaine du 11 au 15/05/202, le point de suivi de la réalisation des 4 plans de redéploiement est le suivant : Région Moronou (100%); Région Lôh Djiboua (80%); Région Gôh (80%) et Agnéby-Tiassa (80%)
A10: 4 | B10: =IF(CAD!C14="","",CAD!C14) -> 1.3-1.1 : Faire la mise à jour mensuelle des contacts téléphoniques des prestataires à insérer dans la flotte | C10: =IF(CAD!D14="","",CAD!D14) -> Faciliter les échanges d'informations logistiques des produits de santé du niveau central au niveau communautaire | D10: =IF(CAD!E14="","",CAD!E14) | E10: =IF(CAD!F14="","",CAD!F14) | F10: =IF(CAD!G14="","",CAD!G14)
A11: 5 | B11: =IF(CAD!C15="","",CAD!C15) -> 1.2-1.1 : Faire le suivi la complétude et la promptitude des rapports des sites non clients directs (mSupply, …) | C11: =IF(CAD!D15="","",CAD!D15) -> améliorer la disponibilité des produits traceurs au niveau des sites derservis par les districts | D11: =IF(CAD!E15="","",CAD!E15) -> Régions sanitaires livrées par l'Agence Régionale de Bouaké | E11: =IF(CAD!F15="","",CAD!F15) -> Du 25/05/2026 au 31/05/2026 | F11: =IF(CAD!G15="","",CAD!G15) -> Relance sous forme de rappels dans les groupes watsapp de districts pour les differentes tâches à effectuer avec mSupply;
A12: 6 | B12: =IF(CAD!C16="","",CAD!C16) -> 1.3-2.3 : Apporter un appui technique et financier aux réunions régionales d'analyse et de mise à niveau des stocks | C12: =IF(CAD!D16="","",CAD!D16) -> améliorer la disponibilité des produits traceurs des programmes de sante au niveau de chaque région | D12: =IF(CAD!E16="","",CAD!E16) -> Bélier, Marahoué,Hambol, Haut-Sassandra, Guémon, et Worodougou | E12: =IF(CAD!F16="","",CAD!F16) -> Du 25/05/2026 au 29/05/2026 | F12: =IF(CAD!G16="","",CAD!G16) -> suivi de l'excécution des plans de rédeploiement issus des réunions d'analyse des stocks; le taux est de 100% pour le Worodougou, Bélier et Haut-Sassandra
A13: 7 | B13: =IF(CAD!C17="","",CAD!C17) -> 1.8-2.1 : Organiser des sessions de formation des acteurs de la chaîne d'approvisionnement | C13: =IF(CAD!D17="","",CAD!D17) -> Renforcer less capacité techniques des gestionnaires (APGP, IDE et SFDE) des produits de santé des sites péripheriques | D13: =IF(CAD!E17="","",CAD!E17) -> Yamoussoukro | E13: =IF(CAD!F17="","",CAD!F17) -> 27/05/2026 au 31/05/2026 | F13: =IF(CAD!G17="","",CAD!G17) -> Formation de 15 acteurs des ESPC et districts surl'optimisation de la gestion des stocks des produits de santé; entreposage et stockage; prise en main de mSupply; Système d'Alerte Précoce et Assistance Technique. La progression des apprenants etait significative à l'issu des pré et Post-Test
A14: 8 | B14: =IF(CAD!C18="","",CAD!C18) | C14: =IF(CAD!D18="","",CAD!D18) | D14: =IF(CAD!E18="","",CAD!E18) | E14: =IF(CAD!F18="","",CAD!F18) | F14: =IF(CAD!G18="","",CAD!G18)
A16: PMO – Gestion de Projet (Project Management Office)
A17: N° | B17: Titre de l'activité | C17: Objectifs | D17: Lieu | E17: Date(s) | F17: Principales recommandations / Résultats clés
A18: 1 | B18: =IF(PMO!C11="","",PMO!C11) | C18: =IF(PMO!D11="","",PMO!D11) | D18: =IF(PMO!E11="","",PMO!E11) | E18: =IF(PMO!F11="","",PMO!F11) | F18: =IF(PMO!G11="","",PMO!G11)
A19: 2 | B19: =IF(PMO!C12="","",PMO!C12) | C19: =IF(PMO!D12="","",PMO!D12) | D19: =IF(PMO!E12="","",PMO!E12) | E19: =IF(PMO!F12="","",PMO!F12) | F19: =IF(PMO!G12="","",PMO!G12)
A20: 3 | B20: =IF(PMO!C13="","",PMO!C13) | C20: =IF(PMO!D13="","",PMO!D13) | D20: =IF(PMO!E13="","",PMO!E13) | E20: =IF(PMO!F13="","",PMO!F13) | F20: =IF(PMO!G13="","",PMO!G13)
A21: 4 | B21: =IF(PMO!C14="","",PMO!C14) | C21: =IF(PMO!D14="","",PMO!D14) | D21: =IF(PMO!E14="","",PMO!E14) | E21: =IF(PMO!F14="","",PMO!F14) | F21: =IF(PMO!G14="","",PMO!G14)
A22: 5 | B22: =IF(PMO!C15="","",PMO!C15) | C22: =IF(PMO!D15="","",PMO!D15) | D22: =IF(PMO!E15="","",PMO!E15) | E22: =IF(PMO!F15="","",PMO!F15) | F22: =IF(PMO!G15="","",PMO!G15)
A23: 6 | B23: =IF(PMO!C16="","",PMO!C16) | C23: =IF(PMO!D16="","",PMO!D16) | D23: =IF(PMO!E16="","",PMO!E16) | E23: =IF(PMO!F16="","",PMO!F16) | F23: =IF(PMO!G16="","",PMO!G16)
A24: 7 | B24: =IF(PMO!C17="","",PMO!C17) | C24: =IF(PMO!D17="","",PMO!D17) | D24: =IF(PMO!E17="","",PMO!E17) | E24: =IF(PMO!F17="","",PMO!F17) | F24: =IF(PMO!G17="","",PMO!G17)
A25: 8 | B25: =IF(PMO!C18="","",PMO!C18) | C25: =IF(PMO!D18="","",PMO!D18) | D25: =IF(PMO!E18="","",PMO!E18) | E25: =IF(PMO!F18="","",PMO!F18) | F25: =IF(PMO!G18="","",PMO!G18)
A27: QAD – Quantifiction Achat et Distribution
A28: N° | B28: Titre de l'activité | C28: Objectifs | D28: Lieu | E28: Date(s) | F28: Principales recommandations / Résultats clés
A29: 1 | B29: =IF(QAD!C11="","",QAD!C11) -> 1.10-1.1 : Participer aux réunions de suivi mensuel de stock des PNS | C29: =IF(QAD!D11="","",QAD!D11) -> * Suivi mensuel des stocks et des PA pour une disponibilité adéquate des produits à tous les niveaux de la chaine d'approvisionnement pour réduire les risques de rupture et de péremption | D29: =IF(QAD!E11="","",QAD!E11) -> En ligne | E29: =IF(QAD!F11="","",QAD!F11) -> 46168 | F29: =IF(QAD!G11="","",QAD!G11) -> *Principales recommandations pour la NPSP* Fournir la date probable de livraison du reliquat des produits de prémière ligne sous BGE Actualiser le eSigl et le fichier suivi de stock en y rétirant l'amikacine inj Retarder la prochaine commande de Bedaquiline 20mg du fait du surstock observé au niveau central comme péripherique sur ce produit ( fin septembre au lieu de fin juin 2026)
A30: 2 | B30: =IF(QAD!C12="","",QAD!C12) -> 3.2-1.2 : Mettre à disposition des transitaires la documentation requise pour organiser l'acheminement | C30: =IF(QAD!D12="","",QAD!D12) -> * Disponibilité rapide des produits dans les entrepôts NPSP | D30: =IF(QAD!E12="","",QAD!E12) -> ABIDJAN | E30: =IF(QAD!F12="","",QAD!F12) -> 46171 | F30: =IF(QAD!G12="","",QAD!G12) -> * Résultats clés* Transmission des observations (date d'effet) sur le document projet d'exonération sur les acquisitions planifiées sur budget du Gouvernement Américain
A31: 3 | B31: =IF(QAD!C13="","",QAD!C13) -> 2.6-5.9 : Organiser quatre sessions d'orientation des Acteurs de la gestion logistique | C31: =IF(QAD!D13="","",QAD!D13) -> Renforcer les capacités des gestionnaires et techniciens de laboratoire en gestion logistique des produits de la charge virale | D31: =IF(QAD!E13="","",QAD!E13) -> ABIDJAN | E31: =IF(QAD!F13="","",QAD!F13) -> 46170 | F31: =IF(QAD!G13="","",QAD!G13) -> Renforcement des capacités de 18 personnes (pharmacie et laboratoire) sur la gestion des produits de mPima et des consommables généraux relatifs aux produits de laboratoire.
A32: 4 | B32: =IF(QAD!C14="","",QAD!C14) -> 2.2-1.4 : Mettre en place un fichier de suivi intégré de la reception des produits à la levée de quarantaine de ces produits | C32: =IF(QAD!D14="","",QAD!D14) -> Respect des délais objectivés | D32: =IF(QAD!E14="","",QAD!E14) -> Abidjan | E32: =IF(QAD!F14="","",QAD!F14) -> 25 au 29 mai | F32: =IF(QAD!G14="","",QAD!G14) -> Finaliser la correspondance entre les désignation/code QAT et Sage X3 pour transmission interne
A33: 5 | B33: =IF(QAD!C15="","",QAD!C15) -> 2.2-3.1 : Organiser 3 inventaires des produits traceurs des programmes suivis | C33: =IF(QAD!D15="","",QAD!D15) -> Améliorer la précision et la justesse des stocks | D33: =IF(QAD!E15="","",QAD!E15) -> Abidjan | E33: =IF(QAD!F15="","",QAD!F15) -> 30 mai au 03 juin | F33: =IF(QAD!G15="","",QAD!G15) -> Améliorer la communication interne concernant l'inventaire tournant.
A34: 6 | B34: =IF(QAD!C16="","",QAD!C16) -> 2.2-2.2 : Faire le suivi hebdomadaire de l'exécution du plan de réapprovisionnement | C34: =IF(QAD!D16="","",QAD!D16) -> Améliorer la disponibilité des produits dans les agences de distribution | D34: =IF(QAD!E16="","",QAD!E16) -> Abidjan | E34: =IF(QAD!F16="","",QAD!F16) -> 25 au 31 mai | F34: =IF(QAD!G16="","",QAD!G16) -> Aborder ce point lors des prochaines réunions avec les parties prenantes car les délais objectivés sont difficilement attteints
A35: 7 | B35: =IF(QAD!C17="","",QAD!C17) -> 2.2-3.2 : Faire le suivi de la prise en compte des écarts relevés lors de chaque inventaire | C35: =IF(QAD!D17="","",QAD!D17) -> Améliorer la précision et la justesse des stocks | D35: =IF(QAD!E17="","",QAD!E17) -> Abidjan | E35: =IF(QAD!F17="","",QAD!F17) -> 25 au 31 mai | F35: =IF(QAD!G17="","",QAD!G17)
A36: 8 | B36: =IF(QAD!C18="","",QAD!C18) | C36: =IF(QAD!D18="","",QAD!D18) | D36: =IF(QAD!E18="","",QAD!E18) | E36: =IF(QAD!F18="","",QAD!F18) | F36: =IF(QAD!G18="","",QAD!G18)
A38: SE – Suivi & Évaluation (MEL)
A39: N° | B39: Titre de l'activité | C39: Objectifs | D39: Lieu | E39: Date(s) | F39: Principales recommandations / Résultats clés
A40: 3 | B40: =IF(SE!C11="","",SE!C11) | C40: =IF(SE!D11="","",SE!D11) | D40: =IF(SE!E11="","",SE!E11) | E40: =IF(SE!F11="","",SE!F11) | F40: =IF(SE!G11="","",SE!G11)
A41: 4 | B41: =IF(SE!C12="","",SE!C12) | C41: =IF(SE!D12="","",SE!D12) | D41: =IF(SE!E12="","",SE!E12) | E41: =IF(SE!F12="","",SE!F12) | F41: =IF(SE!G12="","",SE!G12)
A42: 5 | B42: =IF(SE!C13="","",SE!C13) | C42: =IF(SE!D13="","",SE!D13) | D42: =IF(SE!E13="","",SE!E13) | E42: =IF(SE!F13="","",SE!F13) | F42: =IF(SE!G13="","",SE!G13)
A43: 6 | B43: =IF(SE!C14="","",SE!C14) | C43: =IF(SE!D14="","",SE!D14) | D43: =IF(SE!E14="","",SE!E14) | E43: =IF(SE!F14="","",SE!F14) | F43: =IF(SE!G14="","",SE!G14)
A44: 7 | B44: =IF(SE!C15="","",SE!C15) | C44: =IF(SE!D15="","",SE!D15) | D44: =IF(SE!E15="","",SE!E15) | E44: =IF(SE!F15="","",SE!F15) | F44: =IF(SE!G15="","",SE!G15)
A45: 8 | B45: =IF(SE!C16="","",SE!C16) | C45: =IF(SE!D16="","",SE!D16) | D45: =IF(SE!E16="","",SE!E16) | E45: =IF(SE!F16="","",SE!F16) | F45: =IF(SE!G16="","",SE!G16)
A47: SI – Système d'Information
A48: N° | B48: Titre de l'activité | C48: Objectifs | D48: Lieu | E48: Date(s) | F48: Principales recommandations / Résultats clés
A49: 1 | B49: =IF(SI!C11="","",SI!C11) | C49: =IF(SI!D11="","",SI!D11) | D49: =IF(SI!E11="","",SI!E11) | E49: =IF(SI!F11="","",SI!F11) | F49: =IF(SI!G11="","",SI!G11)
A50: 2 | B50: =IF(SI!C12="","",SI!C12) | C50: =IF(SI!D12="","",SI!D12) | D50: =IF(SI!E12="","",SI!E12) | E50: =IF(SI!F12="","",SI!F12) | F50: =IF(SI!G12="","",SI!G12)
A51: 3 | B51: =IF(SI!C13="","",SI!C13) | C51: =IF(SI!D13="","",SI!D13) | D51: =IF(SI!E13="","",SI!E13) | E51: =IF(SI!F13="","",SI!F13) | F51: =IF(SI!G13="","",SI!G13)
A52: 4 | B52: =IF(SI!C14="","",SI!C14) | C52: =IF(SI!D14="","",SI!D14) | D52: =IF(SI!E14="","",SI!E14) | E52: =IF(SI!F14="","",SI!F14) | F52: =IF(SI!G14="","",SI!G14)
A53: 5 | B53: =IF(SI!C15="","",SI!C15) | C53: =IF(SI!D15="","",SI!D15) | D53: =IF(SI!E15="","",SI!E15) | E53: =IF(SI!F15="","",SI!F15) | F53: =IF(SI!G15="","",SI!G15)
A54: 6 | B54: =IF(SI!C16="","",SI!C16) | C54: =IF(SI!D16="","",SI!D16) | D54: =IF(SI!E16="","",SI!E16) | E54: =IF(SI!F16="","",SI!F16) | F54: =IF(SI!G16="","",SI!G16)
A55: 7 | B55: =IF(SI!C17="","",SI!C17) | C55: =IF(SI!D17="","",SI!D17) | D55: =IF(SI!E17="","",SI!E17) | E55: =IF(SI!F17="","",SI!F17) | F55: =IF(SI!G17="","",SI!G17)
A56: 8 | B56: =IF(SI!C18="","",SI!C18) | C56: =IF(SI!D18="","",SI!D18) | D56: =IF(SI!E18="","",SI!E18) | E56: =IF(SI!F18="","",SI!F18) | F56: =IF(SI!G18="","",SI!G18)
A58: FINANCES — Service Finances
A59: N° | B59: Titre de l'activité | C59: Objectifs | D59: Lieu | E59: Date(s) | F59: Principales recommandations / Résultats clés
A60: 1 | B60: =IF(FINANCES!C11="","",FINANCES!C11) -> 1.11-1.12 : Acquisition de stickers pour le matériel acquis par le projet | C60: =IF(FINANCES!D11="","",FINANCES!D11) -> Référencer et identifier le matériel acquis dans le cadre du projet LHSPLA | D60: =IF(FINANCES!E11="","",FINANCES!E11) -> Abidjan | E60: =IF(FINANCES!F11="","",FINANCES!F11) -> 46164 | F60: =IF(FINANCES!G11="","",FINANCES!G11) -> Finaliser les code QR
A61: 2 | B61: =IF(FINANCES!C12="","",FINANCES!C12) -> 1.11-1.11 : Equiper le personnel du projet en matériel informatique | C61: =IF(FINANCES!D12="","",FINANCES!D12) -> Renforcer les capacités opérationnelles et le système d'information de l’équipe projet LHSPLA | D61: =IF(FINANCES!E12="","",FINANCES!E12) -> Abidjan | E61: =IF(FINANCES!F12="","",FINANCES!F12) -> 46164 | F61: =IF(FINANCES!G12="","",FINANCES!G12) -> Finaliser le paiement d'un acompte au fournisseur.
A62: 3 | B62: =IF(FINANCES!C13="","",FINANCES!C13) -> 1.11-1.9 : Rémunération des agents LHSPLA. | C62: =IF(FINANCES!D13="","",FINANCES!D13) -> Déterminer la quote part de chaque financement dans les refacturation de salaires d'avril à septembre 2026 | D62: =IF(FINANCES!E13="","",FINANCES!E13) -> Abidjan | E62: =IF(FINANCES!F13="","",FINANCES!F13) -> 46155 | F62: =IF(FINANCES!G13="","",FINANCES!G13) -> Proposition de quote part COP=49% MOP=19% MCH=32%
A63: 4 | B63: =IF(FINANCES!C14="","",FINANCES!C14) -> 1.11-1.5 : Atelier de formation sur les méthodes de réconciliations des pièces comptables | C63: =IF(FINANCES!D14="","",FINANCES!D14) -> Création d'un outil permettant de générer des budgets de TDR | D63: =IF(FINANCES!E14="","",FINANCES!E14) -> Abidjan | E63: =IF(FINANCES!F14="","",FINANCES!F14) -> 46164 | F63: =IF(FINANCES!G14="","",FINANCES!G14) -> Cahier de charge transmis au SI Vidéo demonstrative effectuée Test de l'outil
A64: 5 | B64: =IF(FINANCES!C15="","",FINANCES!C15) -> 1.11-1.2 : Réaliser des clôtures comptables mensuels | C64: =IF(FINANCES!D15="","",FINANCES!D15) -> Editer les liquidations d'octobre 2025 à Avril 2026 pour approbation | D64: =IF(FINANCES!E15="","",FINANCES!E15) -> Abidjan | E64: =IF(FINANCES!F15="","",FINANCES!F15) -> 46162 | F64: =IF(FINANCES!G15="","",FINANCES!G15) -> Raport financier présentant les charges et les dépenses effectuées de la période
A65: 6 | B65: =IF(FINANCES!C16="","",FINANCES!C16) -> 1.11-1.2 : Réaliser des clôtures comptables mensuels | C65: =IF(FINANCES!D16="","",FINANCES!D16) -> Editer les appels de fonds de juin à septembre 2026 pour approbation | D65: =IF(FINANCES!E16="","",FINANCES!E16) -> Abidjan | E65: =IF(FINANCES!F16="","",FINANCES!F16) -> 46162 | F65: =IF(FINANCES!G16="","",FINANCES!G16) -> Appels de fonds de juin à septembre 2026
A66: 7 | B66: =IF(FINANCES!C17="","",FINANCES!C17) | C66: =IF(FINANCES!D17="","",FINANCES!D17) | D66: =IF(FINANCES!E17="","",FINANCES!E17) | E66: =IF(FINANCES!F17="","",FINANCES!F17) | F66: =IF(FINANCES!G17="","",FINANCES!G17)
A67: 8 | B67: =IF(FINANCES!C18="","",FINANCES!C18) | C67: =IF(FINANCES!D18="","",FINANCES!D18) | D67: =IF(FINANCES!E18="","",FINANCES!E18) | E67: =IF(FINANCES!F18="","",FINANCES!F18) | F67: =IF(FINANCES!G18="","",FINANCES!G18)
A69: CAC - Chaine d'Approvisionnement Décentralisée
A70: N° | B70: Titre de l'activité | C70: Objectifs | D70: Lieu | E70: Date(s) | F70: Principales recommandations / Résultats clés
A71: 1 | B71: =IF(CAC!C11="","",CAC!C11) -> 1.4-1.4 : Faire le suivi de la disponibilité des produits de santé communautaires | C71: =IF(CAC!D11="","",CAC!D11) -> Mission de suivi des recommandations EUV et de coaching des CAC et ASS dans les districts Tiassalé, 2 ESPC 5DR Ahoara et CSU Morokro) caoching au remplissage du registre ASC et au Weekly Report Communautaire. Diffusion du Weekly aux ASS et CAC. | D71: =IF(CAC!E11="","",CAC!E11) -> DS TIASSALE | E71: =IF(CAC!F11="","",CAC!F11) -> Du 28 au 29 Mai 2026 | F71: =IF(CAC!G11="","",CAC!G11) -> Continuer le coaching au rapportage et au remplissage correcte du rapport ASC dans e-SIGL
A72: 2 | B72: =IF(CAC!C12="","",CAC!C12) -> 2.2-3.1 : Organiser 3 inventaires des produits traceurs des programmes suivis | C72: =IF(CAC!D12="","",CAC!D12) -> Réalisation de l'inventaire tournant à l'agence programme du 30 au 31 Mai 2026 | D72: =IF(CAC!E12="","",CAC!E12) -> Agence programme | E72: =IF(CAC!F12="","",CAC!F12) -> du 16 au 20 Mai 2026 | F72: =IF(CAC!G12="","",CAC!G12) -> Inventaire physique réalisé, finalisation de la justification des écarts et de la redaction du rapport en cours
A73: 3 | B73: =IF(CAC!C13="","",CAC!C13) | C73: =IF(CAC!D13="","",CAC!D13) | D73: =IF(CAC!E13="","",CAC!E13) | E73: =IF(CAC!F13="","",CAC!F13) | F73: =IF(CAC!G13="","",CAC!G13)
A74: 4 | B74: =IF(CAC!C14="","",CAC!C14) | C74: =IF(CAC!D14="","",CAC!D14) | D74: =IF(CAC!E14="","",CAC!E14) | E74: =IF(CAC!F14="","",CAC!F14) | F74: =IF(CAC!G14="","",CAC!G14)
A75: 5 | B75: =IF(CAC!C15="","",CAC!C15) | C75: =IF(CAC!D15="","",CAC!D15) | D75: =IF(CAC!E15="","",CAC!E15) | E75: =IF(CAC!F15="","",CAC!F15) | F75: =IF(CAC!G15="","",CAC!G15)
A76: 6 | B76: =IF(CAC!C16="","",CAC!C16) | C76: =IF(CAC!D16="","",CAC!D16) | D76: =IF(CAC!E16="","",CAC!E16) | E76: =IF(CAC!F16="","",CAC!F16) | F76: =IF(CAC!G16="","",CAC!G16)
A77: 7 | B77: =IF(CAC!C17="","",CAC!C17) | C77: =IF(CAC!D17="","",CAC!D17) | D77: =IF(CAC!E17="","",CAC!E17) | E77: =IF(CAC!F17="","",CAC!F17) | F77: =IF(CAC!G17="","",CAC!G17)
A78: 8 | B78: =IF(CAC!C18="","",CAC!C18) | C78: =IF(CAC!D18="","",CAC!D18) | D78: =IF(CAC!E18="","",CAC!E18) | E78: =IF(CAC!F18="","",CAC!F18) | F78: =IF(CAC!G18="","",CAC!G18)
A80: COM — Service Communication
A81: N° | B81: Titre de l'activité | C81: Objectifs | D81: Lieu | E81: Date(s) | F81: Principales recommandations / Résultats clés
A82: 1 | B82: =IF(COM!C11="","",COM!C11) | C82: =IF(COM!D11="","",COM!D11) | D82: =IF(COM!E11="","",COM!E11) | E82: =IF(COM!F11="","",COM!F11) | F82: =IF(COM!G11="","",COM!G11)
A83: 2 | B83: =IF(COM!C12="","",COM!C12) | C83: =IF(COM!D12="","",COM!D12) | D83: =IF(COM!E12="","",COM!E12) | E83: =IF(COM!F12="","",COM!F12) | F83: =IF(COM!G12="","",COM!G12)
A84: 3 | B84: =IF(COM!C13="","",COM!C13) | C84: =IF(COM!D13="","",COM!D13) | D84: =IF(COM!E13="","",COM!E13) | E84: =IF(COM!F13="","",COM!F13) | F84: =IF(COM!G13="","",COM!G13)
A85: 4 | B85: =IF(COM!C14="","",COM!C14) | C85: =IF(COM!D14="","",COM!D14) | D85: =IF(COM!E14="","",COM!E14) | E85: =IF(COM!F14="","",COM!F14) | F85: =IF(COM!G14="","",COM!G14)
A86: 5 | B86: =IF(COM!C15="","",COM!C15) | C86: =IF(COM!D15="","",COM!D15) | D86: =IF(COM!E15="","",COM!E15) | E86: =IF(COM!F15="","",COM!F15) | F86: =IF(COM!G15="","",COM!G15)
A87: 6 | B87: =IF(COM!C16="","",COM!C16) | C87: =IF(COM!D16="","",COM!D16) | D87: =IF(COM!E16="","",COM!E16) | E87: =IF(COM!F16="","",COM!F16) | F87: =IF(COM!G16="","",COM!G16)
A88: 7 | B88: =IF(COM!C17="","",COM!C17) | C88: =IF(COM!D17="","",COM!D17) | D88: =IF(COM!E17="","",COM!E17) | E88: =IF(COM!F17="","",COM!F17) | F88: =IF(COM!G17="","",COM!G17)
A89: 8 | B89: =IF(COM!C18="","",COM!C18) | C89: =IF(COM!D18="","",COM!D18) | D89: =IF(COM!E18="","",COM!E18) | E89: =IF(COM!F18="","",COM!F18) | F89: =IF(COM!G18="","",COM!G18)
A92: C. ACTIVITÉS PLANIFIÉES — Mois glissant (toutes entités)
A93: CAD – Chaîne d'Approvisionnement Décentralisée
A94: N° | B94: Titre de l'activité | C94: Objectifs | D94: Lieu | E94: Date(s) prévues | F94: Participation DoS ? | G94: Observations / Points d'attention
A95: 1 | B95: =IF(CAD!C24="","",CAD!C24) -> 1.3-2.3 : Apporter un appui technique et financier aux réunions régionales d'analyse et de mise à niveau des stocks | C95: =IF(CAD!D24="","",CAD!D24) -> - Faire le point des recommandations ( suivi du taux de redéploiement, etc.) de la dernière réunion - Faciliter la prise en main du “Weekly Report” pour l’analyse des niveaux de stocks au niveau régional et la prise de décision. - Effectuer les analyses avec les données disponibles pour une prise de décision - Discuter des autres activités et identifier les problèmes à la gestion de la chaîne d’approvisionnement - Proposer un plan d’amélioration ( plans de redéploiements) - Formuler des recommandations | D95: =IF(CAD!E24="","",CAD!E24) -> Régions sanitaires Gbôklê; N'zi et Grands Ponts | E95: =IF(CAD!F24="","",CAD!F24) -> Du 08 au 12/06/2026 | F95: =IF(CAD!G24="","",CAD!G24) -> ❌ NON | G95: =IF(CAD!H24="","",CAD!H24) -> Activité reprogrammée : DS Gbôklê (12/06/2026); DS N'zi (date pas encore communiquée); GRANDS PONTS (date pas encore communiquée)
A96: 2 | B96: =IF(CAD!C26="","",CAD!C26) -> 1.3-2.4 : Organiser des rencontres d'orientation logistique au niveau départemental | C96: =IF(CAD!D26="","",CAD!D26) -> · Présenter et analyser les résultats des activités logistiques au niveau des ESPC : rapportage et qualité des données rapportées ; disponibilités des stocks de produits traceurs et Système d’Alerte Précoce ; Gestion des stocks et utilisation de mSupply ; données de la File Active. · Identifier les problèmes à la mise en œuvre des activités au niveau des ESPC · Renforcer les capacités des gestionnaires de pharmacie des ESPC · Formuler des recommandations | D96: =IF(CAD!E26="","",CAD!E26) -> DS DIVO; DS DABOU; DS DOROPO et DS Alépé | E96: =IF(CAD!F26="","",CAD!F26) -> 01 au 12/06/2026 | F96: =IF(CAD!G26="","",CAD!G26) -> ❌ NON | G96: =IF(CAD!H26="","",CAD!H26) -> DS DIVO (date pas encore communiquée); DS DABOU (date pas encore communiquée) DS DOROPO (date pas encore communiquée) et DS Alépé (prévue le 29/05/2026; reprogrammée à une date ultérieure pour conflit de calendrier)
A97: 3 | B97: =IF(CAD!C27="","",CAD!C27) -> 1.3-2.4 : Organiser des rencontres d'orientation logistique au niveau départemental | C97: =IF(CAD!D27="","",CAD!D27) -> · Présenter et analyser les résultats des activités logistiques au niveau des ESPC des trois derniers mois (Mars,Avril et MAI): rapportage et qualité des données rapportées ; disponibilités des stocks de produits traceurs et Système d’Alerte Précoce ; Gestion des stocks et utilisation de mSupply ; données de la File Active. · Identifier les problèmes à la mise en œuvre des activités au niveau des ESPC · Renforcer les capacités des gestionnaires de pharmacie des ESPC · Formuler des recommandations | D97: =IF(CAD!E27="","",CAD!E27) -> Korhogo 2, Dikodougou, Niakara, Katiola, Botro, Béoumi, Bouaké nord ouest, Mankono, Yamousoukro, Toumodi, Odiénné, Madinani, Zouan-Hounien, Bloléquin, Zoukougbeu, Vavoua, Issia ,Bouaflé, Kani et Kounahiri | E97: =IF(CAD!F27="","",CAD!F27) -> 08/06/2026 au 19/06/2026 | F97: =IF(CAD!G27="","",CAD!G27) -> ❌ NON | G97: =IF(CAD!H27="","",CAD!H27) -> réception des TDR de 08 sites ; préparation avec les Pharmaciens de Districts pour le bon deroulement de ses rencontres
A98: 4 | B98: =IF(CAD!C28="","",CAD!C28) -> 1.3-2.2 : Organiser des visites d'assistance technique aux acteurs de la chaîne d'approvisionnement décentralisée | C98: =IF(CAD!D28="","",CAD!D28) -> effectuer des visites de sites à faibles resultats, travailler avec le site sur:rapportage et qualité des données rapportées ; disponibilités des stocks de produits traceurs et Système d’Alerte Précoce ; Gestion des stocks et utilisation de mSupply ; données de la File Active. | D98: =IF(CAD!E28="","",CAD!E28) -> sites à identifier par PRES dans la zone couverte par CAD BOUAKE | E98: =IF(CAD!F28="","",CAD!F28) -> du 15/06/26 au 25/06/26 | F98: =IF(CAD!G28="","",CAD!G28) -> ❌ NON | G98: =IF(CAD!H28="","",CAD!H28) -> identification de sites selon des points précis de mauvaises performance
A99: 5 | B99: =IF(CAD!C29="","",CAD!C29) -> 1.2-1.1 : Faire le suivi la complétude et la promptitude des rapports des sites non clients directs (mSupply, …) | C99: =IF(CAD!D29="","",CAD!D29) -> Assister les sites au rapportage ,dans les délais, des sites clients directs NPSP | D99: =IF(CAD!E29="","",CAD!E29) -> sites CAD Bouaké | E99: =IF(CAD!F29="","",CAD!F29) -> du 11/05/26 au 31/05/26 | F99: =IF(CAD!G29="","",CAD!G29) -> ❌ NON | G99: =IF(CAD!H29="","",CAD!H29) -> Disponibilité à 100% des données logistiques pour la prise de décision
A100: 6 | B100: =IF(CAD!C30="","",CAD!C30) -> 1.3-1.2 : Fournir des forfaits de communication et de connexion internet aux structures du niveau central jusqu'au niveau communautaire. | C100: =IF(CAD!D30="","",CAD!D30) -> maintenir les sites clients directs NPSP dans la flotte pour faciliter la communication | D100: =IF(CAD!E30="","",CAD!E30) -> CAD Bouaké | E100: =IF(CAD!F30="","",CAD!F30) -> en continue | F100: =IF(CAD!G30="","",CAD!G30) -> ❌ NON | G100: =IF(CAD!H30="","",CAD!H30) -> Maintien de tous les numéros des sites dans la flotte compte tenu du turn over des gestionnaires
A101: 7 | B101: =IF(CAD!C31="","",CAD!C31) -> 1.4-1.3 : Apporter un appui technique et financier au district sanitaire pour le suivi de la distribution communautaire | C101: =IF(CAD!D31="","",CAD!D31) -> Renforcer la disponibilité des CTA et autres ILP en vue d’une meilleure performance de l’ICCM au niveau communautaire | D101: =IF(CAD!E31="","",CAD!E31) -> CAD Abidjan | E101: =IF(CAD!F31="","",CAD!F31) -> Du 11/05/2026 au 31/05/2026 | F101: =IF(CAD!G31="","",CAD!G31) -> ❌ NON | G101: =IF(CAD!H31="","",CAD!H31) -> Appui technique à l'élaboration des TDR et à la programmation des visites des DS
A102: 8 | B102: =IF(CAD!C32="","",CAD!C32) -> 1.8-2.1 : Organiser des sessions de formation des acteurs de la chaîne d'approvisionnement | C102: =IF(CAD!D32="","",CAD!D32) -> Renforcer less capacité techniques des gestionnaires (APGP, IDE et SFDE) des produits de santé des sites péripheriques | D102: =IF(CAD!E32="","",CAD!E32) -> Yamoussoukro | E102: =IF(CAD!F32="","",CAD!F32) -> 01/06/26 au 06/06/26 | F102: =IF(CAD!G32="","",CAD!G32) -> ❌ NON | G102: =IF(CAD!H32="","",CAD!H32) -> Formation de 30 acteurs (APGP,IDE, SFDE) attendus; des Tests prévus; briefing des formateurs afin de prendre en compte les leçons apprises de la formation du groupe precédant
A103: 9 | B103: =IF(CAD!C33="","",CAD!C33) -> 1.2-1.1 : Faire le suivi la complétude et la promptitude des rapports des sites non clients directs (mSupply, …) | C103: =IF(CAD!D33="","",CAD!D33) -> améliorer le rapportage des sites périphériques | D103: =IF(CAD!E33="","",CAD!E33) -> CAD Bouaké | E103: =IF(CAD!F33="","",CAD!F33) -> Du 18 au 31/05/2026 | F103: =IF(CAD!G33="","",CAD!G33) -> ❌ NON | G103: =IF(CAD!H33="","",CAD!H33) -> sensibiliser les gestionnaires sur la gestion des produits périmés afin d'eviter de les rapportés comme produits disponibles et utilisables
A104: 10 | B104: =IF(CAD!C34="","",CAD!C34) -> 1.3-2.7 : Organiser une orientation des pharmaciens de régions sur le management de la CA | C104: =IF(CAD!D34="","",CAD!D34) -> Renforcer les compétence en management et en leadership des PR pour assurer la gouvernance efficace et une redevabilité accrue de la chaine d'approvisionnement pharmaceutique décentralisée | D104: =IF(CAD!E34="","",CAD!E34) -> YAMOUSOUKRO | E104: =IF(CAD!F34="","",CAD!F34) -> 08 au 12/06/2026 | F104: =IF(CAD!G34="","",CAD!G34) -> ❌ NON | G104: =IF(CAD!H34="","",CAD!H34) -> Elaboration des plan de contingence des 10 régions participants afin d'améliorer la disponibilité des produits de santé dans leurs points de prestations de service. Partage d'expériences et de bonnes pratiques de gestion de chaine d'approvisionnement
A106: PMO — PMO – Gestion de Projet (Project Management Office)
A107: N° | B107: Titre de l'activité | C107: Objectifs | D107: Lieu | E107: Date(s) prévues | F107: Participation DoS ? | G107: Observations / Points d'attention
A108: 1 | B108: =IF(PMO!C24="","",PMO!C24) -> 1.11-3.2 : Organiser des réunions mensuelles du bilan de la performance du projet | C108: =IF(PMO!D24="","",PMO!D24) -> Faire le reporting détaillé des activités du projet sur le mois précédent par acteur | D108: =IF(PMO!E24="","",PMO!E24) -> Abidjan Nouvelle PSP-CI | E108: =IF(PMO!F24="","",PMO!F24) -> 46189 | F108: =IF(PMO!G24="","",PMO!G24) -> ❌ NON | G108: =IF(PMO!H24="","",PMO!H24) -> *Réunion mois de juin 2026 *Causes de la non-réalisation des activités *Résolution des insatisfactions
A109: 2 | B109: =IF(PMO!C25="","",PMO!C25) -> 1.11-4.1 : Faire la maintenance annuelle ORCHESTRA | C109: =IF(PMO!D25="","",PMO!D25) -> Maintenance annuelle et assistance pour le logiciel de suivi du projet LHSPLA | D109: =IF(PMO!E25="","",PMO!E25) -> Abidjan Nouvelle PSP-CI | E109: =IF(PMO!F25="","",PMO!F25) | F109: =IF(PMO!G25="","",PMO!G25) -> ❌ NON | G109: =IF(PMO!H25="","",PMO!H25) -> *Aucune suite pour le paiement de la maintenance *Risque de bugs lors d'utilisation de Orchestra
A110: 3 | B110: =IF(PMO!C26="","",PMO!C26) -> 1.8-3.1 : Appuyer les gestionnaires des structures sanitaires publiques dans le cadre de leurs activités | C110: =IF(PMO!D26="","",PMO!D26) -> Amélioration des compétences du pool de formateurs pour des formations et des coachings de qualité fait à l'endroit des gestionnaires des structures sanitaires publiques | D110: =IF(PMO!E26="","",PMO!E26) -> Yamoussoukro | E110: =IF(PMO!F26="","",PMO!F26) -> Date à définir | F110: =IF(PMO!G26="","",PMO!G26) -> ❌ NON | G110: =IF(PMO!H26="","",PMO!H26) -> Apprentissage de l'andragogie. en deux phases : phase pratique et phase théorique
A111: 4 | B111: =IF(PMO!C27="","",PMO!C27) -> 1.11-3.1 : Compiler mensuellement les rapports de progression dans le logiciel ORCHESTRA | C111: =IF(PMO!D27="","",PMO!D27) -> Orchestra est à jour | D111: =IF(PMO!E27="","",PMO!E27) -> Abidjan Nouvelle PSP-CI | E111: =IF(PMO!F27="","",PMO!F27) -> du 04 au 05/06/2026 | F111: =IF(PMO!G27="","",PMO!G27) -> ❌ NON | G111: =IF(PMO!H27="","",PMO!H27) -> Extraction des niveaux d'avancement par entité et transmission des extractions à chaque entité
...

Sheet BulletinDu_25-29mai2026
A1: COMPILATION HEBDOMADAIRE — BULLETIN LHSPLA-TA
A2: Semaine de référence : (se renseigne automatiquement à partir des onglets entité) | E2: Semaine du 25 au 29 mai 2026
A4: B. ACTIVITÉS RÉALISÉES — Semaine précédente (toutes entités)
A5: CAD – Chaîne d'Approvisionnement Décentralisée
A6: N° | B6: Titre de l'activité | C6: Objectifs | D6: Lieu | E6: Date(s) | F6: Principales recommandations / Résultats clés
A7: 1 | B7: 1.3-2.4 : Organiser des rencontres d'orientation logistique au niveau départemental | C7: · Présenter et analyser les résultats des activités logistiques au niveau des ESPC : rapportage et qualité des données rapportées ; disponibilités des stocks de produits traceurs et Système d’Alerte Précoce ; Gestion des stocks et utilisation de mSupply ; données de la File Active. · Identifier les problèmes à la mise en œuvre des activités au niveau des ESPC · Renforcer les capacités des gestionnaires de pharmacie des ESPC · Formuler des recommandations | D7: DS APA (26/05/2026) | E7: 46168 | F7: Nombre d'acteurs des ESPC présents : 14 acteurs; Les acteurs présents ont été sensibilités sur l'importance du respect du délai de dépôt des RM, coachés sur la qualité des données rapportées en passant en revue les erreurs courantes de rapportage (report mensuel des données; mauvaise unité de rapportage; items insuffisamment renseignés; erreurs de calculs; les incohérences régimes et indicateurs), au SAP et sa mise en oeuvre. Aussi, les acteurs ont été orientés sur la gestion des produits iCCM. Quelques recommandations : Organiser les services en responsabilisant les acteurs; Elaborer et transmettre dans les délais les RM; Valider en interne les données avant transmission des rapports au DS; Utiliser correctement toutes les fonctionnalités de mSupply; Estimer correctement les quantités à allouer en tenant compte des consommations réelles et des nombres de jours de rupture notifiés; Mettre en oeuvre le SAP pour anticiper tous risques de rupture et de péremptione
A8: 2 | B8: 1.3-2.2 : Organiser des visites d'assistance technique aux acteurs de la chaîne d'approvisionnement décentralisée | C8: Améliorer la qualité du rapportage, la qualité des prestations et de la gestion des produits et intrants des PNS | E8: Du 25 au 29/05/2026 | F8: Pas de visite réalisée cette semaine
A9: 3 | B9: 1.3-2.3 : Apporter un appui technique et financier aux réunions régionales d'analyse et de mise à niveau des stocks | C9: Accompagner les gestionnaires des sites clients directs dans l'exécution effective des plans de redéploiements des stocks issus des réunions d'analyse | D9: Suivi de l'execution des plans de redeploiement élaborés et en cours de réalisation | E9: Du 25 au 29/05/2026 | F9: 1 plan de redéploiement a été élaboré et en cours de réalisation avec l'appui logistique de LHSPLA. Pour les réunions réalisées la semaine du 11 au 15/05/202, le point de suivi de la réalisation des 4 plans de redéploiement est le suivant : Région Moronou (100%); Région Lôh Djiboua (80%); Région Gôh (80%) et Agnéby-Tiassa (80%)
A10: 5 | B10: 1.2-1.1 : Faire le suivi la complétude et la promptitude des rapports des sites non clients directs (mSupply, …) | C10: améliorer la disponibilité des produits traceurs au niveau des sites derservis par les districts | D10: Régions sanitaires livrées par l'Agence Régionale de Bouaké | E10: Du 25/05/2026 au 31/05/2026 | F10: Relance sous forme de rappels dans les groupes watsapp de districts pour les differentes tâches à effectuer avec mSupply;
A11: 6 | B11: 1.3-2.3 : Apporter un appui technique et financier aux réunions régionales d'analyse et de mise à niveau des stocks | C11: améliorer la disponibilité des produits traceurs des programmes de sante au niveau de chaque région | D11: Bélier, Marahoué,Hambol, Haut-Sassandra, Guémon, et Worodougou | E11: Du 25/05/2026 au 29/05/2026 | F11: suivi de l'excécution des plans de rédeploiement issus des réunions d'analyse des stocks; le taux est de 100% pour le Worodougou, Bélier et Haut-Sassandra
A12: 7 | B12: 1.8-2.1 : Organiser des sessions de formation des acteurs de la chaîne d'approvisionnement | C12: Renforcer less capacité techniques des gestionnaires (APGP, IDE et SFDE) des produits de santé des sites péripheriques | D12: Yamoussoukro | E12: 27/05/2026 au 31/05/2026 | F12: Formation de 15 acteurs des ESPC et districts surl'optimisation de la gestion des stocks des produits de santé; entreposage et stockage; prise en main de mSupply; Système d'Alerte Précoce et Assistance Technique. La progression des apprenants etait significative à l'issu des pré et Post-Test
A14: QAD – Quantifiction Achat et Distribution
A15: N° | B15: Titre de l'activité | C15: Objectifs | D15: Lieu | E15: Date(s) | F15: Principales recommandations / Résultats clés
A16: 1 | B16: 1.10-1.1 : Participer aux réunions de suivi mensuel de stock des PNS | C16: * Suivi mensuel des stocks et des PA pour une disponibilité adéquate des produits à tous les niveaux de la chaine d'approvisionnement pour réduire les risques de rupture et de péremption | D16: En ligne | E16: 46168 | F16: *Principales recommandations pour la NPSP* Fournir la date probable de livraison du reliquat des produits de prémière ligne sous BGE Actualiser le eSigl et le fichier suivi de stock en y rétirant l'amikacine inj Retarder la prochaine commande de Bedaquiline 20mg du fait du surstock observé au niveau central comme péripherique sur ce produit ( fin septembre au lieu de fin juin 2026)
A17: 2 | B17: 3.2-1.2 : Mettre à disposition des transitaires la documentation requise pour organiser l'acheminement | C17: * Disponibilité rapide des produits dans les entrepôts NPSP | D17: ABIDJAN | E17: 46171 | F17: * Résultats clés* Transmission des observations (date d'effet) sur le document projet d'exonération sur les acquisitions planifiées sur budget du Gouvernement Américain
A18: 3 | B18: 2.6-5.9 : Organiser quatre sessions d'orientation des Acteurs de la gestion logistique | C18: Renforcer les capacités des gestionnaires et techniciens de laboratoire en gestion logistique des produits de la charge virale | D18: ABIDJAN | E18: 46170 | F18: Renforcement des capacités de 18 personnes (pharmacie et laboratoire) sur la gestion des produits de mPima et des consommables généraux relatifs aux produits de laboratoire.
A19: 4 | B19: 2.2-1.4 : Mettre en place un fichier de suivi intégré de la reception des produits à la levée de quarantaine de ces produits | C19: Respect des délais objectivés | D19: Abidjan | E19: 25 au 29 mai 2026 | F19: Finaliser la correspondance entre les désignation/code QAT et Sage X3 pour transmission interne
A20: 5 | B20: 2.2-3.1 : Organiser 3 inventaires des produits traceurs des programmes suivis | C20: Améliorer la précision et la justesse des stocks | D20: Abidjan | E20: 30 mai au 03 juin | F20: Améliorer la communication interne concernant l'inventaire tournant.
A21: 6 | B21: 2.2-2.2 : Faire le suivi hebdomadaire de l'exécution du plan de réapprovisionnement | C21: Améliorer la disponibilité des produits dans les agences de distribution | D21: Abidjan | E21: 25 au 31 mai 2026 | F21: Aborder ce point lors des prochaines réunions avec les parties prenantes car les délais objectivés sont difficilement attteints
A22: 7 | B22: 2.2-3.2 : Faire le suivi de la prise en compte des écarts relevés lors de chaque inventaire | C22: Améliorer la précision et la justesse des stocks | D22: Abidjan | E22: 25 au 31 mai 2026
A24: CAC - Chaine d'Approvisionnement Décentralisée
A25: N° | B25: Titre de l'activité | C25: Objectifs | D25: Lieu | E25: Date(s) | F25: Principales recommandations / Résultats clés
A26: 1 | B26: 1.4-1.4 : Faire le suivi de la disponibilité des produits de santé communautaires | C26: Mission de suivi des recommandations EUV et de coaching des CAC et ASS dans les districts Tiassalé, 2 ESPC 5DR Ahoara et CSU Morokro) caoching au remplissage du registre ASC et au Weekly Report Communautaire. Diffusion du Weekly aux ASS et CAC. | D26: DS TIASSALE | E26: Du 28 au 29 Mai 2026 | F26: Continuer le coaching au rapportage et au remplissage correcte du rapport ASC dans e-SIGL
A28: C. ACTIVITÉS PLANIFIÉES — Mois glissant (toutes entités)
A29: CAD – Chaîne d'Approvisionnement Décentralisée
A30: N° | B30: Titre de l'activité | C30: Objectifs | D30: Lieu | E30: Date(s) prévues | F30: Participation DoS ? | G30: Observations / Points d'attention
A31: 1 | B31: 1.3-2.3 : Apporter un appui technique et financier aux réunions régionales d'analyse et de mise à niveau des stocks | C31: - Faire le point des recommandations ( suivi du taux de redéploiement, etc.) de la dernière réunion - Faciliter la prise en main du “Weekly Report” pour l’analyse des niveaux de stocks au niveau régional et la prise de décision. - Effectuer les analyses avec les données disponibles pour une prise de décision - Discuter des autres activités et identifier les problèmes à la gestion de la chaîne d’approvisionnement - Proposer un plan d’amélioration ( plans de redéploiements) - Formuler des recommandations | D31: Régions sanitaires Gbôklê; N'zi et Grands Ponts | E31: Du 08 au 12/06/2026 | F31: ❌ NON | G31: Activité reprogrammée : DS Gbôklê (12/06/2026); DS N'zi (date pas encore communiquée); GRANDS PONTS (date pas encore communiquée)
A32: 2 | B32: 1.3-2.4 : Organiser des rencontres d'orientation logistique au niveau départemental | C32: · Présenter et analyser les résultats des activités logistiques au niveau des ESPC : rapportage et qualité des données rapportées ; disponibilités des stocks de produits traceurs et Système d’Alerte Précoce ; Gestion des stocks et utilisation de mSupply ; données de la File Active. · Identifier les problèmes à la mise en œuvre des activités au niveau des ESPC · Renforcer les capacités des gestionnaires de pharmacie des ESPC · Formuler des recommandations | D32: DS DIVO; DS DABOU; DS DOROPO et DS Alépé | E32: 01 au 12/06/2026 | F32: ❌ NON | G32: DS DIVO (date pas encore communiquée); DS DABOU (date pas encore communiquée) DS DOROPO (date pas encore communiquée) et DS Alépé (prévue le 29/05/2026; reprogrammée à une date ultérieure pour conflit de calendrier)
A33: 3 | B33: 1.3-2.4 : Organiser des rencontres d'orientation logistique au niveau départemental | C33: · Présenter et analyser les résultats des activités logistiques au niveau des ESPC des trois derniers mois (Mars,Avril et MAI): rapportage et qualité des données rapportées ; disponibilités des stocks de produits traceurs et Système d’Alerte Précoce ; Gestion des stocks et utilisation de mSupply ; données de la File Active. · Identifier les problèmes à la mise en œuvre des activités au niveau des ESPC · Renforcer les capacités des gestionnaires de pharmacie des ESPC · Formuler des recommandations | D33: Korhogo 2, Dikodougou, Niakara, Katiola, Botro, Béoumi, Bouaké nord ouest, Mankono, Yamousoukro, Toumodi, Odiénné, Madinani, Zouan-Hounien, Bloléquin, Zoukougbeu, Vavoua, Issia ,Bouaflé, Kani et Kounahiri | E33: 08/06/2026 au 19/06/2026 | F33: ❌ NON | G33: réception des TDR de 08 sites ; préparation avec les Pharmaciens de Districts pour le bon deroulement de ses rencontres
A34: 4 | B34: 1.3-2.2 : Organiser des visites d'assistance technique aux acteurs de la chaîne d'approvisionnement décentralisée | C34: effectuer des visites de sites à faibles resultats, travailler avec le site sur:rapportage et qualité des données rapportées ; disponibilités des stocks de produits traceurs et Système d’Alerte Précoce ; Gestion des stocks et utilisation de mSupply ; données de la File Active. | D34: sites à identifier par PRES dans la zone couverte par CAD BOUAKE | E34: du 15/06/26 au 25/06/26 | F34: ❌ NON | G34: identification de sites selon des points précis de mauvaises performance
A35: 5 | B35: 1.2-1.1 : Faire le suivi la complétude et la promptitude des rapports des sites non clients directs (mSupply, …) | C35: Assister les sites au rapportage ,dans les délais, des sites clients directs NPSP | D35: sites CAD Bouaké | E35: du 11/05/26 au 31/05/26 | F35: ❌ NON | G35: Disponibilité à 100% des données logistiques pour la prise de décision
A36: 6 | B36: 1.3-1.2 : Fournir des forfaits de communication et de connexion internet aux structures du niveau central jusqu'au niveau communautaire. | C36: maintenir les sites clients directs NPSP dans la flotte pour faciliter la communication | D36: CAD Bouaké | E36: en continue | F36: ❌ NON | G36: Maintien de tous les numéros des sites dans la flotte compte tenu du turn over des gestionnaires
A37: 7 | B37: 1.4-1.3 : Apporter un appui technique et financier au district sanitaire pour le suivi de la distribution communautaire | C37: Renforcer la disponibilité des CTA et autres ILP en vue d’une meilleure performance de l’ICCM au niveau communautaire | D37: CAD Abidjan | E37: Du 11/05/2026 au 31/05/2026 | F37: ❌ NON | G37: Appui technique à l'élaboration des TDR et à la programmation des visites des DS
A38: 8 | B38: 1.8-2.1 : Organiser des sessions de formation des acteurs de la chaîne d'approvisionnement | C38: Renforcer less capacité techniques des gestionnaires (APGP, IDE et SFDE) des produits de santé des sites péripheriques | D38: Yamoussoukro | E38: 01/06/26 au 06/06/26 | F38: ❌ NON | G38: Formation de 30 acteurs (APGP,IDE, SFDE) attendus; des Tests prévus; briefing des formateurs afin de prendre en compte les leçons apprises de la formation du groupe precédant
A39: 9 | B39: 1.2-1.1 : Faire le suivi la complétude et la promptitude des rapports des sites non clients directs (mSupply, …) | C39: améliorer le rapportage des sites périphériques | D39: CAD Bouaké | E39: Du 18 au 31/05/2026 | F39: ❌ NON | G39: sensibiliser les gestionnaires sur la gestion des produits périmés afin d'eviter de les rapportés comme produits disponibles et utilisables
A40: 10 | B40: 1.3-2.7 : Organiser une orientation des pharmaciens de régions sur le management de la CA | C40: Renforcer les compétence en management et en leadership des PR pour assurer la gouvernance efficace et une redevabilité accrue de la chaine d'approvisionnement pharmaceutique décentralisée | D40: YAMOUSOUKRO | E40: 08 au 12/06/2026 | F40: ❌ NON | G40: Elaboration des plan de contingence des 10 régions participants afin d'améliorer la disponibilité des produits de santé dans leurs points de prestations de service. Partage d'expériences et de bonnes pratiques de gestion de chaine d'approvisionnement
A42: PMO — PMO – Gestion de Projet (Project Management Office)
A43: N° | B43: Titre de l'activité | C43: Objectifs | D43: Lieu | E43: Date(s) prévues | F43: Participation DoS ? | G43: Observations / Points d'attention
A44: 1 | B44: 1.11-3.2 : Organiser des réunions mensuelles du bilan de la performance du projet | C44: Faire le reporting détaillé des activités du projet sur le mois précédent par acteur | D44: Abidjan Nouvelle PSP-CI | E44: 46189 | F44: ❌ NON | G44: *Réunion mois de juin 2026 *Causes de la non-réalisation des activités *Résolution des insatisfactions
A45: 2 | B45: 1.11-4.1 : Faire la maintenance annuelle ORCHESTRA | C45: Maintenance annuelle et assistance pour le logiciel de suivi du projet LHSPLA | D45: Abidjan Nouvelle PSP-CI | F45: ❌ NON | G45: *Aucune suite pour le paiement de la maintenance *Risque de bugs lors d'utilisation de Orchestra
A46: 3 | B46: 1.8-3.1 : Appuyer les gestionnaires des structures sanitaires publiques dans le cadre de leurs activités | C46: Amélioration des compétences du pool de formateurs pour des formations et des coachings de qualité fait à l'endroit des gestionnaires des structures sanitaires publiques | D46: Yamoussoukro | E46: Date à définir | F46: ❌ NON | G46: Apprentissage de l'andragogie. en deux phases : phase pratique et phase théorique
A47: 4 | B47: 1.11-3.1 : Compiler mensuellement les rapports de progression dans le logiciel ORCHESTRA | C47: Orchestra est à jour | D47: Abidjan Nouvelle PSP-CI | E47: du 04 au 05/06/2026 | F47: ❌ NON | G47: Extraction des niveaux d'avancement par entité et transmission des extractions à chaque entité
A49: QAD – Quantifiction Achat et Distribution
A50: N° | B50: Titre de l'activité | C50: Objectifs | D50: Lieu | E50: Date(s) prévues | F50: Participation DoS ? | G50: Observations / Points d'attention
A51: 1 | B51: 1.1-6.1 : Apporter une assistance technique pour l'organisation d'un atelier de préquantification des médicaments pour la prise en charge de la santé de la Mère et de l'enfant. | C51: Disponibilité des données et hypothèses nécessaires à la prévision des besoins en médicaments de la santé de la mère et de l'enfant | D51: Bassam | E51: 01 au 04 juin 2026 | F51: ✅ OUI
A52: 2 | B52: 1.1-6.2 : Apporter une assistance technique pour l'organisation d'un atelier de quantification des médicaments pour la prise en charge de la santé de la Mère et de l'enfant. | C52: Disponibilité des plans d'approvisionnements pour les besoins de la période 2027-2028 | D52: Yamoussoukro | E52: 15 au 20 juin 2026 | F52: ✅ OUI
A53: 3 | B53: 2.6-5.2 : Réaliser trois missions de supervision pour les laboratoires de charge virale | C53: Renforcement des capacités des gestionnaires de pharmacie et des techniciens de laboratoire dans la gestion des produits de la charge virale /EID | D53: KORHOGO-BOUAKE-DALOA | E53: 07 au 13 juin 2026 | F53: ❌ NON
A54: 4 | B54: 2.6-5.9 : Organiser quatre sessions d'orientation des Acteurs de la gestion logistique | C54: Renforcement des capacités des gestionnaires de pharmacie et des techniciens de laboratoire dans la gestion des produits de la charge virale /EID | D54: ABIDJAN | E54: 01-04 juin 2026 | F54: ❌ NON
A55: 5 | B55: 2.6-5.2 : Réaliser trois missions de supervision pour les laboratoires de charge virale | C55: Renforcement des capacités des gestionnaires de pharmacie et des techniciens de laboratoire dans la gestion des produits de la charge virale /EID | D55: ABENGOUROU | E55: 17 au 19 juin 2026 | F55: ❌ NON
A56: 6 | B56: 2.2-1.2 : Faire un suivi hebdomadaire des entrées en machine des produits de programme | C56: Améliorer la disponibilité des produits au niveau des Agences de distribution | D56: Abidjan | E56: 25 au 31 mai | F56: ❌ NON
A57: 7 | B57: 2.2-3.2 : Faire le suivi de la prise en compte des écarts relevés lors de chaque inventaire | C57: Améliorer la précision et la justesse des stocks | D57: Abidjan | E57: 25 au 31 mai | F57: ❌ NON
A58: 8 | B58: 2.2-2.2 : Faire le suivi hebdomadaire de l'exécution du plan de réapprovisionnement | C58: Améliorer la disponibilité des produits dans les agences de distribution | D58: Abidjan | E58: 25 au 31 mai | F58: ❌ NON
A59: 9 | B59: 2.6-2.1 : Organiser des reunions quinzomadaires de suivi des performances de l'Agence Programme | C59: Améliorer la disponibité et la distribution des produits des programmes aux sites clients directs | D59: Abidjan | E59: 25 mai au 7 juin | F59: ❌ NON
A60: 10 | B60: 2.2-1.4 : Mettre en place un fichier de suivi intégré de la reception des produits à la levée de quarantaine de ces produits | C60: Respect des délais objectivés | D60: Abidjan | E60: 25 mai au 7 juin | F60: ❌ NON
A62: SE – Suivi & Évaluation (MEL)
A63: N° | B63: Titre de l'activité | C63: Objectifs | D63: Lieu | E63: Date(s) prévues | F63: Participation DoS ? | G63: Observations / Points d'attention
A64: 2 | B64: 1.7-6.5 : Apporter un appui à la mise en oeuvre des recommandations de l'EUV. | C64: Évaluer le niveau de mise en œuvre des recommandations issues de l'EUV 2025 et renforcer les capacités des agents de la chaîne d'approvisionnement dans la gestion des produits antipaludiques au niveau de 10 districts sanitaires identifiés. | D64: MARAHOUE, HAMBOL, GBEKE, LOH-GUIBOUA, IFFOU, AGNEBY-TIASSA | E64: 27/05/2026 au 10/06/2026 | F64: ❌ NON
A65: 3 | B65: 1.7-3.4 : Déploiement dans 31 régions | C65: Déployer et Former les gestionnaires des établissements sanitaires, en charge de la File Active dans les districts sanitaires des régions de BOUNKANI, GBOKLE, NAWA, GUEMON, HAUT-SASSANDRA, HAMBOL et GÔH, à l’utilisation du SNGFA pour le rapportage et la gestion des données de file active | D65: AGNEBY-TIASSA, N'ZI, MARAHOUE, GOH, GUEMON et HAMBOL | E65: 07/06/2026 au 18/06/2026 | F65: ❌ NON | G65: Quelques ajustements mineurs de l'outil, relatifs aux formulaires de suivi des patients, ont été identifiés et communiqués à Bluesquare par l'équipe LHSPLA.
A66: 4 | B66: 1.7-3.4 : Déploiement dans 31 régions | C66: Déployer et Former les gestionnaires des établissements sanitaires, en charge de la File Active dans les districts sanitaires des régions de LOH DJIBOUA, MORONOU,IFFOU, BAGOUE, GRANDS-PONTS et BAFING, à l’utilisation du SNGFA pour le rapportage et la gestion des données de file active | D66: LOH DJIBOUA ; MORONOU ; IFFOU ; BAGOUE ; GRANDS-PONTS et BAFING | E66: 21/06/2026 au 03/07/2026 | F66: ❌ NON
A68: SI – Système d'Information
A69: N° | B69: Titre de l'activité | C69: Objectifs | D69: Lieu | E69: Date(s) prévues | F69: Participation DoS ? | G69: Observations / Points d'attention
A70: 4 | B70: 4.2.3.3 : Développer des guides utilisateurs simplifiés | C70: - Ciblage précis des besoins en formations ; - éviter les sessions génériques peu efficaces - optimiser le budget | E70: du 01/06/2026 au 31/06/2026 | F70: ❌ NON
A71: 5 | B71: 1.2-3.1 : Equiper la NPSP en équipement informatique | C71: Doter la NPSP d’ordinateurs portables | E71: du 01/06/2026 au 31/06/2026 | F71: ❌ NON | G71: Acquisition prévu: 37 ordinateurs Une premiere acquisition de 14 ordinateurs est en cours; Reste 23 ordinateurs à aquérir
A72: 6 | B72: 4.2.5.1 : Réaliser une évaluation diagnostique initial (Data Quality Assessment) | C72: - Mesurer l’exactitude des données (concordance entre les données saisies et les sources primaires). - Évaluer l’exhaustivité (complétude des enregistrements et des rapports). - Vérifier la ponctualité (respect des délais de saisie et de transmission). - Analyser la cohérence des données (absence de contradictions entre les différentes sources et rapports). - Apprécier l’accessibilité des données (facilité d’accès, disponibilité et utilisation pour la prise de décision). | D72: Les districts sanitaires de Bondoukou, Kani, Niakaramadougou, Sandegué, Yakassé Attobrou, Gagnoa 1, Daloa, Bouafé, Fresco, Dianra | E72: du 08/06/2026 au 12/06/2026 | F72: ❌ NON
A73: 7 | B73: 4.2.5.4 : Monitorer à distance les sites identifiés par le DQA – tableau de bord mSupply | C73: - Suivre en temps réel les indicateurs clés de performance des sites sélectionnés. - Identifier rapidement les anomalies, incohérences et écarts de données. - Évaluer la qualité et la complétude des données saisies dans mSupply. - Détecter les sites nécessitant un accompagnement ou des actions correctives. - Produire des rapports périodiques de suivi à destination des parties prenantes. - Faciliter la prise de décision basée sur les données issues du tableau de bord mSupply. | E73: du 15/06/2026 au 27/06/2026 | F73: ❌ NON
A74: 8 | B74: 4.2.4.1 : Cartographier et prioriser les bugs mSupply | C74: - Recenser et documenter tous les bugs signalés dans mSupply. - Classifier les anomalies par module, fonctionnalité et type d'incident. - Évaluer l'impact de chaque bug sur les opérations et les utilisateurs. - Définir les niveaux de priorité (critique, majeur, mineur, faible). - Élaborer une feuille de route de correction en collaboration avec les équipes techniques et métiers. - Assurer le suivi de la résolution des anomalies jusqu'à leur clôture. | E74: du 01/06/2026 au 31/06/2026 | F74: ❌ NON
A76: FINANCES — Service Finances
A77: N° | B77: Titre de l'activité | C77: Objectifs | D77: Lieu | E77: Date(s) prévues | F77: Participation DoS ? | G77: Observations / Points d'attention
A78: 2 | B78: 1.11-1.3 : Réaliser un audit interne | C78: Préparer l'audit financier du projet LHSPLA de l'exercice 2025 | D78: NPSP | E78: 46174 | F78: ❌ NON | G78: L'activité sera effectué avec un cabinet
A79: 3 | B79: 1.11-1.1 : Organiser une mission de collecte et de réconciliation des pièces sur le terrain | C79: Collecter les pièces et finaliser les reconciliations des appuis aux sites décentralisés | D79: NPSP | E79: 46174 | F79: ❌ NON
A81: D. POINTS DE VIGILANCE / RISQUES / BESOINS DE DÉCISION (toutes entités)
A83: PMO – Gestion de Projet (Project Management Office)
A84: N° | B84: Catégorie | C84: Description du point | D84: Niveau de criticité | E84: Action attendue / Décision souhaitée
A85: 1 | C85: Restructuration du prestataire du logiciel ORCHESTRA demandant une revision du contrat. Aucune avancée sur le contrat, ce qui retarde la mise en oeuvre du paiement dans le cadre de la maintenance. | D85: 🟠 Élevé | E85: Approche du Département Juridique pour une accélération du traitement de ce dossier.
A87: QAD – Quantifiction Achat et Distribution
A88: N° | B88: Catégorie | C88: Description du point | D88: Niveau de criticité | E88: Action attendue / Décision souhaitée
A89: 1 | B89: Traitement de commandes fournisseurs | C89: Faible disponibilité de plusieurs consommables à acquerir sur budget ETAT au niveau central (DBS, Tubes EDTA, Tubes rouge, Tubes gris, Pastilles de chloramine, etc) | D89: 🟠 Élevé | E89: - Procéder à des acquisitions de dépannages pour garantir la continuité des services - Procéder au paiement des fournisseurs pour une livraison des kits DBS
A90: 2 | B90: Dédouanement et enlèvement | C90: Refus de libération des colis arrivés en raison de l'expiration de l'exonération des produits financés par le Gouvernement Américain. Le service Transit a indiqué que la douane réclamait un courrier, une note ou un document officiel indiquant la poursuite des activités du projet LHSPLA sous le couvert du Département d'Etat Américain. | D90: 🟠 Élevé | E90: - Obtenir un délai additionnel avec la DGD pour la libération des colis arrivés en attendant le renouvellement de l'exonération des produits acquis sur le budget du Gouvernement Américain

Sheet AWP FY26
A1: OBJECTIFS OPÉRATIONNELS | B1: ACTIVITÉS | C1: NARRATIF D'ACTIVITÉS | D1: CODE TACHE | E1: TÂCHES | F1: RESPONSABLES | G1: BENEFICIAIRES (NIVEAU CENTRAL) | H1: BENEFICIAIRES (DIRECTIONS/DEPARTEMENTS) | I1: DATE DE DEBUT | J1: DATE DE FIN | K1: RÉSULTATS ATTENDUS PAR TACHES (Quantifier et expliquer) | L1: RÉSULTATS ATTENDUS PAR ACTIVITÉ (Quantifier et expliquer) | M1: INDICATEURS | N1: BÉNÉFICES ATTENDUS PAR ACTIVITÉ | O1: LIVRABLES par Tâche | P1: LIVRABLES par Activité | Q1: PROGRAM AREA | R1: COST CATEGORY | S1: NARRATIF DU BUDGET | T1: COP(S1) | U1: COP(S2) | V1: COP | W1: MOP | X1: MCH | Y1: US LEGACY | Z1: BUDGET GLOBAL | AA1: 45931 | AB1: 45931 | AC1: 45931 | AD1: 45962 | AE1: 45962 | AF1: 45962 | AG1: 45992 | AH1: 45992 | AI1: 45992 | AJ1: 46023 | AK1: 46023 | AL1: 46023 | AM1: 46054 | AN1: 46054 | AO1: 46054 | AP1: 46082 | AQ1: 46082 | AR1: 46082 | AS1: Avr-26 | AT1: Avr-26 | AU1: 46113 | AV1: 46143 | AW1: 46143 | AX1: 46143 | AY1: 46143 | AZ1: 46174 | BA1: 46174 | BB1: 46174 | BC1: 46174 | BD1: 46204 | BE1: 46204 | BF1: 46204 | BG1: 46204 | BH1: 46235 | BI1: 46235 | BJ1: 46235 | BK1: 46235 | BL1: 46266 | BM1: 46266 | BN1: 46266 | BO1: 46266 | BP1: VERIF 1 | BQ1: VERIF 2 | BR1: VERIF 3 | BS1: VERIF 4
A2: OS 1 : APPUYER LE GOCI, À TRAVERS LA DIRECTION DE L'ACTIVITÉ PHARMACEUTIQUE (DAP), LE COMITÉ NATIONAL DE COORDINATION DE LA CHAINE D'APPROVISIONNEMENT EN MÉDICAMENTS ESSENTIELS ET PRODUITS STRATÉGIQUES DE SANTÉ (CNCAM) ET LES PROGRAMMES NATIONAUX DE SANTÉ (PNLS, PNLP, PNLT, PNSME, ETC.) POUR RENFORCER LE SYSTÈME NATIONAL DE CHAÎNE D'APPROVISIONNEMENT, EN METTANT L'ACCENT SUR LA QUANTIFICATION, LA PRÉVISION, LA LOGISTIQUE NATIONALE, LA GESTION DU PLAN D'APPROVISIONNEMENT EN PRODUITS DE SANTÉ, LA GESTION ET LA VISIBILITÉ DES DONNÉES. | T2: =SUM(T3:T141) -> 414576993 | U2: =SUM(U3:U141) -> 353515415 | V2: =SUM(V3:V141) -> 768092408 | W2: =SUM(W3:W141) -> 4.4660571e+08 | X2: =SUM(X3:X141) -> 6.5316343e+08 | Y2: =SUM(Y3:Y141) -> 446977178 | Z2: =SUM(Z3:Z141) -> 3.0829311e+09 | AA2: COP(S1) | AB2: MOP | AC2: MCH | AD2: COP(S1) | AE2: MOP | AF2: MCH | AG2: COP(S1) | AH2: MOP | AI2: MCH | AJ2: COP(S1) | AK2: MOP | AL2: MCH | AM2: COP(S1) | AN2: MOP | AO2: MCH | AP2: COP(S1) | AQ2: MOP | AR2: MCH | AS2: COP(S2) | AT2: MOP | AU2: MCH | AV2: COP(S2) | AW2: MOP | AX2: MCH | AY2: USLEG | AZ2: COP(S2) | BA2: MOP | BB2: MCH | BC2: US LEG | BD2: COP(S2) | BE2: MOP | BF2: MCH | BG2: US LEG | BH2: COP(S2) | BI2: MOP | BJ2: MCH | BK2: US LEG | BL2: COP(S2) | BM2: MOP | BN2: MCH | BO2: US LEG | BP2: COP(S1) | BQ2: COP(S2) | BR2: MOP | BS2: MCH
A3: OO 1.1 : Soutenir les exercices annuels de quantification et de prévision pour le VIH, le paludisme, la tuberculose, les médicaments essentiels et d'autres produits. | B3: 1.1-1 : Apporter un appui technique et financier aux exercices de quantification du programme national de santé PNLS. | C3: LHSPLA apportera un soutien technique à l'exercice annuel de quantification des ARV/IO et des produits de laboratoire. Le conseiller en quantification plaidera pour l'optimisation du traitement antirétroviral, notamment la priorisation du traitement à base de DTG chez l'enfant (pALD) et chez l'adulte ainsi que la recommandation des présentation des boites de TLD 90 et 180 afin de booster le MMD. De plus, au cours de l'exercice de quantification, le QFA sensibilisera les membres du comité de quantification sur les directives du TPT & IVSA pour s'assurer que les produits sont correctement prévus et planifiés. Un autre exercice de quantification aura lieu pour les kits IST avec différents acteurs des systèmes (PMO, branche IST du PNLS..) Suite aux différents exercices de quantification, LHSPLA soutiendra également le programme VIH pour diffuser le résultat de quantification, le plan d'approvisionnement 2027 des ARV, les produits de laboratoire et des kits IST et poussera les agents d'approvisionnement à passer des commandes pour permettre des approvisionnements respectant le délai de livraison. Le QFA de LHSPLA collaborera avec les autres programmes de santé (PNLT, PNN, Médicaments essentiels,....) pour gérer leurs exercices annuels de quantification afin d'assurer l'exactitude des résultats. Cet accompagnement transversal de LHSPLA à tous les programmes de santé est une manière d'aider aux bonnes pratiques de quantification des produits de santé et ainsi d'éviter les ruptures de stock et les péremptions | D3: =TRIM(_xlfn.TEXTBEFORE(E3,":")) -> 1.1-1.1 | E3: 1.1-1.1 : Apporter une assistance technique et financière pour l'organisation d'un atelier de préquantification des ARV, IO et des produits de laboratoire. | F3: QAD | G3: PNS | H3: PNLS | I3: 46026 | J3: 30/05/2026 | L3: * Les Besoins annuels pour les ARV & IO, Lab, kits IST pour les années 2027 & 2028 sont estimés et disponibles * Les plans d'approvisionnement 2027 & 2028 pour les ARV & IO, Lab, et kits IST sont finalisés et transmis | M3: *Taux de précision de la quantification des produits traceurs du PNLS *Taux d'exécution du plan d'approvisionnement PNLS | N3: Disponibilité adéquate des produits à tous les niveaux de la chaine d'approvisionnement, afin de réduire les risques de rupture et de surstock | O3: Rapport de préquantification PNLS | P3: Rapports de quantification PNLS | Q3: Support and Assistance | R3: Support and Assistance | S3: *Atelier de 5 jours regroupant 28 personnes dont 6 LHSPLA, 15 nationaux, 7 partenaires Prise en charge LHSPLA et partie nationale Location de salle / Pause café / Eau en salle / Forfait carburant véhicule TPM / Full perdiem pour le staff LHSPLA / Frais péage / Forfait transport / Frais de connexion internet / Autres frais | T3: 0 | U3: 10633183 | V3: 10633183 | W3: 0 | X3: 0 | Y3: 0 | Z3: =SUM(T3:Y3) -> 21266366 | AV3: 10633183 | BP3: =T3-SUM(AA3,AD3,AG3,AJ3,AM3,AP3) -> 0 | BQ3: =U3-SUM(AS3,AV3,AZ3,BD3,BH3,BL3) -> 0 | BR3: =W3-SUM(AB3,AE3,AH3,AK3,AN3,AQ3,AT3,AW3,BA3,BE3,BI3,BM3) -> 0 | BS3: =X3-SUM(AC3,AF3,AI3,AL3,AO3,AR3,AU3,AX3,BB3,BF3,BJ3,BN3) -> 0
A4: OO 1.1 : Soutenir les exercices annuels de quantification et de prévision pour le VIH, le paludisme, la tuberculose, les médicaments essentiels et d'autres produits. | B4: 1.1-1 : Apporter un appui technique et financier aux exercices de quantification du programme national de santé PNLS. | C4: LHSPLA apportera un soutien technique à l'exercice annuel de quantification des ARV/IO et des produits de laboratoire. Le conseiller en quantification plaidera pour l'optimisation du traitement antirétroviral, notamment la priorisation du traitement à base de DTG chez l'enfant (pALD) et chez l'adulte ainsi que la recommandation des présentation des boites de TLD 90 et 180 afin de booster le MMD. De plus, au cours de l'exercice de quantification, le QFA sensibilisera les membres du comité de quantification sur les directives du TPT & IVSA pour s'assurer que les produits sont correctement prévus et planifiés. Un autre exercice de quantification aura lieu pour les kits IST avec différents acteurs des systèmes (PMO, branche IST du PNLS..) Suite aux différents exercices de quantification, LHSPLA soutiendra également le programme VIH pour diffuser le résultat de quantification, le plan d'approvisionnement 2027 des ARV, les produits de laboratoire et des kits IST et poussera les agents d'approvisionnement à passer des commandes pour permettre des approvisionnements respectant le délai de livraison. Le QFA de LHSPLA collaborera avec les autres programmes de santé (PNLT, PNN, Médicaments essentiels,....) pour gérer leurs exercices annuels de quantification afin d'assurer l'exactitude des résultats. Cet accompagnement transversal de LHSPLA à tous les programmes de santé est une manière d'aider aux bonnes pratiques de quantification des produits de santé et ainsi d'éviter les ruptures de stock et les péremptions | D4: =TRIM(_xlfn.TEXTBEFORE(E4,":")) -> 1.1-1.2 | E4: 1.1-1.2 : Apporter une assistance technique et financière pour l'organisation d'un atelier de quantification des ARV, IO. | F4: QAD | G4: PNS | H4: PNLS | I4: 46026 | J4: 30/05/2026 | L4: * Les Besoins annuels pour les ARV & IO, Lab, kits IST pour les années 2027 & 2028 sont estimés et disponibles * Les plans d'approvisionnement 2027 & 2028 pour les ARV & IO, Lab, et kits IST sont finalisés et transmis | M4: *Taux de précision de la quantification des produits traceurs du PNLS *Taux d'exécution du plan d'approvisionnement PNLS | N4: Disponibilité adéquate des produits ARV/IO à tous les niveaux de la chaine d'approvisionnement, afin de réduire les risques de rupture et de surstock | O4: Rapport de quantification ARV/IO | P4: Rapports de quantification PNLS | Q4: Support and Assistance | R4: Support and Assistance | S4: *Atelier de 6 jours regroupant 25 personnes dont 7 LHSPLA Prise en charge LHSPLA Location de salle / Pause café / Eau en salle / Forfait carburant véhicule Directrice, TPM, PSM / Full perdiem pour le staff LHSPLA / Frais péage / Frais de connexion internet / Autres frais | U4: 7890360 | V4: 7890360 | Y4: 0 | Z4: =SUM(T4:Y4) -> 15780720 | AV4: 7890360 | BP4: =T4-SUM(AA4,AD4,AG4,AJ4,AM4,AP4) -> 0 | BQ4: =U4-SUM(AS4,AV4,AZ4,BD4,BH4,BL4) -> 0 | BR4: =W4-SUM(AB4,AE4,AH4,AK4,AN4,AQ4,AT4,AW4,BA4,BE4,BI4,BM4) -> 0 | BS4: =X4-SUM(AC4,AF4,AI4,AL4,AO4,AR4,AU4,AX4,BB4,BF4,BJ4,BN4) -> 0
A5: OO 1.1 : Soutenir les exercices annuels de quantification et de prévision pour le VIH, le paludisme, la tuberculose, les médicaments essentiels et d'autres produits. | B5: 1.1-1 : Apporter un appui technique et financier aux exercices de quantification du programme national de santé PNLS. | C5: LHSPLA apportera un soutien technique à l'exercice annuel de quantification des ARV/IO et des produits de laboratoire. Le conseiller en quantification plaidera pour l'optimisation du traitement antirétroviral, notamment la priorisation du traitement à base de DTG chez l'enfant (pALD) et chez l'adulte ainsi que la recommandation des présentation des boites de TLD 90 et 180 afin de booster le MMD. De plus, au cours de l'exercice de quantification, le QFA sensibilisera les membres du comité de quantification sur les directives du TPT & IVSA pour s'assurer que les produits sont correctement prévus et planifiés. Un autre exercice de quantification aura lieu pour les kits IST avec différents acteurs des systèmes (PMO, branche IST du PNLS..) Suite aux différents exercices de quantification, LHSPLA soutiendra également le programme VIH pour diffuser le résultat de quantification, le plan d'approvisionnement 2027 des ARV, les produits de laboratoire et des kits IST et poussera les agents d'approvisionnement à passer des commandes pour permettre des approvisionnements respectant le délai de livraison. Le QFA de LHSPLA collaborera avec les autres programmes de santé (PNLT, PNN, Médicaments essentiels,....) pour gérer leurs exercices annuels de quantification afin d'assurer l'exactitude des résultats. Cet accompagnement transversal de LHSPLA à tous les programmes de santé est une manière d'aider aux bonnes pratiques de quantification des produits de santé et ainsi d'éviter les ruptures de stock et les péremptions | D5: =TRIM(_xlfn.TEXTBEFORE(E5,":")) -> 1.1-1.3 | E5: 1.1-1.3 : Apporter une assistance technique et financière pour l'organisation d'un atelier de quantification des produits de laboratoire liés au VIH. | F5: QAD | G5: PNS | H5: PNLS | I5: 46027 | J5: 30/05/2026 | L5: * Les Besoins annuels pour les ARV & IO, Lab, kits IST pour les années 2027 & 2028 sont estimés et disponibles * Les plans d'approvisionnement 2027 & 2028 pour les ARV & IO, Lab, et kits IST sont finalisés et transmis | M5: *Taux de précision de la quantification des produits traceurs du PNLS *Taux d'exécution du plan d'approvisionnement PNLS | N5: Disponibilité adéquate des produits de laboratoire surtout ceux de la charge virale à tous les niveaux de la chaine d'approvisionnement, afin de réduire les risques de rupture et de surstock | O5: Rapport de quantification LABO | P5: Rapports de quantification PNLS | Q5: Support and Assistance | R5: Support and Assistance | S5: *Atelier de 6 jours regroupant 20 personnes dont 5 LHSPLA Prise en charge LHSPLA *Location de salle *Pause café *Eau en salle *Forfait carburant véhicule TPM, PSM *Full perdiem pour le staff LHSPLA *Frais péage *Forfait carburant *Frais de connexion internet *Autres frais | U5: 6021592 | V5: 6021592 | Y5: 0 | Z5: =SUM(T5:Y5) -> 12043184 | AV5: 6021592 | BP5: =T5-SUM(AA5,AD5,AG5,AJ5,AM5,AP5) -> 0 | BQ5: =U5-SUM(AS5,AV5,AZ5,BD5,BH5,BL5) -> 0 | BR5: =W5-SUM(AB5,AE5,AH5,AK5,AN5,AQ5,AT5,AW5,BA5,BE5,BI5,BM5) -> 0 | BS5: =X5-SUM(AC5,AF5,AI5,AL5,AO5,AR5,AU5,AX5,BB5,BF5,BJ5,BN5) -> 0
A6: OO 1.1 : Soutenir les exercices annuels de quantification et de prévision pour le VIH, le paludisme, la tuberculose, les médicaments essentiels et d'autres produits. | B6: 1.1-1 : Apporter un appui technique et financier aux exercices de quantification du programme national de santé PNLS. | C6: LHSPLA apportera un soutien technique à l'exercice annuel de quantification des ARV/IO et des produits de laboratoire. Le conseiller en quantification plaidera pour l'optimisation du traitement antirétroviral, notamment la priorisation du traitement à base de DTG chez l'enfant (pALD) et chez l'adulte ainsi que la recommandation des présentation des boites de TLD 90 et 180 afin de booster le MMD. De plus, au cours de l'exercice de quantification, le QFA sensibilisera les membres du comité de quantification sur les directives du TPT & IVSA pour s'assurer que les produits sont correctement prévus et planifiés. Un autre exercice de quantification aura lieu pour les kits IST avec différents acteurs des systèmes (PMO, branche IST du PNLS..) Suite aux différents exercices de quantification, LHSPLA soutiendra également le programme VIH pour diffuser le résultat de quantification, le plan d'approvisionnement 2027 des ARV, les produits de laboratoire et des kits IST et poussera les agents d'approvisionnement à passer des commandes pour permettre des approvisionnements respectant le délai de livraison. Le QFA de LHSPLA collaborera avec les autres programmes de santé (PNLT, PNN, Médicaments essentiels,....) pour gérer leurs exercices annuels de quantification afin d'assurer l'exactitude des résultats. Cet accompagnement transversal de LHSPLA à tous les programmes de santé est une manière d'aider aux bonnes pratiques de quantification des produits de santé et ainsi d'éviter les ruptures de stock et les péremptions | D6: =TRIM(_xlfn.TEXTBEFORE(E6,":")) -> 1.1-1.4 | E6: 1.1-1.4 : Apporter une assistance technique à l' atelier de quantification des produits de lutte contre les IST. | F6: QAD | G6: PNS | H6: PNLS | I6: 46026 | J6: 30/05/2026 | L6: * Les Besoins annuels pour les ARV & IO, Lab, kits IST pour les années 2027 & 2028 sont estimés et disponibles * Les plans d'approvisionnement 2027 & 2028 pour les ARV & IO, Lab, et kits IST sont finalisés et transmis | M6: *Taux de précision de la quantification des produits traceurs du PNLS *Taux d'exécution du plan d'approvisionnement PNLS | N6: Disponibilité adéquate des kits IST à tous les niveaux de la chaine d'approvisionnement, afin de réduire les risques de rupture et de surstock | O6: Rapport de quantification KIT IST | P6: Rapports de quantification PNLS | Q6: Support and Assistance | R6: Support and Assistance | S6: Sans budget | U6: 0 | V6: 0 | W6: 0 | X6: 0 | Y6: 0 | Z6: =SUM(T6:Y6) -> 0 | BP6: =T6-SUM(AA6,AD6,AG6,AJ6,AM6,AP6) -> 0 | BQ6: =U6-SUM(AS6,AV6,AZ6,BD6,BH6,BL6) -> 0 | BR6: =W6-SUM(AB6,AE6,AH6,AK6,AN6,AQ6,AT6,AW6,BA6,BE6,BI6,BM6) -> 0 | BS6: =X6-SUM(AC6,AF6,AI6,AL6,AO6,AR6,AU6,AX6,BB6,BF6,BJ6,BN6) -> 0
A7: OO 1.1 : Soutenir les exercices annuels de quantification et de prévision pour le VIH, le paludisme, la tuberculose, les médicaments essentiels et d'autres produits. | B7: 1.1-2 : Apporter un appui technique et financier aux exercices de quantification du programme national de santé PNLP. | C7: LHSPLA apportera un soutien technique à l'exercice annuel de quantification des ARV/IO et des produits de laboratoire. Le conseiller en quantification plaidera pour l'optimisation du traitement antirétroviral, notamment la priorisation du traitement à base de DTG chez l'enfant (pALD) et chez l'adulte ainsi que la recommandation des présentation des boites de TLD 90 et 180 afin de booster le MMD. De plus, au cours de l'exercice de quantification, le QFA sensibilisera les membres du comité de quantification sur les directives du TPT & IVSA pour s'assurer que les produits sont correctement prévus et planifiés. Un autre exercice de quantification aura lieu pour les kits IST avec différents acteurs des systèmes (PMO, branche IST du PNLS..) Suite aux différents exercices de quantification, LHSPLA soutiendra également le programme VIH pour diffuser le résultat de quantification, le plan d'approvisionnement 2027 des ARV, les produits de laboratoire et des kits IST et poussera les agents d'approvisionnement à passer des commandes pour permettre des approvisionnements respectant le délai de livraison. Le QFA de LHSPLA collaborera avec les autres programmes de santé (PNLT, PNN, Médicaments essentiels,....) pour gérer leurs exercices annuels de quantification afin d'assurer l'exactitude des résultats. Cet accompagnement transversal de LHSPLA à tous les programmes de santé est une manière d'aider aux bonnes pratiques de quantification des produits de santé et ainsi d'éviter les ruptures de stock et les péremptions | D7: =TRIM(_xlfn.TEXTBEFORE(E7,":")) -> 1.1-2.1 | E7: 1.1-2.1 : Apporter une assistance technique et financière pour l'organisation d'un atelier de préquantification des antipaludiques et autres intrants de lutte contre le paludisme. | F7: QAD | G7: PNS | H7: PNLP | I7: 46027 | J7: 30/05/2026 | L7: *Les Besoins annuels 2027 & 2028 des antipaludiques et intrants pour les années 2027 & 2028 sont estimés et disponibles * Les Plans d'approvisionnement 2027 & 2028 pour les antipaludiques sont finalisés et transmis | M7: *Taux de précision de la quantification des produits traceurs du PNLP *Taux d'exécution du plan d'approvisionnement PNLP | N7: Disponibilité adéquate des antipaludiques à tous les niveaux de la chaine d'approvisionnement, afin de réduire les risques de rupture et de surstock | O7: Rapport de préquantification PNLP | P7: Rapport de quantification PNLP | Q7: Support and Assistance | R7: Support and Assistance | S7: Atelier de 5 jours avec 6 participants LHSPLA Prise en chargeLHSPLA *Forfait carburant véhicule TPM, PSM *Full perdiem pour le staff LHSPLA *Forfait transport *Frais de connexion internet *Frais péage *Autres frais | T7: 0 | U7: 0 | V7: 0 | W7: 3364310 | Y7: 0 | Z7: =SUM(T7:Y7) -> 3364310 | AW7: 3364310 | BP7: =T7-SUM(AA7,AD7,AG7,AJ7,AM7,AP7) -> 0 | BQ7: =U7-SUM(AS7,AW7,AZ7,BD7,BH7,BL7) -> -3364310 | BR7: =W7-SUM(AB7,AE7,AH7,AK7,AN7,AQ7,#REF!,#REF!,BA7,BE7,BI7,BM7) -> #REF! | BS7: =X7-SUM(AC7,AF7,AI7,AL7,AO7,AR7,AU7,AX7,BB7,BF7,BJ7,BN7) -> 0
A8: OO 1.1 : Soutenir les exercices annuels de quantification et de prévision pour le VIH, le paludisme, la tuberculose, les médicaments essentiels et d'autres produits. | B8: 1.1-2 : Apporter un appui technique et financier aux exercices de quantification du programme national de santé PNLP. | C8: LHSPLA apportera un soutien technique à l'exercice annuel de quantification des ARV/IO et des produits de laboratoire. Le conseiller en quantification plaidera pour l'optimisation du traitement antirétroviral, notamment la priorisation du traitement à base de DTG chez l'enfant (pALD) et chez l'adulte ainsi que la recommandation des présentation des boites de TLD 90 et 180 afin de booster le MMD. De plus, au cours de l'exercice de quantification, le QFA sensibilisera les membres du comité de quantification sur les directives du TPT & IVSA pour s'assurer que les produits sont correctement prévus et planifiés. Un autre exercice de quantification aura lieu pour les kits IST avec différents acteurs des systèmes (PMO, branche IST du PNLS..) Suite aux différents exercices de quantification, LHSPLA soutiendra également le programme VIH pour diffuser le résultat de quantification, le plan d'approvisionnement 2027 des ARV, les produits de laboratoire et des kits IST et poussera les agents d'approvisionnement à passer des commandes pour permettre des approvisionnements respectant le délai de livraison. Le QFA de LHSPLA collaborera avec les autres programmes de santé (PNLT, PNN, Médicaments essentiels,....) pour gérer leurs exercices annuels de quantification afin d'assurer l'exactitude des résultats. Cet accompagnement transversal de LHSPLA à tous les programmes de santé est une manière d'aider aux bonnes pratiques de quantification des produits de santé et ainsi d'éviter les ruptures de stock et les péremptions | D8: =TRIM(_xlfn.TEXTBEFORE(E8,":")) -> 1.1-2.2 | E8: 1.1-2.2 : Apporter une assistance technique et financière pour l'organisation d'un atelier de quantification des antipaludiques et autres intrants de lutte contre le paludisme. | F8: QAD | G8: PNS | H8: PNLP | I8: 46027 | J8: 30/05/2026 | L8: *Les Besoins annuels 2027 & 2028 des antipaludiques et intrants pour les années 2027 & 2028 sont estimés et disponibles * Les Plans d'approvisionnement 2027 & 2028 pour les antipaludiques sont finalisés et transmis | M8: *Taux de précision de la quantification des produits traceurs du PNLP *Taux d'exécution du plan d'approvisionnement PNLP | N8: Disponibilité adéquate des antipaludiques à tous les niveaux de la chaine d'approvisionnement, afin de réduire les risques de rupture et de surstock | O8: Rapport de quantification PNLP | P8: Rapports de quantification PNLP | Q8: Support and Assistance | R8: Support and Assistance | S8: -Atelier de 5 jours avec 7 participants LHSPLA Prise en chargeLHSPLA et location de salle *Forfait carburant véhicule Directrice , TPM *Full perdiem pour le staff LHSPLA *Location de salle *Pause café *Eau en salle *Forfait transport *Frais de connexion internet *Frais péage *Autres frais | U8: 0 | V8: 0 | W8: 6275034 | Y8: 0 | Z8: =SUM(T8:Y8) -> 6275034 | AW8: 6275034 | BP8: =T8-SUM(AA8,AD8,AG8,AJ8,AM8,AP8) -> 0 | BQ8: =U8-SUM(AS8,AW8,AZ8,BD8,BH8,BL8) -> -6275034 | BR8: =W8-SUM(AB8,AE8,AH8,AK8,AN8,AQ8,#REF!,#REF!,BA8,BE8,BI8,BM8) -> #REF! | BS8: =X8-SUM(AC8,AF8,AI8,AL8,AO8,AR8,AU8,AX8,BB8,BF8,BJ8,BN8) -> 0
A9: OO 1.1 : Soutenir les exercices annuels de quantification et de prévision pour le VIH, le paludisme, la tuberculose, les médicaments essentiels et d'autres produits. | B9: 1.1-3 : Apporter un appui technique aux exercices de quantification du programme national de santé PNLT. | C9: LHSPLA apportera un soutien technique à l'exercice annuel de quantification des ARV/IO et des produits de laboratoire. Le conseiller en quantification plaidera pour l'optimisation du traitement antirétroviral, notamment la priorisation du traitement à base de DTG chez l'enfant (pALD) et chez l'adulte ainsi que la recommandation des présentation des boites de TLD 90 et 180 afin de booster le MMD. De plus, au cours de l'exercice de quantification, le QFA sensibilisera les membres du comité de quantification sur les directives du TPT & IVSA pour s'assurer que les produits sont correctement prévus et planifiés. Un autre exercice de quantification aura lieu pour les kits IST avec différents acteurs des systèmes (PMO, branche IST du PNLS..) Suite aux différents exercices de quantification, LHSPLA soutiendra également le programme VIH pour diffuser le résultat de quantification, le plan d'approvisionnement 2027 des ARV, les produits de laboratoire et des kits IST et poussera les agents d'approvisionnement à passer des commandes pour permettre des approvisionnements respectant le délai de livraison. Le QFA de LHSPLA collaborera avec les autres programmes de santé (PNLT, PNN, Médicaments essentiels,....) pour gérer leurs exercices annuels de quantification afin d'assurer l'exactitude des résultats. Cet accompagnement transversal de LHSPLA à tous les programmes de santé est une manière d'aider aux bonnes pratiques de quantification des produits de santé et ainsi d'éviter les ruptures de stock et les péremptions | D9: =TRIM(_xlfn.TEXTBEFORE(E9,":")) -> 1.1-3.1 | E9: 1.1-3.1 : Apporter une assistance technique pour l'organisation d'un atelier de quantification des médicaments et intrants de lutte contre la tuberculose. | F9: QAD | G9: PNS | H9: PNLT | I9: 46026 | J9: 30/05/2026 | L9: *Les Besoins annuels 2027 & 2028 des antituberculeux et intrants pour les années 2027 & 2028 sont estimés et disponibles * Les Plans d'approvisionnement 2027 & 2028 pour les antipaludiques sont finalisés et transmis | M9: *Taux de précision de la quantification des produits traceurs du PNLT *Taux d'exécution du plan d'approvisionnement PNLT | N9: Disponibilité adéquate des antituberculeux à tous les niveaux de la chaine d'approvisionnement, afin de réduire les risques de rupture et de surstock | O9: Rapport de quantification PNLT | P9: Rapports de quantification PNLT | Q9: Support and Assistance | R9: Support and Assistance | S9: -Atelier de 5 jours avec 5 participants LHSPLA Prise en charge LHSPLA *Perdiems *Forfait carburant véhicule *Full perdiem pour le staff LHSPLA *Forfait Transport *Frais de connexion internet *Frais péage *Autres frais | U9: 7726354 | V9: 7726354 | Y9: 0 | Z9: =SUM(T9:Y9) -> 15452708 | AV9: 7726354 | BP9: =T9-SUM(AA9,AD9,AG9,AJ9,AM9,AP9) -> 0 | BQ9: =U9-SUM(AV9,#REF!,AZ9,BD9,BH9,BL9) -> #REF! | BR9: =W9-SUM(AB9,AE9,AH9,AK9,AN9,AQ9,AT9,AW9,BA9,BE9,BI9,BM9) -> 0 | BS9: =X9-SUM(AC9,AF9,AI9,AL9,AO9,AR9,AU9,AX9,BB9,BF9,BJ9,BN9) -> 0
A10: OO 1.1 : Soutenir les exercices annuels de quantification et de prévision pour le VIH, le paludisme, la tuberculose, les médicaments essentiels et d'autres produits. | B10: 1.1-4 : Apporter un appui technique aux exercices de quantification du programme national de santé PNN. | C10: LHSPLA apportera un soutien technique à l'exercice annuel de quantification des ARV/IO et des produits de laboratoire. Le conseiller en quantification plaidera pour l'optimisation du traitement antirétroviral, notamment la priorisation du traitement à base de DTG chez l'enfant (pALD) et chez l'adulte ainsi que la recommandation des présentation des boites de TLD 90 et 180 afin de booster le MMD. De plus, au cours de l'exercice de quantification, le QFA sensibilisera les membres du comité de quantification sur les directives du TPT & IVSA pour s'assurer que les produits sont correctement prévus et planifiés. Un autre exercice de quantification aura lieu pour les kits IST avec différents acteurs des systèmes (PMO, branche IST du PNLS..) Suite aux différents exercices de quantification, LHSPLA soutiendra également le programme VIH pour diffuser le résultat de quantification, le plan d'approvisionnement 2027 des ARV, les produits de laboratoire et des kits IST et poussera les agents d'approvisionnement à passer des commandes pour permettre des approvisionnements respectant le délai de livraison. Le QFA de LHSPLA collaborera avec les autres programmes de santé (PNLT, PNN, Médicaments essentiels,....) pour gérer leurs exercices annuels de quantification afin d'assurer l'exactitude des résultats. Cet accompagnement transversal de LHSPLA à tous les programmes de santé est une manière d'aider aux bonnes pratiques de quantification des produits de santé et ainsi d'éviter les ruptures de stock et les péremptions | D10: =TRIM(_xlfn.TEXTBEFORE(E10,":")) -> 1.1-4.1 | E10: 1.1-4.1 : Apporter une assistance technique pour l'organisation d'un atélier de quantification des médicaments de la nutrition. | F10: QAD | G10: PNS | H10: PNN | I10: 46028 | J10: 30/05/2026 | L10: *Les Besoins annuels 2027 & 2028 des médicaments et intrants de lutte contre la malnutrition pour les années 2027 & 2028 sont estimés et disponibles * Les Plans d'approvisionnement 2027 & 2028 pour les médicaments et intrants de la nutrition sont finalisés et transmis | M10: *Taux de précision de la quantification des produits traceurs du PNN *Taux d'exécution du plan d'approvisionnement PNN | N10: Disponibilité adéquate des intrants de lutte contre la malnutrition à tous les niveaux de la chaine d'approvisionnement, afin de réduire les risques de rupture et de surstock | O10: Rapport de quantification PNN | P10: Rapports de quantification PNN | Q10: Support and Assistance | R10: Support and Assistance | S10: -Atelier de 5 jours regroupant 15 personnes dont 4 participants LHSPLA Prise en charge LHSPLA *Full perdiem pour le staff LHSPLA *Forfait Transport *Frais de connexion internet *Frais péage *Autres frais | T10: 2335120 | U10: 2009900 | V10: 4345020 | Y10: 0 | Z10: =SUM(T10:Y10) -> 8690040 | AZ10: 2009900 | BP10: =T10-SUM(AA10,AD10,AG10,AJ10,AM10,AP10) -> 2335120 | BQ10: =U10-SUM(AS10,AV10,AZ10,BD10,BH10,BL10) -> 0 | BR10: =W10-SUM(AB10,AE10,AH10,AK10,AN10,AQ10,AT10,AW10,BA10,BE10,BI10,BM10) -> 0 | BS10: =X10-SUM(AC10,AF10,AI10,AL10,AO10,AR10,AU10,AX10,BB10,BF10,BJ10,BN10) -> 0
A11: OO 1.1 : Soutenir les exercices annuels de quantification et de prévision pour le VIH, le paludisme, la tuberculose, les médicaments essentiels et d'autres produits. | B11: 1.1-5 : Apporter un appui technique aux exercices de quantification de la NPSP. | C11: LHSPLA apportera un soutien technique à l'exercice annuel de quantification des ARV/IO et des produits de laboratoire. Le conseiller en quantification plaidera pour l'optimisation du traitement antirétroviral, notamment la priorisation du traitement à base de DTG chez l'enfant (pALD) et chez l'adulte ainsi que la recommandation des présentation des boites de TLD 90 et 180 afin de booster le MMD. De plus, au cours de l'exercice de quantification, le QFA sensibilisera les membres du comité de quantification sur les directives du TPT & IVSA pour s'assurer que les produits sont correctement prévus et planifiés. Un autre exercice de quantification aura lieu pour les kits IST avec différents acteurs des systèmes (PMO, branche IST du PNLS..) Suite aux différents exercices de quantification, LHSPLA soutiendra également le programme VIH pour diffuser le résultat de quantification, le plan d'approvisionnement 2027 des ARV, les produits de laboratoire et des kits IST et poussera les agents d'approvisionnement à passer des commandes pour permettre des approvisionnements respectant le délai de livraison. Le QFA de LHSPLA collaborera avec les autres programmes de santé (PNLT, PNN, Médicaments essentiels,....) pour gérer leurs exercices annuels de quantification afin d'assurer l'exactitude des résultats. Cet accompagnement transversal de LHSPLA à tous les programmes de santé est une manière d'aider aux bonnes pratiques de quantification des produits de santé et ainsi d'éviter les ruptures de stock et les péremptions | D11: =TRIM(_xlfn.TEXTBEFORE(E11,":")) -> 1.1-5.1 | E11: 1.1-5.1 : Apporter une assistance technique pour l'organisation d'un atelier de préquantification des medicaments essentiels. | F11: QAD | G11: NPSP | H11: DA | I11: 46025 | J11: 30/05/2026 | L11: * Les Besoins annuels 2027 des médicaments essentiels sont estimés et disponibles * Le Plan d'approvisionnement 2027 des médicaments essentiels est finalisé et transmis | M11: *Taux de précision de la quantification des médicaments essentiels | N11: Disponibilité adéquate des médicaments essentiels à tous les niveaux de la chaine d'approvisionnement, afin de réduire les risques de rupture et de surstock | O11: Rapport de préquantification | P11: Rapport de quantification | Q11: Support and Assistance | R11: Training | S11: Sans budget | T11: 0 | V11: 0 | Y11: 0 | Z11: =SUM(T11:Y11) -> 0 | BP11: =T11-SUM(AA11,AD11,AG11,AJ11,AM11,AP11) -> 0 | BQ11: =U11-SUM(AS11,AV11,AZ11,BD11,BH11,BL11) -> 0 | BR11: =W11-SUM(AB11,AE11,AH11,AK11,AN11,AQ11,AT11,AW11,BA11,BE11,BI11,BM11) -> 0 | BS11: =X11-SUM(AC11,AF11,AI11,AL11,AO11,AR11,AU11,AX11,BB11,BF11,BJ11,BN11) -> 0
A12: OO 1.1 : Soutenir les exercices annuels de quantification et de prévision pour le VIH, le paludisme, la tuberculose, les médicaments essentiels et d'autres produits. | B12: 1.1-5 : Apporter un appui technique aux exercices de quantification de la NPSP. | C12: LHSPLA apportera un soutien technique à l'exercice annuel de quantification des ARV/IO et des produits de laboratoire. Le conseiller en quantification plaidera pour l'optimisation du traitement antirétroviral, notamment la priorisation du traitement à base de DTG chez l'enfant (pALD) et chez l'adulte ainsi que la recommandation des présentation des boites de TLD 90 et 180 afin de booster le MMD. De plus, au cours de l'exercice de quantification, le QFA sensibilisera les membres du comité de quantification sur les directives du TPT & IVSA pour s'assurer que les produits sont correctement prévus et planifiés. Un autre exercice de quantification aura lieu pour les kits IST avec différents acteurs des systèmes (PMO, branche IST du PNLS..) Suite aux différents exercices de quantification, LHSPLA soutiendra également le programme VIH pour diffuser le résultat de quantification, le plan d'approvisionnement 2027 des ARV, les produits de laboratoire et des kits IST et poussera les agents d'approvisionnement à passer des commandes pour permettre des approvisionnements respectant le délai de livraison. Le QFA de LHSPLA collaborera avec les autres programmes de santé (PNLT, PNN, Médicaments essentiels,....) pour gérer leurs exercices annuels de quantification afin d'assurer l'exactitude des résultats. Cet accompagnement transversal de LHSPLA à tous les programmes de santé est une manière d'aider aux bonnes pratiques de quantification des produits de santé et ainsi d'éviter les ruptures de stock et les péremptions | D12: =TRIM(_xlfn.TEXTBEFORE(E12,":")) -> 1.1-5.2 | E12: 1.1-5.2 : Apporter une assistance technique pour l'organisation d'un atelier de quantification des medicaments essentiels. | F12: QAD | G12: NPSP | H12: DA | I12: 46025 | J12: 30/05/2026 | L12: * Les Besoins annuels 2027 des médicaments essentiels sont estimés et disponibles * Le Plan d'approvisionnement 2027 des médicaments essentiels est finalisé et transmis | M12: *Taux de précision de la quantification des médicaments essentiels | N12: Disponibilité adéquate des médicaments essentiels à tous les niveaux de la chaine d'approvisionnement, afin de réduire les risques de rupture et de surstock | O12: Rapport de quantification | P12: Rapport de quantification | Q12: Support and Assistance | R12: Training | S12: Sans budget | T12: 0 | U12: 0 | V12: 0 | X12: 20050000 | Y12: 0 | Z12: =SUM(T12:Y12) -> 20050000 | AX12: 20050000 | BP12: =T12-SUM(AA12,AD12,AG12,AJ12,AM12,AP12) -> 0 | BQ12: =U12-SUM(AS12,AV12,AZ12,BD12,BH12,BL12) -> 0 | BR12: =W12-SUM(AB12,AE12,AH12,AK12,AN12,AQ12,AT12,AW12,BA12,BE12,BI12,BM12) -> 0 | BS12: =X12-SUM(AC12,AF12,AI12,AL12,AO12,AR12,AU12,AX12,BB12,BF12,BJ12,BN12) -> 0
A13: OO 1.1 : Soutenir les exercices annuels de quantification et de prévision pour le VIH, le paludisme, la tuberculose, les médicaments essentiels et d'autres produits. | B13: 1.1-6 : Apporter un appui technique et financier aux exercices de quantification du programme national de santé de la Mère et de l'Enfant | C13: LHSPLA apportera un soutien technique à l'exercice annuel de quantification des ARV/IO et des produits de laboratoire. Le conseiller en quantification plaidera pour l'optimisation du traitement antirétroviral, notamment la priorisation du traitement à base de DTG chez l'enfant (pALD) et chez l'adulte ainsi que la recommandation des présentation des boites de TLD 90 et 180 afin de booster le MMD. De plus, au cours de l'exercice de quantification, le QFA sensibilisera les membres du comité de quantification sur les directives du TPT & IVSA pour s'assurer que les produits sont correctement prévus et planifiés. Un autre exercice de quantification aura lieu pour les kits IST avec différents acteurs des systèmes (PMO, branche IST du PNLS..) Suite aux différents exercices de quantification, LHSPLA soutiendra également le programme VIH pour diffuser le résultat de quantification, le plan d'approvisionnement 2027 des ARV, les produits de laboratoire et des kits IST et poussera les agents d'approvisionnement à passer des commandes pour permettre des approvisionnements respectant le délai de livraison. Le QFA de LHSPLA collaborera avec les autres programmes de santé (PNLT, PNN, Médicaments essentiels,....) pour gérer leurs exercices annuels de quantification afin d'assurer l'exactitude des résultats. Cet accompagnement transversal de LHSPLA à tous les programmes de santé est une manière d'aider aux bonnes pratiques de quantification des produits de santé et ainsi d'éviter les ruptures de stock et les péremptions | D13: =TRIM(_xlfn.TEXTBEFORE(E13,":")) -> 1.1-6.1 | E13: 1.1-6.1 : Apporter une assistance technique pour l'organisation d'un atelier de préquantification des médicaments pour la prise en charge de la santé de la Mère et de l'enfant dans le cadre de la reduction de la mortalité materno-infantile | F13: QAD | G13: PNS | H13: PNSME | I13: 46027 | J13: 30/06/2026 | L13: * Les Besoins annuels 2027 & 2028 des médicaments de la prise en charge de la Santé de la Mère et de l'Enfant sont estimés et disponibles * Les Plans d'approvisionnement 2027 & 2028 des médicaments de la Santé de la Mère et de l'Enfant sont finalisés et transmis | M13: *Taux de précision de la quantification des produits traceurs du PNSME *Taux d'exécution du plan d'approvisionnement PNSME | N13: Disponibilité adéquate des produits à tous les niveaux de la chaine d'approvisionnement, afin de réduire les risques de rupture dans le cadre de la réduction de la mortalité materno-infantile | O13: Rapport de préquantification PNSME | P13: Rapport de quantification PNSME | Q13: Support and Assistance | R13: Support and Assistance | S13: -Atelier de 4 jours avec 4 participants LHSPLA Prise en charge LHSPLA Location salle Pause café *Forfait carburant véhicule TPM *Full perdiem pour le staff LHSPLA *Forfait carburant *Frais de connexion internet *Frais péage *Autres frais | U13: 0 | V13: 0 | X13: 4311360 | Y13: 0 | Z13: =SUM(T13:Y13) -> 4311360 | BB13: 4083740 | BP13: =T13-SUM(AA13,AD13,AG13,AJ13,AM13,AP13) -> 0 | BQ13: =U13-SUM(AS13,AV13,AZ13,BD13,BH13,BL13) -> 0 | BR13: =W13-SUM(AB13,AE13,AH13,AK13,AN13,AQ13,AT13,AW13,BA13,BE13,BI13,BM13) -> 0 | BS13: =X13-SUM(AC13,AF13,AI13,AL13,AO13,AR13,AU13,AX13,BB13,BF13,BJ13,BN13) -> 227620
A14: OO 1.1 : Soutenir les exercices annuels de quantification et de prévision pour le VIH, le paludisme, la tuberculose, les médicaments essentiels et d'autres produits. | B14: 1.1-6 : Apporter un appui technique et financier aux exercices de quantification du programme national de santé de la Mère et de l'Enfant | C14: LHSPLA apportera un soutien technique à l'exercice annuel de quantification des ARV/IO et des produits de laboratoire. Le conseiller en quantification plaidera pour l'optimisation du traitement antirétroviral, notamment la priorisation du traitement à base de DTG chez l'enfant (pALD) et chez l'adulte ainsi que la recommandation des présentation des boites de TLD 90 et 180 afin de booster le MMD. De plus, au cours de l'exercice de quantification, le QFA sensibilisera les membres du comité de quantification sur les directives du TPT & IVSA pour s'assurer que les produits sont correctement prévus et planifiés. Un autre exercice de quantification aura lieu pour les kits IST avec différents acteurs des systèmes (PMO, branche IST du PNLS..) Suite aux différents exercices de quantification, LHSPLA soutiendra également le programme VIH pour diffuser le résultat de quantification, le plan d'approvisionnement 2027 des ARV, les produits de laboratoire et des kits IST et poussera les agents d'approvisionnement à passer des commandes pour permettre des approvisionnements respectant le délai de livraison. Le QFA de LHSPLA collaborera avec les autres programmes de santé (PNLT, PNN, Médicaments essentiels,....) pour gérer leurs exercices annuels de quantification afin d'assurer l'exactitude des résultats. Cet accompagnement transversal de LHSPLA à tous les programmes de santé est une manière d'aider aux bonnes pratiques de quantification des produits de santé et ainsi d'éviter les ruptures de stock et les péremptions | D14: =TRIM(_xlfn.TEXTBEFORE(E14,":")) -> 1.1-6.2 | E14: 1.1-6.2 : Apporter une assistance technique pour l'organisation d'un atelier de quantification des médicaments pour la prise en charge de la santé de la Mère et de l'enfant dans le cadre de la reduction de la mortalité materno-infantile. | F14: QAD | G14: PNS | H14: PNSME | I14: 46027 | J14: 30/06/2026 | L14: * Les Besoins annuels 2027 & 2028 des médicaments pour la prise en charge de la Santé de la Mère et de l'Enfant sont estimés et disponibles * Les Plans d'approvisionnement 2027 & 2028 des médicaments de la Santé de la Mère et de l'Enfant sont finalisés et transmis | M14: *Taux de précision de la quantification des produits traceurs du PNSME *Taux d'exécution du plan d'approvisionnement PNSME | N14: Disponibilité adéquate des produits à tous les niveaux de la chaine d'approvisionnement, afin de réduire les risques de rupture et de surstock | O14: Rapport de quantification PNSME | P14: Rapport de quantification PNSME | Q14: Support and Assistance | R14: Support and Assistance | S14: -Atelier de 6 jours avec 5 participants LHSPLA Prise en chargeLHSPLA Location de salle Pause café *Forfait carburant véhicule *Full perdiem pour le staff LHSPLA *Forfait Transport *Frais de connexion internet *Frais péage *Autres frais | U14: 0 | V14: 0 | X14: 7115655 | Y14: 0 | Z14: =SUM(T14:Y14) -> 7115655 | BB14: 7115655 | BP14: =T14-SUM(AA14,AD14,AG14,AJ14,AM14,AP14) -> 0 | BQ14: =U14-SUM(AS14,AV14,AZ14,BD14,BH14,BL14) -> 0 | BR14: =W14-SUM(AB14,AE14,AH14,AK14,AN14,AQ14,AT14,AW14,BA14,BE14,BI14,BM14) -> 0 | BS14: =X14-SUM(AC14,AF14,AI14,AL14,AO14,AR14,AU14,AX14,BB14,BF14,BJ14,BN14) -> 0
A15: OO 1.1 : Soutenir les exercices annuels de quantification et de prévision pour le VIH, le paludisme, la tuberculose, les médicaments essentiels et d'autres produits. | B15: 1.1-7 : Apporter un appui technique aux programmes de santé pour la restitution des résultats de quantification et le suivi de la résolution des gaps | C15: Ces reunions, regroupant la DAP, les PTF, les programmes, le Gouvernement (DAF Santé, DGS, etc), devraient permettre de présenter à toutes les parties prenantes les résultats de la quantification et trouver des solutions aux gaps identifiés lors des exercices de quantification | D15: =TRIM(_xlfn.TEXTBEFORE(E15,":")) -> 1.1-7.1 | E15: 1.1-7.1 : Apporter un appui technique et financier aux programmes pour l'organisation de reunions de restitution des résultats de la quantification et le suivi de la résolution des gaps | F15: QAD | G15: PNS | I15: 46029 | J15: 30/08/2026 | L15: *Les résultats des quantifications sont restitués et les gaps sont adressés *La résolution des gaps est suivie et des alertes sont émises quotidiennement | M15: *Taux d'exécution des plans d'approvisionnement | N15: Couverture financière complète des besoins des plans d'approvisionnement 2027 | O15: Rapport de réunions de restitution | P15: Rapport de réunions de restitution | Q15: Support and Assistance | R15: Support and Assistance | S15: Réunion au niveau de chaque PNS (PNLP, PNLS, PNSME) : 20 participants attendus Pause café Pause dejeuner Eau en salle Forfait transport pour la partie nationale (hors PNS) | U15: 515400 | V15: 515400 | W15: 515400 | X15: 515400 | Y15: 0 | Z15: =SUM(T15:Y15) -> 2061600 | AV15: 515400 | BA15: 515400 | BF15: 515400 | BP15: =T15-SUM(AA15,AD15,AG15,AJ15,AM15,AP15) -> 0 | BQ15: =U15-SUM(AS15,AV15,AZ15,BD15,BH15,BL15) -> 0 | BR15: =W15-SUM(AB15,AE15,AH15,AK15,AN15,AQ15,AT15,AW15,BA15,BE15,BI15,BM15) -> 0 | BS15: =X15-SUM(AC15,AF15,AI15,AL15,AO15,AR15,AU15,AX15,BB15,BF15,BJ15,BN15) -> 0
A16: OO 1.1 : Soutenir les exercices annuels de quantification et de prévision pour le VIH, le paludisme, la tuberculose, les médicaments essentiels et d'autres produits. | B16: 1.1-9 : Apporter un appui à la diffusion des hypothèses de quantification | C16: Sous le lead de la DGS et la DAP, cette activité permettra aux PNS (PNLS &PNLP) d'expliquer aux prestataires et PMO, les hypothèses utilisées lors des exercices de quantification pour une utilisation rationnelle des produits de santé. | D16: =TRIM(_xlfn.TEXTBEFORE(E16,":")) -> 1.1-9.1 | E16: 1.1-9.1 : Organiser des reunions de présentation des hypothèses de quantification à travers les plateformes existantes (CREMCAPS, e-learning) | F16: QAD | G16: PNS | I16: 45962 | J16: 30/12/2025 | L16: *Les hypothèses de quantification sont diffusées à travers la plateforme Cremcaps | M16: Nombre de reunions organisées Nombre de gestionnaires orientés | N16: Disponibilité adéquate des produits à tous les niveaux de la chaine d'approvisionnement, afin de réduire les risques de rupture et de surstock | O16: Rapport de réunion | P16: Rapport de réunion | Q16: Support and Assistance | R16: Training | S16: Sans budget | T16: 0 | V16: 0 | Y16: 0 | Z16: =SUM(T16:Y16) -> 0 | BP16: =T16-SUM(AA16,AD16,AG16,AJ16,AM16,AP16) -> 0 | BQ16: =U16-SUM(AS16,AV16,AZ16,BD16,BH16,BL16) -> 0 | BR16: =W16-SUM(AB16,AE16,AH16,AK16,AN16,AQ16,AT16,AW16,BA16,BE16,BI16,BM16) -> 0 | BS16: =X16-SUM(AC16,AF16,AI16,AL16,AO16,AR16,AU16,AX16,BB16,BF16,BJ16,BN16) -> 0
A17: OO 1.1 : Apporter l'assistance technique pour faciliter la distribution des produits de santé des districts sanitaires aux sites non clients directs. | B17: 1.1-10 : Appuyer les Districts sanitaires en équipement informatique | C17: L'équipement en matériel informatique des districts sanitaires est essentiel pour l'opérationnalisation efficace de ses activités et ceux de ses ESPC. Cela permettra d'effectuer le deploiement des nouveaux centres sur leurs aires sanitaires, | D17: =TRIM(_xlfn.TEXTBEFORE(E17,":")) -> 1.1-10.1 | E17: 1.1-10.1 : Equiper Les Districts Sanitaires en matériel informatique pour une opérationnalisation de leurs activités | F17: SI | G17: DGS | I17: 45931 | J17: 46173 | K17: 100% du matériel informatique acquis | L17: 100% du matériel informatique acquis | M17: Nombre de materiel informatique acquis /nombre de materiel informatique prevu | N17: "*Amélioration de la disponibilité des produits * Amelioration de la distribution aux centres de santé" | O17: * Bordereau de livraison *Facture | P17: * Bordereau de livraison *Facture | Q17: Equipment and supplies | R17: Equipment | S17: Acquisition de 35 tablettes (190.000 FCFA / tablette+chargeur) et de 15 ordinateurs bureaux (650 000/ ordinateur) | U17: 0 | V17: 0 | W17: 6650000 | X17: 9750000 | Y17: 0 | Z17: =SUM(T17:Y17) -> 16400000 | AH17: =190000*35 -> 6650000 | AI17: =650000*15 -> 9750000 | AW17: 6650000 | AX17: 9750000 | BP17: =T17-SUM(AA17,AD17,AG17,AJ17,AM17,AP17) -> 0 | BQ17: =U17-SUM(AS17,AV17,AZ17,BD17,BH17,BL17) -> 0 | BR17: =W17-SUM(AB17,AE17,AH17,AK17,AN17,AQ17,AT17,AW17,BA17,BE17,BI17,BM17) -> -6650000 | BS17: =X17-SUM(AC17,AF17,AI17,AL17,AO17,AR17,AU17,AX17,BB17,BF17,BJ17,BN17) -> -9750000
A18: OO 1.1 : Apporter l'assistance technique pour faciliter la distribution des produits de santé des districts sanitaires aux sites non clients directs. | B18: 1.1-11 : Evaluer le niveau d'appropriation de la quantification par les PNS | C18: L'évaluation du niveau d'appropriation de la quantification par les PNS permettra de connaitre le niveau d'appropriation de la quantification par les programmes | D18: =TRIM(_xlfn.TEXTBEFORE(E18,":")) -> 1.1-11.1 | E18: 1.1-11.1 : Mettre en place un GTT chargé de l'évaluation du niveau d'appropriation de la quantification par les PNS | F18: QAD | G18: DAP | H18: PNS | I18: 46143 | J18: 46203 | L18: Le niveau d'appropriation de la quantification par les programmes est connu | N18: Améliorer la qualité de la quantification | O18: compte rendu de GTT | P18: Analyser et diffuser le rapport d'évaluation | Q18: Support and Assistance | R18: Meeting | S18: Sans budget | V18: 0 | Z18: =SUM(T18:Y18) -> 0
A19: OO 1.1 : Apporter l'assistance technique pour faciliter la distribution des produits de santé des districts sanitaires aux sites non clients directs. | B19: 1.1-11 : Evaluer le niveau d'appropriation de la quantification par les PNS | C19: L'évaluation du niveau d'appropriation de la quantification par les PNS permettra de connaitre le niveau d'appropriation de la quantification par les programmes | D19: =TRIM(_xlfn.TEXTBEFORE(E19,":")) -> 1.1-11.2 | E19: 1.1-11.2 : Élaborer un forrmulaire d'évaluation | F19: QAD | G19: DAP | H19: PNS | I19: 46157 | J19: 46203 | L19: Le niveau d'appropriation de la quantification par les programmes est connu | N19: Améliorer la qualité de la quantification | O19: Formulaire d'évaluation disponible | P19: Analyser et diffuser le rapport d'évaluation | Q19: Support and Assistance | R19: Support and Assistance | S19: Sans budget | V19: 0 | Z19: =SUM(T19:Y19) -> 0
A20: OO 1.1 : Apporter l'assistance technique pour faciliter la distribution des produits de santé des districts sanitaires aux sites non clients directs. | B20: 1.1-11 : Evaluer le niveau d'appropriation de la quantification par les PNS | C20: L'évaluation du niveau d'appropriation de la quantification par les PNS permettra de connaitre le niveau d'appropriation de la quantification par les programmes | D20: =TRIM(_xlfn.TEXTBEFORE(E20,":")) -> 1.1-11.3 | E20: 1.1-11.3 :Collecter les réponses des parties prenantes | F20: QAD | G20: DAP | H20: PNS | I20: 46174 | J20: 46203 | L20: Le niveau d'appropriation de la quantification par les programmes est connu | N20: Améliorer la qualité de la quantification | O20: Point de la collecte | P20: Analyser et diffuser le rapport d'évaluation | Q20: Support and Assistance | R20: Support and Assistance | S20: Sans budget | V20: 0 | Z20: =SUM(T20:Y20) -> 0
A21: OO 1.1 : Apporter l'assistance technique pour faciliter la distribution des produits de santé des districts sanitaires aux sites non clients directs. | B21: 1.1-11 : Evaluer le niveau d'appropriation de la quantification par les PNS | C21: L'évaluation du niveau d'appropriation de la quantification par les PNS permettra de connaitre le niveau d'appropriation de la quantification par les programmes | D21: =TRIM(_xlfn.TEXTBEFORE(E21,":")) -> 1.1-11.4 | E21: 1.1-11.4 : Analyser et diffuser le rapport d'évaluation | F21: QAD | G21: DAP | H21: PNS | I21: 46204 | J21: 46264 | L21: Le niveau d'appropriation de la quantification par les programmes est connu | N21: Améliorer la qualité de la quantification | O21: Mail de transmissison | P21: Analyser et diffuser le rapport d'évaluation | Q21: Support and Assistance | R21: Support and Assistance | S21: Sans budget | V21: 0 | Z21: =SUM(T21:Y21) -> 0
A22: OO 1.2 : Apporter l'assistance technique pour faciliter la distribution des produits de santé des districts sanitaires aux sites non clients directs. | B22: 1.2-1 : Faire le suivi de la livraison des produits de santé aux sites deservis par le district sanitaire | C22: L'équipe CAD s'assurera auprès des districts sanitaires de la transmission des rapports par les ESPC, de la disponibilité des chronogrammes et de l'exécution effective de la distribution selon les circuits | D22: =TRIM(_xlfn.TEXTBEFORE(E22,":")) -> 1.2-1.1 | E22: 1.2-1.1 : Faire le suivi la complétude et la promptitude des rapports des sites non clients directs (mSupply, …) | F22: CAD | G22: DAP | H22: DPAS | I22: 45931 | J22: 46295 | K22: . >= 95% de promptitude . 100% de complétude | L22: Proportion d'ESPC ayant bénéficié de livraison sur site = 70% | M22: Promptitude des rapports | N22: Approvisionnement régulier des ESPC | O22: Rapport mensuel | P22: Rapport trimestriel | Q22: Support and Assistance | R22: Support and Assistance | S22: Sans budget | T22: 0 | V22: 0 | W22: 0 | Y22: 0 | Z22: =SUM(T22:Y22) -> 0 | BP22: =T22-SUM(AA22,AD22,AG22,AJ22,AM22,AP22) -> 0 | BQ22: =U22-SUM(AS22,AV22,AZ22,BD22,BH22,BL22) -> 0 | BR22: =W22-SUM(AB22,AE22,AH22,AK22,AN22,AQ22,AT22,AW22,BA22,BE22,BI22,BM22) -> 0 | BS22: =X22-SUM(AC22,AF22,AI22,AL22,AO22,AR22,AU22,AX22,BB22,BF22,BJ22,BN22) -> 0
A23: OO 1.2 : Apporter l'assistance technique pour faciliter la distribution des produits de santé des districts sanitaires aux sites non clients directs. | B23: 1.2-1 : Faire le suivi de la livraison des produits de santé aux sites deservis par le district sanitaire | C23: L'équipe CAD s'assurera auprès des districts sanitaires de la transmission des rapports par les ESPC, de la disponibilité des chronogrammes et de l'exécution effective de la distribution selon les circuits | D23: =TRIM(_xlfn.TEXTBEFORE(E23,":")) -> 1.2-1.2 | E23: 1.2-1.2 : Faire le suivi de la disponibilité du chronogramme de distribution au niveau des districts sanitaires | F23: CAD | G23: DAP | H23: DPAS | I23: 45931 | J23: 46295 | K23: Proportion de district sanitaire utilisant les circuits optimisés pour la distribution au dernier km = 90% | L23: Proportion d'ESPC ayant bénéficié de livraison sur site = 70% | M23: Taux de disponibilité des produits traceurs | N23: Approvisionnement régulier des ESPC | O23: Rapport mensuel | P23: Rapport trimestriel | Q23: Support and Assistance | R23: Support and Assistance | S23: Sans budget | T23: 0 | V23: 0 | W23: 0 | Y23: 0 | Z23: =SUM(T23:Y23) -> 0 | BP23: =T23-SUM(AA23,AD23,AG23,AJ23,AM23,AP23) -> 0 | BQ23: =U23-SUM(AS23,AV23,AZ23,BD23,BH23,BL23) -> 0 | BR23: =W23-SUM(AB23,AE23,AH23,AK23,AN23,AQ23,AT23,AW23,BA23,BE23,BI23,BM23) -> 0 | BS23: =X23-SUM(AC23,AF23,AI23,AL23,AO23,AR23,AU23,AX23,BB23,BF23,BJ23,BN23) -> 0
A24: OO 1.2 : Apporter l'assistance technique pour faciliter la distribution des produits de santé des districts sanitaires aux sites non clients directs. | B24: 1.2-1 : Faire le suivi de la livraison des produits de santé aux sites deservis par le district sanitaire | C24: L'équipe CAD s'assurera auprès des districts sanitaires de la transmission des rapports par les ESPC, de la disponibilité des chronogrammes et de l'exécution effective de la distribution selon les circuits | D24: =TRIM(_xlfn.TEXTBEFORE(E24,":")) -> 1.2-1.3 | E24: 1.2-1.3 : Faire le suivi de l'éxecution effective de la distribution selon le chronogramme de livraison | F24: CAD | G24: DAP | H24: DPAS | I24: 45931 | J24: 46295 | K24: Taux de respect du chronogramme de livraison = 95% | L24: Proportion d'ESPC ayant bénéficié de livraison sur site = 70% | M24: Taux de disponibilité des produits traceurs | N24: Approvisionnement régulier des ESPC | O24: Rapport mensuel | P24: Rapport trimestriel | Q24: Support and Assistance | R24: Support and Assistance | S24: Sans budget | T24: 0 | V24: 0 | W24: 0 | Y24: 0 | Z24: =SUM(T24:Y24) -> 0 | BP24: =T24-SUM(AA24,AD24,AG24,AJ24,AM24,AP24) -> 0 | BQ24: =U24-SUM(AS24,AV24,AZ24,BD24,BH24,BL24) -> 0 | BR24: =W24-SUM(AB24,AE24,AH24,AK24,AN24,AQ24,AT24,AW24,BA24,BE24,BI24,BM24) -> 0 | BS24: =X24-SUM(AC24,AF24,AI24,AL24,AO24,AR24,AU24,AX24,BB24,BF24,BJ24,BN24) -> 0
A25: OO 1.2 : Apporter l'assistance technique pour faciliter la distribution des produits de santé des districts sanitaires aux sites non clients directs. | B25: 1.2-2 : Appuyer l'équipe projet e-STOCK en équipement informatique | C25: Cette activité vise à renforcer les capacités opérationnelles de l’équipe projet à travers la dotation en équipements informatiques. Cet appui permettra d’assurer un suivi technique plus efficace, une meilleure réactivité dans la résolution des incidents, et une performance accrue dans la mise en œuvre des activités liées à mSupply. | D25: =TRIM(_xlfn.TEXTBEFORE(E25,":")) -> 1.2-2.1 | E25: 1.2-2.1 : Doter l’équipe projet e-STOCK en équipement informatique. | F25: SI | G25: DAP | I25: 45962 | J25: 31/12/2025 | K25: 100% du matériel informatique acquis | L25: 100% du matériel informatique acquis | M25: Nombre de materiel informatique acquis /nombre de materiel informatique prevu | N25: *Amélioration de la disponibilité des produits * Réactivité dans la prise en charge des incidents et demandes mSupply | O25: * Bordereau de livraison *Facture | P25: * Bordereau de livraison *Facture | Q25: Equipment and supplies | R25: Equipment | S25: Acquisition de 01 ordinateur portable Core i7 | T25: 975000 | V25: 975000 | Y25: 0 | Z25: =SUM(T25:Y25) -> 1950000 | AG25: 975000 | BP25: =T25-SUM(AA25,AD25,AG25,AJ25,AM25,AP25) -> 0 | BQ25: =U25-SUM(AS25,AV25,AZ25,BD25,BH25,BL25) -> 0 | BR25: =W25-SUM(AB25,AE25,AH25,AK25,AN25,AQ25,AT25,AW25,BA25,BE25,BI25,BM25) -> 0 | BS25: =X25-SUM(AC25,AF25,AI25,AL25,AO25,AR25,AU25,AX25,BB25,BF25,BJ25,BN25) -> 0
A26: OO 1.2 : Apporter l'assistance technique pour faciliter la distribution des produits de santé des districts sanitaires aux sites non clients directs. | B26: 1.2-3 : Equiper la NPSP en équipement informatique | C26: L’acquisition de matériel informatique essentiel pour le bon fonctionnement et l'amélioration des performances de la NPSP. Cela permettra d'optimiser ses opérations quotidiennes et aussi d'assurer la qualité et la fiabilité des services offerts. | D26: =TRIM(_xlfn.TEXTBEFORE(E26,":")) -> 1.2-3.1 | E26: 1.2-3.1 : Equiper la NPSP en équipement informatique | F26: SI | G26: NPSP-CI | H26: DAF/ DSI | I26: 45667 | J26: 46203 | K26: 100% du matériel informatique acquis | L26: 100% du matériel informatique acquis | M26: Nombre de materiel informatique acquis /nombre de materiel informatique prevu | N26: *Amélioration de la disponibilité des produits * Amelioration de la distribution aux centres de santé" | O26: * Bordereau de livraison *Facture | P26: * Bordereau de livraison *Facture | Q26: Equipment and supplies | R26: Equipment | S26: Acquisition de 37 ordinateurs portables en vue d'équiper la NPSP | T26: 14610000 | U26: 0 | V26: 14610000 | Y26: 23400000 | Z26: =SUM(T26:Y26) -> 52620000 | AY26: 23400000 | BP26: =T26-SUM(AA26,AD26,AG26,AJ26,AM26,AP26) -> 14610000 | BQ26: =U26-SUM(AS26,AV26,AZ26,BD26,BH26,BL26) -> 0 | BR26: =W26-SUM(AB26,AE26,AH26,AK26,AN26,AQ26,AT26,AW26,BA26,BE26,BI26,BM26) -> 0 | BS26: =X26-SUM(AC26,AF26,AI26,AL26,AO26,AR26,AU26,AX26,BB26,BF26,BJ26,BN26) -> 0
A27: OO 1.3 : Assister les régions, districts et hôpitaux de référence dans la gestion des stocks et la coordination des activités de la chaîne d’approvisionnement visant à accroître la disponibilité des produits au point de prestation de services | B27: 1.3-1 : Faciliter la communication entre les acteurs de la chaîne d'approvisionnement y compris ceux du niveau communautaire | C27: LHSPLA apportera une assistance aux prestataires des structures concernées afin de faciliter les échanges des informations logistiques des produits de santé du niveau central jusqu'au niveau communautaire (transmission des rapport-Commandes de qualité dans les délais requis, disponibilité des stocks, mise à niveau des stocks, SAP, ...). Les contacts téléphoniques de ces prestataires, inserrés dans la flotte, seront mis à jour mensuellement. | D27: =TRIM(_xlfn.TEXTBEFORE(E27,":")) -> 1.3-1.1 | E27: 1.3-1.1 : Faire la mise à jour mensuelle des contacts téléphoniques des prestataires à insérer dans la flotte | F27: CAD | G27: DAP | H27: DPAS / DMOSE | I27: 45931 | J27: 46295 | K27: 100% des structures ont intégré dans la flotte | L27: Au moins 98% des sites ont transmis des Rapport commande de qualité dans les délais | M27: Nombres de structures de santé beneficiant de la flotte | N27: Echanges d'informations et suivi des activités Données de qualité dans e-SIGL/mSupply | O27: Points mensuels structures dans la flotte NPSP | P27: Rapport trimestriel | Q27: Support and Assistance | R27: Support and Assistance | S27: Sans budget | T27: 0 | V27: 0 | W27: 0 | Z27: =SUM(T27:Y27) -> 0 | BP27: =T27-SUM(AA27,AD27,AG27,AJ27,AM27,AP27) -> 0 | BQ27: =U27-SUM(AS27,AV27,AZ27,BD27,BH27,BL27) -> 0 | BR27: =W27-SUM(AB27,AE27,AH27,AK27,AN27,AQ27,AT27,AW27,BA27,BE27,BI27,BM27) -> 0 | BS27: =X27-SUM(AC27,AF27,AI27,AL27,AO27,AR27,AU27,AX27,BB27,BF27,BJ27,BN27) -> 0
A28: OO 1.3 : Assister les régions, districts et hôpitaux de référence dans la gestion des stocks et la coordination des activités de la chaîne d’approvisionnement visant à accroître la disponibilité des produits au point de prestation de services | B28: 1.3-1 : Faciliter la communication entre les acteurs de la chaîne d'approvisionnement y compris ceux du niveau communautaire | C28: LHSPLA apportera une assistance aux prestataires des structures concernées afin de faciliter les échanges des informations logistiques des produits de santé du niveau central jusqu'au niveau communautaire (transmission des rapport-Commandes de qualité dans les délais requis, disponibilité des stocks, mise à niveau des stocks, SAP, ...). Les contacts téléphoniques de ces prestataires, inserrés dans la flotte, seront mis à jour mensuellement. | D28: =TRIM(_xlfn.TEXTBEFORE(E28,":")) -> 1.3-1.2 | E28: 1.3-1.2 : Fournir des forfaits de communication et de connexion internet aux structures du niveau central jusqu'au niveau communautaire. | F28: CAD | G28: DAP | H28: DPAS | I28: 45931 | J28: 46295 | K28: Au moins 98% des numéros des structures identifiées sont dans la flotte NPSP | L28: Au moins 98% des sites ont transmis des Rapport commande de qualité dans les délais | M28: Nombres d'acteurs bénéficiares de la flotte | N28: Echanges d'informations et suivi des activités Présence de données de qualité dans e-SIGL/mSupply | O28: Point des sites clients directs identifiés qui ont un numéro MTN actif dans la flotte NPSP | P28: Rapport trimestriel | Q28: Consultants | R28: Consultants | S28: . 33 contacts des Pharmaciens régionaux (dotation mensuelle de 10000 Fcfa par contact sur 06 mois pour les appels), . 34 contacts des Pharmaciens de District (dotation mensuelle de 5000 Fcfa par contact sur 06 mois), . 55 contacts des gestionnaires des autres sites clients directs (dotation mensuelle de 3000 Fcfa par contact sur 06 mois), . 6 contacts de gestionnaires de la DPAS (dotation mensuelle de 3000 Fcfa par contact sur 06 mois) | T28: 4098000 | U28: 0 | V28: 4098000 | W28: 15936000 | Z28: =SUM(T28:Y28) -> 24132000 | AD28: 2049000 | AE28: 3984000 | AG28: 2049000 | AH28: 3984000 | AW28: 11572430 | BP28: =T28-SUM(AA28,AD28,AG28,AJ28,AM28,AP28) -> 0 | BQ28: =U28-SUM(AS28,AV28,AZ28,BD28,BH28,BL28) -> 0 | BR28: =W28-SUM(AB28,AE28,AH28,AK28,AN28,AQ28,AT28,AW28,BA28,BE28,BI28,BM28) -> -3604430 | BS28: =X28-SUM(AC28,AF28,AI28,AL28,AO28,AR28,AU28,AX28,BB28,BF28,BJ28,BN28) -> 0
A29: OO 1.3 : Assister les régions, districts et hôpitaux de référence dans la gestion des stocks et la coordination des activités de la chaîne d’approvisionnement visant à accroître la disponibilité des produits au point de prestation de services | B29: 1.3-1 : Faciliter la communication entre les acteurs de la chaîne d'approvisionnement y compris ceux du niveau communautaire | C29: LHSPLA apportera une assistance aux prestataires des structures concernées afin de faciliter les échanges des informations logistiques des produits de santé du niveau central jusqu'au niveau communautaire (transmission des rapport-Commandes de qualité dans les délais requis, disponibilité des stocks, mise à niveau des stocks, SAP, ...). Les contacts téléphoniques de ces prestataires, inserrés dans la flotte, seront mis à jour mensuellement. | D29: =TRIM(_xlfn.TEXTBEFORE(E29,":")) -> 1.3-1.3 | E29: 1.3-1.3: Suivre la complétude et la promptitude des RCM des sites clients directs de la NPSP à partir du eSIGL | F29: CAD | G29: DAP | H29: DPAS / DMOSE | I29: 45931 | J29: 46295 | K29: 98% de promptitude et 100% de complétude | L29: Au moins 98% des sites ont transmis des Rapport commande de qualité dans les délais | M29: Promptitude des rapports | N29: Echanges d'informations et suivi des activités Présence de données de qualité dans e-SIGL/mSupply | O29: Point mensuel de la promptitude et complétude des rapports transmis dans e-SIGL (Voir rapport trimestriel) | P29: Rapport trimestriel | Q29: Support and Assistance | R29: Support and Assistance | S29: Sans budget | T29: 0 | V29: 0 | W29: 0 | Z29: =SUM(T29:Y29) -> 0 | BP29: =T29-SUM(AA29,AD29,AG29,AJ29,AM29,AP29) -> 0 | BQ29: =U29-SUM(AS29,AV29,AZ29,BD29,BH29,BL29) -> 0 | BR29: =W29-SUM(AB29,AE29,AH29,AK29,AN29,AQ29,AT29,AW29,BA29,BE29,BI29,BM29) -> 0 | BS29: =X29-SUM(AC29,AF29,AI29,AL29,AO29,AR29,AU29,AX29,BB29,BF29,BJ29,BN29) -> 0
A30: OO 1.3 : Assister les régions, districts et hôpitaux de référence dans la gestion des stocks et la coordination des activités de la chaîne d’approvisionnement visant à accroître la disponibilité des produits au point de prestation de services | B30: 1.3-1 : Faciliter la communication entre les acteurs de la chaîne d'approvisionnement y compris ceux du niveau communautaire | C30: LHSPLA apportera une assistance aux prestataires des structures concernées afin de faciliter les échanges des informations logistiques des produits de santé du niveau central jusqu'au niveau communautaire (transmission des rapport-Commandes de qualité dans les délais requis, disponibilité des stocks, mise à niveau des stocks, SAP, ...). Les contacts téléphoniques de ces prestataires, inserrés dans la flotte, seront mis à jour mensuellement. | D30: =TRIM(_xlfn.TEXTBEFORE(E30,":")) -> 1.3-1.4 | E30: 1.3-1.4 : Contacter les gestionnaires pour le suivi des activités logistiques et les coacher au besoin | F30: CAD | G30: DAP | H30: DPAS / DMOSE | I30: 45931 | J30: 46295 | K30: Au moins 90% des gestionnaires coachés rapportent correctement dans e-SIGL | L30: Au moins 98% des sites ont transmis des Rapport commande de qualité dans les délais | M30: Nombre de gestionnaires coachés | N30: Echanges d'informations et suivi des activités Présence de données de qualité dans e-SIGL/mSupply | O30: Point mensuel des personnes coachées au remplissage correct dans e-SIGL | P30: Rapport trimestriel | Q30: Support and Assistance | R30: Support and Assistance | S30: Sans budget | T30: 0 | V30: 0 | W30: 0 | Z30: =SUM(T30:Y30) -> 0 | BP30: =T30-SUM(AA30,AD30,AG30,AJ30,AM30,AP30) -> 0 | BQ30: =U30-SUM(AS30,AV30,AZ30,BD30,BH30,BL30) -> 0 | BR30: =W30-SUM(AB30,AE30,AH30,AK30,AN30,AQ30,AT30,AW30,BA30,BE30,BI30,BM30) -> 0 | BS30: =X30-SUM(AC30,AF30,AI30,AL30,AO30,AR30,AU30,AX30,BB30,BF30,BJ30,BN30) -> 0
A31: OO 1.3 : Assister les régions, districts et hôpitaux de référence dans la gestion des stocks et la coordination des activités de la chaîne d’approvisionnement visant à accroître la disponibilité des produits au point de prestation de services | B31: 1.3-2 : Assister les régions, districts et hôpitaux dans la coordination des activités logistiquess et la prise de décisions | C31: LHSPLA assistera techniquement et financièrement les régions, districts et hôpitaux dans la mise en œuvre des activités logistiques. Dans ce cadre, des visites de sites, des réunions de coordination, des supervisions formatives, des formations et des coachings seront organisées avec l'appui de LHSPLA / LHSPLA will technically and financially assist regions, districts and hospitals in the implementation of logistics activities. In this context, site visits, coordination meetings, formative supervision, training and coaching will be organized with the support of LHSPLA. | D31: =TRIM(_xlfn.TEXTBEFORE(E31,":")) -> 1.3-2.2 | E31: 1.3-2.2 : Organiser des visites d'assistance technique aux acteurs de la chaîne d'approvisionnement décentralisée | F31: CAD | G31: DAP | H31: DPAS | I31: 45931 | J31: 46295 | K31: Pour le COP: Au moins 50 sites clients directs sont visités sur un trimestre (au moins 25 par bureau CAD). Les sites à visiter sont identifiés selon certains critères (coaching, SIMS, ...) | L31: 100% des acteurs des sites dont la performanceest inférieur aux objectifs ont été identifiés et sont accompagnés | M31: Taux de mise en oeuvre des recommandations ( Cible: 75% des recommandations des visites ont été mise en oeuvre) | N31: *Améliorer les activités de la chaîne d'approvisionnement *Contribuer à la mise à niveau des stocks des sites clients directs par région *Coaching des gestionnaires des ESPC sur les activités logistiques et de rapportage *Coaching des gestionnaires des sites clients directs sur les activités logistiques et de rapportage *Echanges d'informations et suivi des activités de la chaîne d'approvisionnement *Echanges d'informations avec les prescripteurs et prises de décision sur les consommations de certains produits | O31: Rapport de mission | P31: Rapport trimestriel | Q31: Support and Assistance | R31: Site visits | S31: . Nombre de structures à visiter: 50 (25 CAD Abidjan - 25 CAD Bouake) . Nombre de participants: 7 . Durée de la mission : 10 jours . Fréquence: 1 /trimestre . Elements du budget: * Full perdiem pour le staff * Forfait collation pour les acteurs (PR) du niveau décentralisé * carburant | T31: 10913835 | U31: 10708825 | V31: 21622660 | W31: 0 | X31: 3046482 | Z31: =SUM(T31:Y31) -> 46291802 | AD31: 10913835 | AL31: 10014131 | BH31: 10708825 | BJ31: 3046482 | BP31: =T31-SUM(AA31,AD31,AG31,AJ31,AM31,AP31) -> 0 | BQ31: =U31-SUM(AS31,AV31,AZ31,BD31,BH31,BL31) -> 0 | BR31: =W31-SUM(AB31,AE31,AH31,AK31,AN31,AQ31,AT31,AW31,BA31,BE31,BI31,BM31) -> 0 | BS31: =X31-SUM(AC31,AF31,AI31,AL31,AO31,AR31,AU31,AX31,BB31,BF31,BJ31,BN31) -> -10014131
A32: OO 1.3 : Assister les régions, districts et hôpitaux de référence dans la gestion des stocks et la coordination des activités de la chaîne d’approvisionnement visant à accroître la disponibilité des produits au point de prestation de services | B32: 1.3-2 : Assister les régions, districts et hôpitaux dans la coordination des activités logistiquess et la prise de décisions | C32: LHSPLA assistera techniquement et financièrement les régions, districts et hôpitaux dans la mise en œuvre des activités logistiques. Dans ce cadre, des visites de sites, des réunions de coordination, des supervisions formatives, des formations et des coachings seront organisées avec l'appui de LHSPLA / LHSPLA will technically and financially assist regions, districts and hospitals in the implementation of logistics activities. In this context, site visits, coordination meetings, formative supervision, training and coaching will be organized with the support of LHSPLA. | D32: =TRIM(_xlfn.TEXTBEFORE(E32,":")) -> 1.3-2.3 | E32: 1.3-2.3 : Apporter un appui technique et financier aux réunions régionales d’analyse et de mise à niveau des stocks | F32: CAD | G32: DAP | H32: DPAS | I32: 45931 | J32: 46295 | K32: Les 33 Régions sanitaires ont réalisées 04 réunions d'analyses de Stocks au cours de l'année | L32: 100% des acteurs des sites dont la performanceest inférieur aux objectifs ont été identifiés et sont accompagnés | M32: Taux d'exécution des plans de rédistribution (cible = 100%) | N32: *Améliorer les activités de la chaîne d'approvisionnement *Contribuer à la mise à niveau des stocks des sites clients directs par région *Coaching des gestionnaires des ESPC sur les activités logistiques et de rapportage *Coaching des gestionnaires des sites clients directs sur les activités logistiques et de rapportage *Echanges d'informations et suivi des activités de la chaîne d'approvisionnement *Echanges d'informations avec les prescripteurs et prises de décision sur les consommations de certains produits | O32: Compte-rendu de réunion | P32: Rapport trimestriel | Q32: Support and Assistance | R32: Other : financial support for beneficiaries | S32: Organiser sur 1 trimestre, 1 Réunion en présentiel et 1 réunion en visio-conférence dans chacune des 33 régions. Les participants sont: 33 DR, 113 DS, 18 EPHR, 5 CHU, EPHD et CSU à raison d'une personne par structure. Un forfait collation de 10000 F pour chaque personne non hébergée au cours des réunions en présentiel. Des full perdiems de 40000 Fcfa pour les personnes hébergées au cours des réunions en présentiel. Des forfaits connexion internet de 3000 Fcfa /personne pour les participants autres que les pharmaciens de région au cours des réunions en visio-conférence. Il y aura des frais de transfert de fonds de la NPSP aux 33 régions sanitaires. Chaque réunion en présentiel vera la participation de l'équipe CAD (2 conseillers techniques, 6 assistants et 2 conducteurs) sur 10 jours. Il est prévu le full perdiem pour le staff et 4 véhicules avec une dotation en carburant avec des frais de transfert de fonds. Il est prévu un appui au plan de redéploiement issu de la réunion. le montant dépendra du circuit établi. | T32: 20877531 | U32: 25396449 | V32: 46273980 | W32: 0 | X32: 26096225 | Z32: =SUM(T32:Y32) -> 118644185 | AD32: 20877531 | AF32: 6130700 | AI32: 25896399 | AV32: 25396449 | AX32: 23826756 | BP32: =T32-SUM(AA32,AD32,AG32,AJ32,AM32,AP32) -> 0 | BQ32: =U32-SUM(AS32,AV32,AZ32,BD32,BH32,BL32) -> 0 | BR32: =W32-SUM(AB32,AE32,AH32,AK32,AN32,AQ32,AT32,AW32,BA32,BE32,BI32,BM32) -> 0 | BS32: =X32-SUM(AC32,AF32,AI32,AL32,AO32,AR32,AU32,AX32,BB32,BF32,BJ32,BN32) -> -29757630
A33: OO 1.3 : Assister les régions, districts et hôpitaux de référence dans la gestion des stocks et la coordination des activités de la chaîne d’approvisionnement visant à accroître la disponibilité des produits au point de prestation de services | B33: 1.3-2 : Assister les régions, districts et hôpitaux dans la coordination des activités logistiquess et la prise de décisions | C33: LHSPLA assistera techniquement et financièrement les régions, districts et hôpitaux dans la mise en œuvre des activités logistiques. Dans ce cadre, des visites de sites, des réunions de coordination, des supervisions formatives, des formations et des coachings seront organisées avec l'appui de LHSPLA / LHSPLA will technically and financially assist regions, districts and hospitals in the implementation of logistics activities. In this context, site visits, coordination meetings, formative supervision, training and coaching will be organized with the support of LHSPLA. | D33: =TRIM(_xlfn.TEXTBEFORE(E33,":")) -> 1.3-2.4 | E33: 1.3-2.4 : Organiser des rencontres d'orientation logistique au niveau départemental | F33: CAD | G33: DAP | H33: DPAS | I33: 45931 | J33: 46295 | K33: 100% des districts sanitaires ont réalisés toutes les réunions prévues | L33: 100% des acteurs des sites dont la performanceest inférieur aux objectifs ont été identifiés et sont accompagnés | M33: Nombres d'acteurs accompagnés (cible= 100%) | N33: *Améliorer les activités de la chaîne d'approvisionnement *Contribuer à la mise à niveau des stocks des sites clients directs par région *Coaching des gestionnaires des ESPC sur les activités logistiques et de rapportage *Coaching des gestionnaires des sites clients directs sur les activités logistiques et de rapportage *Echanges d'informations et suivi des activités de la chaîne d'approvisionnement *Echanges d'informations avec les prescripteurs et prises de décision sur les consommations de certains produits | O33: Rapport de la réunion | P33: Rapport trimestriel | Q33: Support and Assistance | R33: Other : financial support for beneficiaries | S33: Appui financier pour les rencontres trimestrielles d'orientation logistique sur deux trimestres à raison d'une dotation de 200000 F/district/trimestre pour 44 districts (22 pour Abidjan et 20 pour Bouaké) Participation des équipes CAD en full perdiems et forfait carburant avec les frais de transfert de fonds pour 42 districts | T33: 21699183 | U33: 0 | V33: 21699183 | W33: 0 | X33: 40332983 | Y33: 0 | Z33: =SUM(T33:Y33) -> 83731349 | AG33: 21699183 | AR33: 23878163 | AX33: 33493899 | BP33: =T33-SUM(AA33,AD33,AG33,AJ33,AM33,AP33) -> 0 | BQ33: =U33-SUM(AS33,AV33,AZ33,BD33,BH33,BL33) -> 0 | BR33: =W33-SUM(AB33,AE33,AH33,AK33,AN33,AQ33,AT33,AW33,BA33,BE33,BI33,BM33) -> 0 | BS33: =X33-SUM(AC33,AF33,AI33,AL33,AO33,AR33,AU33,AX33,BB33,BF33,BJ33,BN33) -> -17039079
A34: OO 1.3 : Assister les régions, districts et hôpitaux de référence dans la gestion des stocks et la coordination des activités de la chaîne d’approvisionnement visant à accroître la disponibilité des produits au point de prestation de services | B34: 1.3-2 : Assister les régions, districts et hôpitaux dans la coordination des activités logistiquess et la prise de décisions | C34: LHSPLA assistera techniquement et financièrement les régions, districts et hôpitaux dans la mise en œuvre des activités logistiques. Dans ce cadre, des visites de sites, des réunions de coordination, des supervisions formatives, des formations et des coachings seront organisées avec l'appui de LHSPLA / LHSPLA will technically and financially assist regions, districts and hospitals in the implementation of logistics activities. In this context, site visits, coordination meetings, formative supervision, training and coaching will be organized with the support of LHSPLA. | D34: =TRIM(_xlfn.TEXTBEFORE(E34,":")) -> 1.3-2.5 | E34: 1.3-2.5 : Apporter un appui au renforcement du management et du leadership des acteurs de la chaine d'approvisionnement decentralisée | F34: CAD | G34: DAP | H34: DPAS | I34: 45931 | J34: 46295 | K34: Les responsables de pharmacies disposent de connaissances renforcées en leadership et en gestion d’équipe. | L34: 100% des acteurs des sites dont la performanceest inférieur aux objectifs ont été identifiés et sont accompagnés | N34: *Améliorer les activités de la chaîne d'approvisionnement *Contribuer à la mise à niveau des stocks des sites clients directs par région *Coaching des gestionnaires des ESPC sur les activités logistiques et de rapportage *Coaching des gestionnaires des sites clients directs sur les activités logistiques et de rapportage *Echanges d'informations et suivi des activités de la chaîne d'approvisionnement *Echanges d'informations avec les prescripteurs et prises de décision sur les consommations de certains produits | O34: Rapport de la mission | P34: Rapport trimestriel | Q34: Support and Assistance | R34: Support and Assistance | S34: Budget MCH: . Nombre de régions à visiter: 4 (2 CAD Abidjan - 2 CAD Bouake) . Nombre de participants: 6 . Durée de la mission : 5 jours . Fréquence: 1 /trimestre . Elements du budget: * Full perdiem pour le staff * Full perdiem & Forfait collation pour les acteurs (PR) du niveau décentralisé * carburant | T34: 0 | U34: 0 | V34: 0 | W34: 0 | X34: 6809122 | Y34: 0 | Z34: =SUM(T34:Y34) -> 6809122 | AR34: 4539415 | AX34: 6809122 | BP34: =T34-SUM(AA34,AD34,AG34,AJ34,AM34,AP34) -> 0 | BQ34: =U34-SUM(AS34,AV34,AZ34,BD34,BH34,BL34) -> 0 | BR34: =W34-SUM(AB34,AE34,AH34,AK34,AN34,AQ34,AT34,AW34,BA34,BE34,BI34,BM34) -> 0 | BS34: =X34-SUM(AC34,AF34,AI34,AL34,AO34,AR34,AU34,AX34,BB34,BF34,BJ34,BN34) -> -4539415
A35: OO 1.3 : Assister les régions, districts et hôpitaux de référence dans la gestion des stocks et la coordination des activités de la chaîne d’approvisionnement visant à accroître la disponibilité des produits au point de prestation de services | B35: 1.3-2 : Assister les régions, districts et hôpitaux dans la coordination des activités logistiquess et la prise de décisions | C35: LHSPLA assistera techniquement et financièrement les régions, districts et hôpitaux dans la mise en œuvre des activités logistiques. Dans ce cadre, des visites de sites, des réunions de coordination, des supervisions formatives, des formations et des coachings seront organisées avec l'appui de LHSPLA / LHSPLA will technically and financially assist regions, districts and hospitals in the implementation of logistics activities. In this context, site visits, coordination meetings, formative supervision, training and coaching will be organized with the support of LHSPLA. | D35: =TRIM(_xlfn.TEXTBEFORE(E35,":")) -> 1.3-2.6 | E35: 1.3-2.6 : Organiser 4 réunions de coordination en ligne sur les activités de la chaîne d’approvisionnement avec les points focaux des PMO | F35: CAD | G35: PNS | H35: DPAS | I35: 45931 | J35: 46295 | K35: 100% des réunions planifiées ont été réalisées dans les delais | L35: 100% des acteurs des sites dont la performanceest inférieur aux objectifs ont été identifiés et sont accompagnés | M35: Taux de recommandations mise en oeuvre à l'issu de ces rencontres (Cible = 75%) | N35: *Améliorer les activités de la chaîne d'approvisionnement *Contribuer à la mise à niveau des stocks des sites clients directs par région *Coaching des gestionnaires des ESPC sur les activités logistiques et de rapportage *Coaching des gestionnaires des sites clients directs sur les activités logistiques et de rapportage *Echanges d'informations et suivi des activités de la chaîne d'approvisionnement *Echanges d'informations avec les prescripteurs et prises de décision sur les consommations de certains produits | O35: Compte-rendu de réunion de coordination | P35: Rapport trimestriel | Q35: Support and Assistance | R35: Training | S35: Sans budget | T35: 0 | V35: 0 | W35: 0 | Y35: 0 | Z35: =SUM(T35:Y35) -> 0 | BP35: =T35-SUM(AA35,AD35,AG35,AJ35,AM35,AP35) -> 0 | BQ35: =U35-SUM(AS35,AV35,AZ35,BD35,BH35,BL35) -> 0 | BR35: =W35-SUM(AB35,AE35,AH35,AK35,AN35,AQ35,AT35,AW35,BA35,BE35,BI35,BM35) -> 0 | BS35: =X35-SUM(AC35,AF35,AI35,AL35,AO35,AR35,AU35,AX35,BB35,BF35,BJ35,BN35) -> 0
A36: OO 1.3 : Assister les régions, districts et hôpitaux de référence dans la gestion des stocks et la coordination des activités de la chaîne d’approvisionnement visant à accroître la disponibilité des produits au point de prestation de services | B36: 1.3-2 : Assister les régions, districts et hôpitaux dans la coordination des activités logistiquess et la prise de décisions | C36: LHSPLA assistera techniquement et financièrement les régions, districts et hôpitaux dans la mise en œuvre des activités logistiques. Dans ce cadre, des visites de sites, des réunions de coordination, des supervisions formatives, des formations et des coachings seront organisées avec l'appui de LHSPLA / LHSPLA will technically and financially assist regions, districts and hospitals in the implementation of logistics activities. In this context, site visits, coordination meetings, formative supervision, training and coaching will be organized with the support of LHSPLA. | D36: =TRIM(_xlfn.TEXTBEFORE(E36,":")) -> 1.3-2.7 | E36: 1.3-2.7 :Organiser une orientation des pharmaciens de régions sur le management et le leadership dans les activités de chaine d'approvisionnement décentralisée | F36: CAD | G36: DAP | H36: DPAS | I36: 45931 | J36: 46295 | K36: 4 pharmaciens de régions dans 4 régions sanitaires ont leur capacité manageriale renforcée | L36: 100% des acteurs des sites dont la performanceest inférieur aux objectifs ont été identifiés et sont accompagnés | N36: *Améliorer les activités de la chaîne d'approvisionnement *Contribuer à la mise à niveau des stocks des sites clients directs par région *Coaching des gestionnaires des ESPC sur les activités logistiques et de rapportage *Coaching des gestionnaires des sites clients directs sur les activités logistiques et de rapportage *Echanges d'informations et suivi des activités de la chaîne d'approvisionnement *Echanges d'informations avec les prescripteurs et prises de décision sur les consommations de certains produits | O36: Rapport de formation | P36: Rapport trimestriel | Q36: Support and Assistance | R36: Support and Assistance | S36: Budget MCH: Une formation ens alle. Nombre de participants : 15, qui recevront des full perdiem, un forfait transport et du carburant | T36: 0 | U36: 0 | V36: 0 | W36: 0 | X36: 4626958 | Y36: 0 | Z36: =SUM(T36:Y36) -> 4626958 | AI36: 4626958 | AX36: 4626958 | BP36: =T36-SUM(AA36,AD36,AG36,AJ36,AM36,AP36) -> 0 | BQ36: =U36-SUM(AS36,AV36,AZ36,BD36,BH36,BL36) -> 0 | BR36: =W36-SUM(AB36,AE36,AH36,AK36,AN36,AQ36,AT36,AW36,BA36,BE36,BI36,BM36) -> 0 | BS36: =X36-SUM(AC36,AF36,AI36,AL36,AO36,AR36,AU36,AX36,BB36,BF36,BJ36,BN36) -> -4626958
A37: OO 1.3 : Assister les régions, districts et hôpitaux de référence dans la gestion des stocks et la coordination des activités de la chaîne d’approvisionnement visant à accroître la disponibilité des produits au point de prestation de services | B37: 1.3-2 : Assister les régions, districts et hôpitaux dans la coordination des activités logistiquess et la prise de décisions | C37: LHSPLA assistera techniquement et financièrement les régions, districts et hôpitaux dans la mise en œuvre des activités logistiques. Dans ce cadre, des visites de sites, des réunions de coordination, des supervisions formatives, des formations et des coachings seront organisées avec l'appui de LHSPLA / LHSPLA will technically and financially assist regions, districts and hospitals in the implementation of logistics activities. In this context, site visits, coordination meetings, formative supervision, training and coaching will be organized with the support of LHSPLA. | D37: =TRIM(_xlfn.TEXTBEFORE(E37,":")) -> 1.3-2.8 | E37: 1.3-2.8 : Organiser 4 réunions trimestrielles avec les acteurs impliqués dans la gestion des produits de santé de la mère et de l'enfant (PNSME,DAP, NPSP,PMO, LHSPLA...) | F37: CAD | G37: PNS | H37: PNSME | I37: 45931 | J37: 46295 | K37: 100% des réunions planifiées ont été réalisées dans les delais | L37: 100% des acteurs des sites dont la performanceest inférieur aux objectifs ont été identifiés et sont accompagnés | M37: Taux de recommandations mise en oeuvre à l'issu de ces rencontres (Cible = 75%) | N37: *Améliorer les activités de la chaîne d'approvisionnement *Contribuer à la mise à niveau des stocks des sites clients directs par région *Coaching des gestionnaires des ESPC sur les activités logistiques et de rapportage *Coaching des gestionnaires des sites clients directs sur les activités logistiques et de rapportage *Echanges d'informations et suivi des activités de la chaîne d'approvisionnement *Echanges d'informations avec les prescripteurs et prises de décision sur les consommations de certains produits | O37: Compte-rendu de réunion de coordination | P37: Rapport trimestriel | Q37: Support and Assistance | R37: Meeting | S37: Sans budget | T37: 0 | V37: 0 | W37: 0 | X37: 0 | Y37: 0 | Z37: =SUM(T37:Y37) -> 0 | AF37: 1046600 | AI37: 1046600 | AR37: 1046600 | BP37: =T37-SUM(AA37,AD37,AG37,AJ37,AM37,AP37) -> 0 | BQ37: =U37-SUM(AS37,AV37,AZ37,BD37,BH37,BL37) -> 0 | BR37: =W37-SUM(AB37,AE37,AH37,AK37,AN37,AQ37,AT37,AW37,BA37,BE37,BI37,BM37) -> 0 | BS37: =X37-SUM(AC37,AF37,AI37,AL37,AO37,AR37,AU37,AX37,BB37,BF37,BJ37,BN37) -> -3139800
A38: OO 1.3 : Assister les régions, districts et hôpitaux de référence dans la gestion des stocks et la coordination des activités de la chaîne d’approvisionnement visant à accroître la disponibilité des produits au point de prestation de services | B38: 1.3-2 : Assister les régions, districts et hôpitaux dans la coordination des activités logistiquess et la prise de décisions | C38: LHSPLA assistera techniquement et financièrement les régions, districts et hôpitaux dans la mise en œuvre des activités logistiques. Dans ce cadre, des visites de sites, des réunions de coordination, des supervisions formatives, des formations et des coachings seront organisées avec l'appui de LHSPLA / LHSPLA will technically and financially assist regions, districts and hospitals in the implementation of logistics activities. In this context, site visits, coordination meetings, formative supervision, training and coaching will be organized with the support of LHSPLA. | D38: =TRIM(_xlfn.TEXTBEFORE(E38,":")) -> 1.3-2.9 | E38: 1.3-2.9 : Organiser deux atéliers de coordination avec les Pharmaciens de région, la DAP et les Programmes nationaux de santé | F38: CAD | G38: DAP | H38: PNS | I38: 45931 | J38: 46295 | K38: 100% des ateliers de coordination ont été réalisés | L38: 100% des acteurs des sites dont la performanceest inférieur aux objectifs ont été identifiés et sont accompagnés | N38: *Améliorer les activités de la chaîne d'approvisionnement *Contribuer à la mise à niveau des stocks des sites clients directs par région *Coaching des gestionnaires des ESPC sur les activités logistiques et de rapportage *Coaching des gestionnaires des sites clients directs sur les activités logistiques et de rapportage *Echanges d'informations et suivi des activités de la chaîne d'approvisionnement *Echanges d'informations avec les prescripteurs et prises de décision sur les consommations de certains produits | O38: Rapport d'atélier | P38: Rapport trimestriel | Q38: Support and Assistance | R38: Meeting | S38: il s'agira d'organiser deux atéliers pour chaque bureau CAD: Location de salle à Yammousoukro et Khorogo/ 02 (DAP), 03 (PNS), 01 (Agence Programme), 01 (DEX), 01 (QAD), 08 (CAD). Full perdiem sur 05 jours, Forfait transport et Forfait carburant. | V38: 0 | Y38: 29505554 | Z38: =SUM(T38:Y38) -> 29505554 | BC38: 29505554
A39: OO 1.4 : Assister les acteurs des districts, les acteurs des ESPC et les agents de santé communautaire dans le suivi du mécanisme permettant le suivi de la disponibilité des produits de santé communautaire | B39: 1.4-1 : Assister les districts dans la coordination des activités logistiques communautaires et la prise de décision | C39: LHSPLA assistera techniquement et financièrement les régions à travers les districts dans la mise en œuvre des activités communautaire. Dans ce cadre, des réunions de coordination, des formations et des visites/coachings des ESPC engagés dans la stratégie iCCM seront organisées avec l'appui de LHSPLA. Le volet communautaire du système d'alerte précoce sera renforcé avec l'appui de LHSPLA. | D39: =TRIM(_xlfn.TEXTBEFORE(E39,":")) -> 1.4-1.1 | E39: 1.4-1.1 : Organiser une réunion de coordination avec le PNLP, la DAP, la DSCPS, les Pharmaciens de région, les pharmaciens de 106 districts sur la chaîne d'approvisionnement des produits du programme | F39: CAD | G39: PNS | H39: PNLP | I39: 45931 | J39: 46295 | K39: 100% des informations clés sur les directives et stratégies du PNLP sont connues par tous les participants | L39: Prises de décision pour permettre de maintenir une disponibilité des produits de santé communautaire à au moins 95% | N39: Améliorer les activités de la chaîne d'approvisionnement Contribuer à la mise à niveau des stocks des ESPC par district sanitaire. Coaching des ASS et ASC sur les activités logistiques et de rapportage. | O39: Rapport de réunion | P39: Rapport trimestriel | Q39: Support and Assistance | R39: Support and Assistance | S39: Il s'agit d'une réunion en 4 sessions de 2 jours chacune. Cette réunion va regrouper 2 ONG, 33 Pharmaciens de Région, 1 représentant de la DAP, 1 représentant de la DSC, 6 représentants du PNLP, 4 représentants LHSPLA, 1 représentant de la DPAS et 106 représentants des districts engagés dans la stratégie iCCM. Chaque participant recevra le full perdiem sur 3 jours et les organisateurs (LHSPLA, DAP, DSC, DPAS et PNLP) un full perdiem sur 13 jours. Il y aura la location d'une salle de plus de 60 places pour les sessions, des pauses café et eau minérale chaque matin et chaque soir. Il y aura le forfait transport pour les participants et des forfait carburant et péage autoroute pour les CT LHSPLA, le DC et chef de département GAS du PNLP. Des frais de transfert de fonds sont prévus. | T39: 0 | U39: 0 | V39: 0 | W39: 33106606 | Y39: 0 | Z39: =SUM(T39:Y39) -> 33106606 | AE39: 32774682 | BP39: =T39-SUM(AA39,AD39,AG39,AJ39,AM39,AP39) -> 0 | BQ39: =U39-SUM(AS39,AV39,AZ39,BD39,BH39,BL39) -> 0 | BR39: =W39-SUM(AB39,AE39,AH39,AK39,AN39,AQ39,AT39,AW39,BA39,BE39,BI39,BM39) -> 331924 | BS39: =X39-SUM(AC39,AF39,AI39,AL39,AO39,AR39,AU39,AX39,BB39,BF39,BJ39,BN39) -> 0
A40: OO 1.4 : Assister les acteurs des districts, les acteurs des ESPC et les agents de santé communautaire dans le suivi du mécanisme permettant le suivi de la disponibilité des produits de santé communautaire | B40: 1.4-1 : Assister les districts dans la coordination des activités logistiques communautaires et la prise de décision | C40: LHSPLA assistera techniquement et financièrement les régions à travers les districts dans la mise en œuvre des activités communautaire. Dans ce cadre, des réunions de coordination, des formations et des visites/coachings des ESPC engagés dans la stratégie iCCM seront organisées avec l'appui de LHSPLA. Le volet communautaire du système d'alerte précoce sera renforcé avec l'appui de LHSPLA. | D40: =TRIM(_xlfn.TEXTBEFORE(E40,":")) -> 1.4-1.2 | E40: 1.4-1.2 : Organiser une réunion bilan avec les acteurs de la partie nationale sur les approvisionnements des produits de santé communautaire | F40: CAD | G40: DSC-PS | H40: DPAS | I40: 45931 | J40: 46295 | K40: 100% des participants sont au même niveau d'information sur les données de gestion des produits de santé communautaire au niveau national | L40: Prises de décision pour permettre de maintenir une disponibilité des produits de santé communautaire à au moins 95% | N40: Améliorer les activités de la chaîne d'approvisionnement Contribuer à la mise à niveau des stocks des ESPC par district sanitaire. Coaching des ASS et ASC sur les activités logistiques et de rapportage. | O40: Rapport de réunion | P40: Rapport trimestriel | Q40: Support and Assistance | R40: Support and Assistance | S40: Il s'agit d'une réunion d'un jour avec 30 partipants dont 25 acteurs hors NPSP. il est des forfaits transport, des pause café et la location d'une salle | T40: 0 | U40: 0 | V40: 0 | W40: 4711800 | Y40: 0 | Z40: =SUM(T40:Y40) -> 4711800 | BA40: 4711800 | BP40: =T40-SUM(AA40,AD40,AG40,AJ40,AM40,AP40) -> 0 | BQ40: =U40-SUM(AS40,AV40,AZ40,BD40,BH40,BL40) -> 0 | BR40: =W40-SUM(AB40,AE40,AH40,AK40,AN40,AQ40,AT40,AW40,BA40,BE40,BI40,BM40) -> 0 | BS40: =X40-SUM(AC40,AF40,AI40,AL40,AO40,AR40,AU40,AX40,BB40,BF40,BJ40,BN40) -> 0
A41: OO 1.4 : Assister les acteurs des districts, les acteurs des ESPC et les agents de santé communautaire dans le suivi du mécanisme permettant le suivi de la disponibilité des produits de santé communautaire | B41: 1.4-1 : Assister les districts dans la coordination des activités logistiques communautaires et la prise de décision | C41: LHSPLA assistera techniquement et financièrement les régions à travers les districts dans la mise en œuvre des activités communautaire. Dans ce cadre, des réunions de coordination, des formations et des visites/coachings des ESPC engagés dans la stratégie iCCM seront organisées avec l'appui de LHSPLA. Le volet communautaire du système d'alerte précoce sera renforcé avec l'appui de LHSPLA. | D41: =TRIM(_xlfn.TEXTBEFORE(E41,":")) -> 1.4-1.3 | E41: 1.4-1.3 : Apporter un appui technique et financier au district sanitaire pour le suivi de la gestion des produits de santé communautaire | F41: CAD | G41: DAP | H41: DPAS | I41: 45931 | J41: 46295 | K41: 93% des districts sanitaires font le suivi de la gestion des produits de santé communautaire | L41: Prises de décision pour permettre de maintenir une disponibilité des produits de santé communautaire à au moins 95% | N41: Améliorer les activités de la chaîne d'approvisionnement Contribuer à la mise à niveau des stocks des ESPC par district sanitaire. Coaching des ASS et ASC sur les activités logistiques et de rapportage. | O41: Rapport de la visite | P41: Rapport trimestriel | Q41: Support and Assistance | R41: Other : financial support for beneficiaries | S41: Sur deux trimestres, 60 pharmacies de district engagées dans la stratégie iCCM (soit 15 districts sanitaire par trimestre et par bureau décentralisé) organiseront, en collaboration avec le Coordonnateur des Activités Communautaire (CAC), une visite de suivi de la gestion des produits de santé communautaire auprès de 5 ESPC. Les membres de l' équipe du district (Gestionnaire de pharmacie et CAC) recevront chacun une collation de 10 000FCFA, et un forfait transport de 10 000FCFA par jour et pendant 5 jours. Dans chadque ESPC, l'Agent de Santé Superviseur (IDE ou la SFDE) et 4 ASC (ASC coach et 3 autres ASC) , recevront 10000 Fcfa chacun comme collation. Des frais de transferts de fonds sont également prévus. Enfin, Les membres de l'équipe CAD participeront à certaines visites, sur la base de critères de performances, afin de s'assurer du bon déroulement de l'activité sur le terrain. | T41: 0 | U41: 0 | V41: 0 | W41: 24453817 | Y41: 0 | Z41: =SUM(T41:Y41) -> 24453817 | AH41: 12226909 | AW41: 22738693 | BP41: =T41-SUM(AA41,AD41,AG41,AJ41,AM41,AP41) -> 0 | BQ41: =U41-SUM(AS41,AV41,AZ41,BD41,BH41,BL41) -> 0 | BR41: =W41-SUM(AB41,AE41,AH41,AK41,AN41,AQ41,AT41,AW41,BA41,BE41,BI41,BM41) -> -10511785 | BS41: =X41-SUM(AC41,AF41,AI41,AL41,AO41,AR41,AU41,AX41,BB41,BF41,BJ41,BN41) -> 0
